Workbook
Name SegmentaciónDeDatos_LLAVE_AUTO: #REF!
Name SegmentaciónDeDatos_LLAVE_AUTO: #REF!

Sheet UBER 2025
A1: SEM | B1: CONDUCTOR | C1: AUTO | D1: TAG | E1: SOCIO | F1: PLATAFORMA | G1: APP | H1: GANANCIA | I1: IMPUESTOS | J1: P. AJUSANT | K1: SEGURO | L1: EFECTIVO | M1: PAGO A TERCEROS | N1: TAG | O1: UBER tot | P1: RENTA | Q1: SEM PASADA | R1: FIANZA | S1: MULTA | T1: HOJALATERO | U1: DESCUENTOS | V1: FA | W1: TOTAL | X1: PAGOS | Y1: DEVOLUCIONES | Z1: PAGADO | AA1: ADEUDO | AB1: GANANCIAS TOTALES | AC1: COMENTARIOS
A2: 1 | B2: ADOLFO LOPEZ MARTINEZ | C2: AVEO|2021|OCRE|NEB156A | D2: OHLM023012552 | E2: ASHC | F2: IVETH | G2: UBER | H2: 1943.26 | I2: -16 | J2: 0 | K2: 0 | L2: -758.4 | M2: =-38.8652+32 -> -6.8652 | N2: 0 | O2: =SUM(H2:N2) -> 1161.9948 | P2: -2142.85 | Q2: 0 | R2: 0 | S2: 0 | T2: 0 | U2: 0 | V2: 0 | W2: =+O2+SUM(P2:V2) -> -980.8552 | X2: =IF(W2>=0,W2,0) -> 0 | Y2: =IF(W2<=0,W2,0) -> -980.8552 | Z2: 981 | AA2: =+Y2+Z2 -> 0.1448 | AB2: =+O2-X2+Z2+AA2 -> 2143.1396
A3: 1 | B3: ARACELI CASTILLO GUERRERO | C3: AVEO|2018|GRIS|X59AWG | D3: - | E3: ASHC | F3: ASHC | G3: UBER | H3: 6825.48 | I3: -448 | J3: 0 | K3: 0 | L3: -1537.44 | M3: -136.5096 | N3: 0 | O3: =SUM(H3:N3) -> 4703.5304 | P3: -2142.85 | Q3: 0 | R3: 0 | S3: 0 | T3: 0 | U3: 0 | V3: 0 | W3: =+O3+SUM(P3:V3) -> 2560.6804 | X3: =IF(W3>=0,W3,0) -> 2560.6804 | Y3: =IF(W3<=0,W3,0) -> 0 | Z3: 0 | AA3: =+Y3+Z3 -> 0 | AB3: =+O3-X3+Z3+AA3 -> 2142.85
A4: 1 | B4: CESAR PIÑA BARONA | C4: HYUNDAI|2022|PLATA|D40BKD | D4: OHLM023658024 | E4: ASHC | F4: IVETH | G4: UBER | H4: 0 | I4: 0 | J4: 0 | K4: 0 | L4: 0 | M4: 0 | N4: 0 | O4: =SUM(H4:N4) -> 0 | P4: -2142.85 | Q4: -67 | R4: 0 | S4: 0 | T4: 0 | U4: 0 | V4: 0 | W4: =+O4+SUM(P4:V4) -> -2209.85 | X4: =IF(W4>=0,W4,0) -> 0 | Y4: =IF(W4<=0,W4,0) -> -2209.85 | Z4: 2210 | AA4: =+Y4+Z4 -> 0.15 | AB4: =+O4-X4+Z4+AA4 -> 2210.15
A5: 1 | B5: CLAUDIA LEAÑOS | C5: KIA RIO|2017|ROJO|MYE912A | D5: - | E5: U64 | F5: ASHC | G5: UBER | H5: 3855.54 | I5: -30.4 | J5: 0 | K5: 0 | L5: -2145.89 | M5: -77.1108 | N5: 0 | O5: =SUM(H5:N5) -> 1602.1392 | P5: -2142.85 | Q5: -510.28 | R5: 0 | S5: 0 | T5: 0 | U5: 0 | V5: 0 | W5: =+O5+SUM(P5:V5) -> -1050.9908 | X5: =IF(W5>=0,W5,0) -> 0 | Y5: =IF(W5<=0,W5,0) -> -1050.9908 | Z5: 1051 | AA5: =+Y5+Z5 -> 0.0092 | AB5: =+O5-X5+Z5+AA5 -> 2653.1484
A6: 1 | B6: IVAN MOGUEL PULIDO | C6: VERSA|2023|PLATA|NCT814A | D6: OHLM023012487 | E6: ASHC | F6: ASHC | G6: UBER | H6: 3884.89 | I6: 0 | J6: 0 | K6: 0 | L6: -2355.1 | M6: -90.2478 | N6: -70.97 | O6: =SUM(H6:N6) -> 1368.5722 | P6: -714.28 | Q6: 0 | R6: 0 | S6: 0 | T6: -500 | U6: 0 | V6: 0 | W6: =+O6+SUM(P6:V6) -> 154.2922 | X6: =IF(W6>=0,W6,0) -> 154.2922 | Y6: =IF(W6<=0,W6,0) -> 0 | Z6: 0 | AA6: =+Y6+Z6 -> 0 | AB6: =+O6-X6+Z6+AA6 -> 1214.28
A7: 1 | B7: JESUS AURELIO NUNGARAY CASTILLO | C7: VENTO|2020|GRIS|R66BER | D7: - | E7: ASHC | F7: ASHC | G7: UBER | H7: 4885.68 | I7: 0 | J7: 0 | K7: 0 | L7: -2620.14 | M7: -97.7136 | N7: 0 | O7: =SUM(H7:N7) -> 2167.8264 | P7: -2142.85 | Q7: -683.71 | R7: 0 | S7: 0 | T7: 0 | U7: 0 | V7: 0 | W7: =+O7+SUM(P7:V7) -> -658.7336 | X7: =IF(W7>=0,W7,0) -> 0 | Y7: =IF(W7<=0,W7,0) -> -658.7336 | Z7: 659 | AA7: =+Y7+Z7 -> 0.2664 | AB7: =+O7-X7+Z7+AA7 -> 2827.0928
A8: 1 | B8: JORGE VAZQUEZ HERNANDEZ | C8: AVEO|2018|GRIS|X59AWG | D8: - | E8: ASHC | F8: ASHC | G8: UBER | H8: 9781.33 | I8: 0 | J8: 0 | K8: 0 | L8: -4655.05 | M8: -195.6266 | N8: 0 | O8: =SUM(H8:N8) -> 4930.6534 | P8: -2142.85 | Q8: 0 | R8: 0 | S8: 0 | T8: 0 | U8: 0 | V8: 0 | W8: =+O8+SUM(P8:V8) -> 2787.8034 | X8: =IF(W8>=0,W8,0) -> 2787.8034 | Y8: =IF(W8<=0,W8,0) -> 0 | Z8: 0 | AA8: =+Y8+Z8 -> 0 | AB8: =+O8-X8+Z8+AA8 -> 2142.85
A9: 1 | B9: JOSE GUADALUPE GARCIA MORALES | C9: MARCH|2020|TURQ|N15BKD | D9: OHLM031409071 | E9: ASHC | F9: ASHC | G9: UBER | H9: 5089.85 | I9: -24 | J9: 0 | K9: 0 | L9: -3520.73 | M9: =-101.797+48 -> -53.797 | N9: 0 | O9: =SUM(H9:N9) -> 1491.323 | P9: -2142.85 | Q9: 0 | R9: -500 | S9: 0 | T9: 0 | U9: 0 | V9: 0 | W9: =+O9+SUM(P9:V9) -> -1151.527 | X9: =IF(W9>=0,W9,0) -> 0 | Y9: =IF(W9<=0,W9,0) -> -1151.527 | Z9: 1152 | AA9: =+Y9+Z9 -> 0.473 | AB9: =+O9-X9+Z9+AA9 -> 2643.796
A10: 1 | B10: JOSE JUAN HERNANDEZ MEJIA | C10: VERSA|2017|ACERO|X24APU | D10: OHLM023720345 | E10: ASHC | F10: ASHC | G10: UBER | H10: 4940.33 | I10: -38.4 | J10: 0 | K10: 0 | L10: -2048.73 | M10: =-98.8066+77 -> -21.8066 | N10: 0 | O10: =SUM(H10:N10) -> 2831.3934 | P10: -2142.85 | Q10: -375.31 | R10: -500 | S10: 0 | T10: 0 | U10: 0 | V10: 0 | W10: =+O10+SUM(P10:V10) -> -186.7666 | X10: =IF(W10>=0,W10,0) -> 0 | Y10: =IF(W10<=0,W10,0) -> -186.7666 | Z10: 187 | AA10: =+Y10+Z10 -> 0.2334 | AB10: =+O10-X10+Z10+AA10 -> 3018.6268
A11: 1 | B11: OSCAR BLANCAS NORIEGA | C11: VENTO|2017|GRIS|NZV7888 | D11: OHLM023720279 | E11: ASHC | F11: ASHC | G11: UBER | H11: 4068.3 | I11: -38.4 | J11: 0 | K11: 0 | L11: -935.09 | M11: =-81.366+77 -> -4.366 | N11: 0 | O11: =SUM(H11:N11) -> 3090.444 | P11: -1971.42 | Q11: -1063 | R11: -500 | S11: 0 | T11: 0 | U11: 0 | V11: 0 | W11: =+O11+SUM(P11:V11) -> -443.976 | X11: =IF(W11>=0,W11,0) -> 0 | Y11: =IF(W11<=0,W11,0) -> -443.976 | Z11: 444 | AA11: =+Y11+Z11 -> 0.024 | AB11: =+O11-X11+Z11+AA11 -> 3534.468
A12: 1 | B12: ULISES ITIEL CASTILLO AVILA | C12: KIA RIO|2020|GRIS|NCK475B | D12: OHLM031397326 | E12: ASHC | F12: IVETH | G12: UBER | H12: 5393.23 | I12: -68.8 | J12: 0 | K12: 0 | L12: -2447.29 | M12: -107.8646 | N12: 0 | O12: =SUM(H12:N12) -> 2769.2754 | P12: -2142.85 | Q12: 0 | R12: 0 | S12: 0 | T12: 0 | U12: 0 | V12: 0 | W12: =+O12+SUM(P12:V12) -> 626.4254 | X12: =IF(W12>=0,W12,0) -> 626.4254 | Y12: =IF(W12<=0,W12,0) -> 0 | Z12: 0 | AA12: =+Y12+Z12 -> 0 | AB12: =+O12-X12+Z12+AA12 -> 2142.85
A13: 2 | B13: ABRAHAM ESCOBEDO ESCALANTE | C13: BEAT|2020|GRIS|NFN014B | D13: - | E13: U64 | F13: ASHC | G13: UBER | H13: 1382.8 | I13: -22.4 | J13: 0 | K13: 0 | L13: -723.89 | M13: -27.656 | N13: 0 | O13: =SUM(H13:N13) -> 608.854 | P13: -1428.56 | Q13: 0 | R13: 0 | S13: 0 | T13: 0 | U13: 0 | V13: 0 | W13: =+O13+SUM(P13:V13) -> -819.706 | X13: =IF(W13>=0,W13,0) -> 0 | Y13: =IF(W13<=0,W13,0) -> -819.706 | Z13: 0 | AA13: =+Y13+Z13 -> -819.706 | AB13: =+O13-X13+Z13+AA13 -> -210.852 | AC13: PÉRDIDA
A14: 2 | B14: ADOLFO LOPEZ MARTINEZ | C14: AVEO|2021|OCRE|NEB156A | D14: OHLM023012552 | E14: ASHC | F14: IVETH | G14: UBER | H14: 0 | I14: 0 | J14: 0 | K14: 0 | L14: 0 | M14: 0 | N14: 0 | O14: =SUM(H14:N14) -> 0 | P14: -2500 | Q14: 0 | R14: 0 | S14: 0 | T14: 0 | U14: 0 | V14: 0 | W14: =+O14+SUM(P14:V14) -> -2500 | X14: =IF(W14>=0,W14,0) -> 0 | Y14: =IF(W14<=0,W14,0) -> -2500 | Z14: 2500 | AA14: =+Y14+Z14 -> 0 | AB14: =+O14-X14+Z14+AA14 -> 2500
A15: 2 | B15: ARACELI CASTILLO GUERRERO | C15: AVEO|2018|GRIS|X59AWG | D15: - | E15: ASHC | F15: ASHC | G15: UBER | H15: 3130.3 | I15: 0 | J15: 0 | K15: 0 | L15: -1220.45 | M15: -62.606 | N15: 0 | O15: =SUM(H15:N15) -> 1847.244 | P15: -2500 | Q15: 0 | R15: 0 | S15: 0 | T15: 0 | U15: 0 | V15: 0 | W15: =+O15+SUM(P15:V15) -> -652.756 | X15: =IF(W15>=0,W15,0) -> 0 | Y15: =IF(W15<=0,W15,0) -> -652.756 | Z15: 653 | AA15: =+Y15+Z15 -> 0.244 | AB15: =+O15-X15+Z15+AA15 -> 2500.488
A16: 2 | B16: CESAR PIÑA BARONA | C16: HYUNDAI|2022|PLATA|D40BKD | D16: OHLM023658024 | E16: ASHC | F16: IVETH | G16: UBER | H16: 0 | I16: 0 | J16: 0 | K16: 0 | L16: 0 | M16: 0 | N16: 0 | O16: =SUM(H16:N16) -> 0 | P16: -2500 | Q16: 0 | R16: 0 | S16: 0 | T16: 0 | U16: 0 | V16: 0 | W16: =+O16+SUM(P16:V16) -> -2500 | X16: =IF(W16>=0,W16,0) -> 0 | Y16: =IF(W16<=0,W16,0) -> -2500 | Z16: 2500 | AA16: =+Y16+Z16 -> 0 | AB16: =+O16-X16+Z16+AA16 -> 2500
A17: 2 | B17: CLAUDIA LEAÑOS | C17: KIA RIO|2017|ROJO|MYE912A | D17: - | E17: U64 | F17: ASHC | G17: UBER | H17: 3759.89 | I17: -60.8 | J17: 0 | K17: 0 | L17: -1578.07 | M17: -75.1978 | N17: 0 | O17: =SUM(H17:N17) -> 2045.8222 | P17: -2500 | Q17: 0 | R17: 0 | S17: 0 | T17: 0 | U17: 0 | V17: 0 | W17: =+O17+SUM(P17:V17) -> -454.1778 | X17: =IF(W17>=0,W17,0) -> 0 | Y17: =IF(W17<=0,W17,0) -> -454.1778 | Z17: 0 | AA17: =+Y17+Z17 -> -454.1778 | AB17: =+O17-X17+Z17+AA17 -> 1591.6444 | AC17: PÉRDIDA
A18: 2 | B18: DIEGO SANCHEZ | C18: VENTO|2020|GRIS|R66BER | D18: OHLM023720329 | E18: ASHC | F18: ASHC | G18: UBER | H18: 2574.35 | I18: 0 | J18: 0 | K18: 0 | L18: -1659.48 | M18: -51.487 | N18: 0 | O18: =SUM(H18:N18) -> 863.383 | P18: -1428.56 | Q18: 0 | R18: -500 | S18: 0 | T18: 0 | U18: 0 | V18: 0 | W18: =+O18+SUM(P18:V18) -> -1065.177 | X18: =IF(W18>=0,W18,0) -> 0 | Y18: =IF(W18<=0,W18,0) -> -1065.177 | Z18: 1065 | AA18: =+Y18+Z18 -> -0.177 | AB18: =+O18-X18+Z18+AA18 -> 1928.206
A19: 2 | B19: EDGAR GEOVANY URIBE | C19: AVEO|2019|PLATA|NEL860A | D19: OHLM023720337 | E19: ASHC | F19: ASHC | G19: UBER | H19: 4536.98 | I19: -119.2 | J19: 0 | K19: 0 | L19: -898.58 | M19: -113.3596 | N19: 0 | O19: =SUM(H19:N19) -> 3405.8404 | P19: -2500 | Q19: 0 | R19: 0 | S19: -500 | T19: 0 | U19: 0 | V19: 0 | W19: =+O19+SUM(P19:V19) -> 405.8404 | X19: =IF(W19>=0,W19,0) -> 405.8404 | Y19: =IF(W19<=0,W19,0) -> 0 | Z19: 0 | AA19: =+Y19+Z19 -> 0 | AB19: =+O19-X19+Z19+AA19 -> 3000
A20: 2 | B20: IRAM HERNANDEZ | C20: AVEO|2022|AZUL|MUF515A | D20: OHLM023720311 | E20: ASHC | F20: ASHC | G20: UBER | H20: 6165.24 | I20: 0 | J20: 0 | K20: 0 | L20: -2465.51 | M20: -123.3048 | N20: 0 | O20: =SUM(H20:N20) -> 3576.4252 | P20: -2500 | Q20: 0 | R20: 0 | S20: -500 | T20: 0 | U20: 0 | V20: 0 | W20: =+O20+SUM(P20:V20) -> 576.4252 | X20: =IF(W20>=0,W20,0) -> 576.4252 | Y20: =IF(W20<=0,W20,0) -> 0 | Z20: 0 | AA20: =+Y20+Z20 -> 0 | AB20: =+O20-X20+Z20+AA20 -> 3000
A21: 2 | B21: IVAN MOGUEL PULIDO | C21: VERSA|2023|PLATA|NCT814A | D21: OHLM023012487 | E21: ASHC | F21: ASHC | G21: UBER | H21: 11072.8 | I21: -262.4 | J21: 0 | K21: 0 | L21: -4296.05 | M21: -221.456 | N21: -46 | O21: =SUM(H21:N21) -> 6246.894 | P21: -2500 | Q21: 0 | R21: 0 | S21: 0 | T21: -500 | U21: 0 | V21: 0 | W21: =+O21+SUM(P21:V21) -> 3246.894 | X21: =IF(W21>=0,W21,0) -> 3246.894 | Y21: =IF(W21<=0,W21,0) -> 0 | Z21: 0 | AA21: =+Y21+Z21 -> 0 | AB21: =+O21-X21+Z21+AA21 -> 3000
A22: 2 | B22: JESUS AURELIO NUNGARAY CASTILLO | C22: VENTO|2020|GRIS|R66BER | D22: - | E22: ASHC | F22: ASHC | G22: UBER | H22: 2251.02 | I22: 0 | J22: 0 | K22: 0 | L22: -1814.27 | M22: -45.0204 | N22: -127.82 | O22: =SUM(H22:N22) -> 263.9096 | P22: -714.28 | Q22: 0 | R22: 0 | S22: 0 | T22: 0 | U22: 0 | V22: 0 | W22: =+O22+SUM(P22:V22) -> -450.3704 | X22: =IF(W22>=0,W22,0) -> 0 | Y22: =IF(W22<=0,W22,0) -> -450.3704 | Z22: 450 | AA22: =+Y22+Z22 -> -0.3704 | AB22: =+O22-X22+Z22+AA22 -> 713.5392
A23: 2 | B23: JORGE VAZQUEZ HERNANDEZ | C23: AVEO|2018|GRIS|X59AWG | D23: - | E23: ASHC | F23: ASHC | G23: UBER | H23: 3233.43 | I23: 0 | J23: 0 | K23: 0 | L23: -628.14 | M23: -64.6686 | N23: 0 | O23: =SUM(H23:N23) -> 2540.6214 | P23: -2500 | Q23: 0 | R23: 0 | S23: 0 | T23: 0 | U23: 0 | V23: 0 | W23: =+O23+SUM(P23:V23) -> 40.6214 | X23: =IF(W23>=0,W23,0) -> 40.6214 | Y23: =IF(W23<=0,W23,0) -> 0 | Z23: 0 | AA23: =+Y23+Z23 -> 0 | AB23: =+O23-X23+Z23+AA23 -> 2500
A24: 2 | B24: JOSE GUADALUPE GARCIA MORALES | C24: MARCH|2020|TURQ|N15BKD | D24: OHLM031409071 | E24: ASHC | F24: ASHC | G24: UBER | H24: 5208.21 | I24: 0 | J24: 0 | K24: 0 | L24: -3087.32 | M24: -104.1642 | N24: 0 | O24: =SUM(H24:N24) -> 2016.7258 | P24: -2500 | Q24: -1151.53 | R24: -500 | S24: 0 | T24: 0 | U24: 0 | V24: 0 | W24: =+O24+SUM(P24:V24) -> -2134.8042 | X24: =IF(W24>=0,W24,0) -> 0 | Y24: =IF(W24<=0,W24,0) -> -2134.8042 | Z24: 2135 | AA24: =+Y24+Z24 -> 0.1958 | AB24: =+O24-X24+Z24+AA24 -> 4151.9216
A25: 2 | B25: JOSE GUILLERMO HERNANDEZ RAMIREZ | C25: AVEO|2018|ROJO|R51BKD | D25: OHLM017365206 | E25: U64 | F25: ASHC | G25: UBER | H25: 6685.99 | I25: -164.8 | J25: 0 | K25: 0 | L25: -3647.5 | M25: -133.7198 | N25: 0 | O25: =SUM(H25:N25) -> 2739.9702 | P25: -2500 | Q25: 0 | R25: 0 | S25: 0 | T25: 0 | U25: 0 | V25: 0 | W25: =+O25+SUM(P25:V25) -> 239.9702 | X25: =IF(W25>=0,W25,0) -> 239.9702 | Y25: =IF(W25<=0,W25,0) -> 0 | Z25: 0 | AA25: =+Y25+Z25 -> 0 | AB25: =+O25-X25+Z25+AA25 -> 2500
A26: 2 | B26: JOSE JUAN HERNANDEZ MEJIA | C26: VERSA|2017|ACERO|X24APU | D26: OHLM023720345 | E26: ASHC | F26: ASHC | G26: UBER | H26: 3188.12 | I26: -48 | J26: 0 | K26: 0 | L26: -1867.2 | M26: -63.7624 | N26: 0 | O26: =SUM(H26:N26) -> 1209.1576 | P26: -2500 | Q26: -186.97 | R26: -500 | S26: 0 | T26: 0 | U26: 0 | V26: 0 | W26: =+O26+SUM(P26:V26) -> -1977.8124 | X26: =IF(W26>=0,W26,0) -> 0 | Y26: =IF(W26<=0,W26,0) -> -1977.8124 | Z26: 1882 | AA26: =+Y26+Z26 -> -95.8124 | AB26: =+O26-X26+Z26+AA26 -> 2995.3452
A27: 2 | B27: OSCAR BLANCAS NORIEGA | C27: VENTO|2017|GRIS|NZV7888 | D27: OHLM023720279 | E27: ASHC | F27: ASHC | G27: UBER | H27: 4151.87 | I27: -81.6 | J27: 0 | K27: 0 | L27: -1247.87 | M27: -83.0374 | N27: 0 | O27: =SUM(H27:N27) -> 2739.3626 | P27: -2300 | Q27: 0 | R27: -339 | S27: -257 | T27: 0 | U27: 0 | V27: 0 | W27: =+O27+SUM(P27:V27) -> -156.6374 | X27: =IF(W27>=0,W27,0) -> 0 | Y27: =IF(W27<=0,W27,0) -> -156.6374 | Z27: 157 | AA27: =+Y27+Z27 -> 0.3626 | AB27: =+O27-X27+Z27+AA27 -> 2896.7252
A28: 2 | B28: ULISES ITIEL CASTILLO AVILA | C28: KIA RIO|2020|GRIS|NCK475B | D28: OHLM031397326 | E28: ASHC | F28: IVETH | G28: UBER | H28: 7618.92 | I28: -139.2 | J28: 0 | K28: 0 | L28: -4430.72 | M28: -152.3784 | N28: 0 | O28: =SUM(H28:N28) -> 2896.6216 | P28: -2500 | Q28: 0 | R28: 0 | S28: 0 | T28: 0 | U28: 0 | V28: 0 | W28: =+O28+SUM(P28:V28) -> 396.6216 | X28: =IF(W28>=0,W28,0) -> 396.6216 | Y28: =IF(W28<=0,W28,0) -> 0 | Z28: 0 | AA28: =+Y28+Z28 -> 0 | AB28: =+O28-X28+Z28+AA28 -> 2500
A29: 3 | B29: ABRAHAM ESCOBEDO ESCALANTE | C29: BEAT|2020|GRIS|NFN014B | D29: - | E29: U64 | F29: ASHC | G29: UBER | H29: 2639.76 | I29: 0 | J29: 0 | K29: 0 | L29: -2186.24 | M29: -52.7952 | N29: 0 | O29: =SUM(H29:N29) -> 400.7248 | P29: -2500 | Q29: -35 | R29: 0 | S29: 0 | T29: 0 | U29: 0 | V29: 0 | W29: =+O29+SUM(P29:V29) -> -2134.2752 | X29: =IF(W29>=0,W29,0) -> 0 | Y29: =IF(W29<=0,W29,0) -> -2134.2752 | Z29: 0 | AA29: =+Y29+Z29 -> -2134.2752 | AB29: =+O29-X29+Z29+AA29 -> -1733.5504 | AC29: PÉRDIDA
A30: 3 | B30: ADOLFO LOPEZ MARTINEZ | C30: AVEO|2021|OCRE|NEB156A | D30: OHLM023012552 | E30: ASHC | F30: ASHC | G30: UBER | H30: 50.31 | I30: 0 | J30: 0 | K30: 0 | L30: 0 | M30: 0 | N30: 0 | O30: =SUM(H30:N30) -> 50.31 | P30: -1071 | Q30: 0 | R30: 0 | S30: 0 | T30: 0 | U30: 0 | V30: 0 | W30: =+O30+SUM(P30:V30) -> -1020.69 | X30: =IF(W30>=0,W30,0) -> 0 | Y30: =IF(W30<=0,W30,0) -> -1020.69 | Z30: 1021 | AA30: =+Y30+Z30 -> 0.31 | AB30: =+O30-X30+Z30+AA30 -> 1071.62
A31: 3 | B31: ADOLFO LOPEZ MARTINEZ | C31: AVEO|2021|OCRE|NEB156A | D31: OHLM023012552 | E31: ASHC | F31: IVETH | G31: UBER | H31: 1787.03 | I31: 0 | J31: 0 | K31: 0 | L31: -586.14 | M31: -35.7406 | N31: 0 | O31: =SUM(H31:N31) -> 1165.1494 | P31: -1429 | Q31: 0 | R31: 0 | S31: 0 | T31: 0 | U31: 0 | V31: 0 | W31: =+O31+SUM(P31:V31) -> -263.8506 | X31: =IF(W31>=0,W31,0) -> 0 | Y31: =IF(W31<=0,W31,0) -> -263.8506 | Z31: 264 | AA31: =+Y31+Z31 -> 0.1494 | AB31: =+O31-X31+Z31+AA31 -> 1429.2988
A32: 3 | B32: ARACELI CASTILLO GUERRERO | C32: AVEO|2018|GRIS|X59AWG | D32: - | E32: ASHC | F32: ASHC | G32: UBER | H32: 3737.75 | I32: 0 | J32: 0 | K32: 0 | L32: -1707.4 | M32: -74.755 | N32: 0 | O32: =SUM(H32:N32) -> 1955.595 | P32: -2500 | Q32: 0 | R32: 0 | S32: 0 | T32: 0 | U32: 0 | V32: 0 | W32: =+O32+SUM(P32:V32) -> -544.405 | X32: =IF(W32>=0,W32,0) -> 0 | Y32: =IF(W32<=0,W32,0) -> -544.405 | Z32: 544 | AA32: =+Y32+Z32 -> -0.405 | AB32: =+O32-X32+Z32+AA32 -> 2499.19
A33: 3 | B33: CESAR PIÑA BARONA | C33: HYUNDAI|2022|PLATA|D40BKD | D33: OHLM023658024 | E33: ASHC | F33: ASHC | G33: UBER | H33: 0 | I33: 0 | J33: 0 | K33: 0 | L33: 0 | M33: 0 | N33: 0 | O33: =SUM(H33:N33) -> 0 | P33: -1071 | Q33: -1300 | R33: 0 | S33: 0 | T33: 0 | U33: 0 | V33: 0 | W33: =+O33+SUM(P33:V33) -> -2371 | X33: =IF(W33>=0,W33,0) -> 0 | Y33: =IF(W33<=0,W33,0) -> -2371 | Z33: 2371 | AA33: =+Y33+Z33 -> 0 | AB33: =+O33-X33+Z33+AA33 -> 2371 | AC33: PAGADO
A34: 3 | B34: CESAR PIÑA BARONA | C34: HYUNDAI|2022|PLATA|D40BKD | D34: OHLM023658024 | E34: ASHC | F34: IVETH | G34: UBER | H34: 0 | I34: 0 | J34: 0 | K34: 0 | L34: 0 | M34: 0 | N34: 0 | O34: =SUM(H34:N34) -> 0 | P34: -1429 | Q34: 0 | R34: 0 | S34: 0 | T34: 0 | U34: 0 | V34: 0 | W34: =+O34+SUM(P34:V34) -> -1429 | X34: =IF(W34>=0,W34,0) -> 0 | Y34: =IF(W34<=0,W34,0) -> -1429 | Z34: 1429 | AA34: =+Y34+Z34 -> 0 | AB34: =+O34-X34+Z34+AA34 -> 1429 | AC34: PAGADO
A35: 3 | B35: CLAUDIA LEAÑOS | C35: KIA RIO|2017|ROJO|MYE912A | D35: - | E35: U64 | F35: ASHC | G35: UBER | H35: 449.82 | I35: 0 | J35: 0 | K35: 0 | L35: -93.56 | M35: 0 | N35: 0 | O35: =SUM(H35:N35) -> 356.26 | P35: 0 | Q35: 0 | R35: 0 | S35: 0 | T35: 0 | U35: 0 | V35: 0 | W35: =+O35+SUM(P35:V35) -> 356.26 | X35: =IF(W35>=0,W35,0) -> 356.26 | Y35: =IF(W35<=0,W35,0) -> 0 | Z35: 0 | AA35: =+Y35+Z35 -> 0 | AB35: =+O35-X35+Z35+AA35 -> 0
A36: 3 | B36: DIEGO SANCHEZ | C36: VENTO|2020|GRIS|R66BER | D36: OHLM023720329 | E36: ASHC | F36: ASHC | G36: UBER | H36: 4532.44 | I36: 0 | J36: 0 | K36: 0 | L36: -2041.45 | M36: -101.0688 | N36: 0 | O36: =SUM(H36:N36) -> 2389.9212 | P36: -2500 | Q36: 0 | R36: -500 | S36: 0 | T36: 0 | U36: 0 | V36: 0 | W36: =+O36+SUM(P36:V36) -> -610.0788 | X36: =IF(W36>=0,W36,0) -> 0 | Y36: =IF(W36<=0,W36,0) -> -610.0788 | Z36: 620 | AA36: =+Y36+Z36 -> 9.9212 | AB36: =+O36-X36+Z36+AA36 -> 3019.8424 | AC36: PAGADO | 21 ENE
A37: 3 | B37: EDGAR GEOVANY URIBE | C37: AVEO|2019|PLATA|NEL860A | D37: OHLM023720337 | E37: ASHC | F37: ASHC | G37: UBER | H37: 5544.83 | I37: -101.6 | J37: 0 | K37: 0 | L37: -1756.2 | M37: -137.71245 | N37: 0 | O37: =SUM(H37:N37) -> 3549.3175 | P37: -2500 | Q37: 0 | R37: 0 | S37: -500 | T37: 0 | U37: 0 | V37: 0 | W37: =+O37+SUM(P37:V37) -> 549.31755 | X37: =IF(W37>=0,W37,0) -> 549.31755 | Y37: =IF(W37<=0,W37,0) -> 0 | Z37: 0 | AA37: =+Y37+Z37 -> 0 | AB37: =+O37-X37+Z37+AA37 -> 3000
A38: 3 | B38: FERNANDO ESQUIVEL SOSA | C38: VENTO|2018|AMARILLO|PED1652 | D38: OHLM031409055 | E38: ASHC | F38: ASHC | G38: UBER | H38: 7403.76 | I38: -138.4 | J38: 0 | K38: 0 | L38: -1056.42 | M38: -148.0752 | N38: 0 | O38: =SUM(H38:N38) -> 6060.8648 | P38: -1968 | Q38: 0 | R38: -500 | S38: 0 | T38: 0 | U38: 0 | V38: 0 | W38: =+O38+SUM(P38:V38) -> 3592.8648 | X38: =IF(W38>=0,W38,0) -> 3592.8648 | Y38: =IF(W38<=0,W38,0) -> 0 | Z38: 0 | AA38: =+Y38+Z38 -> 0 | AB38: =+O38-X38+Z38+AA38 -> 2468
A39: 3 | B39: IRAM HERNANDEZ | C39: AVEO|2022|AZUL|MUF515A | D39: OHLM023720311 | E39: ASHC | F39: ASHC | G39: UBER | H39: 5136.53 | I39: -54.31 | J39: 0 | K39: 0 | L39: -1437.61 | M39: -77.04795 | N39: -55 | O39: =SUM(H39:N39) -> 3512.562 | P39: -2500 | Q39: 0 | R39: 0 | S39: -300 | T39: 0 | U39: 0 | V39: 0 | W39: =+O39+SUM(P39:V39) -> 712.56205 | X39: =IF(W39>=0,W39,0) -> 712.56205 | Y39: =IF(W39<=0,W39,0) -> 0 | Z39: 0 | AA39: =+Y39+Z39 -> 0 | AB39: =+O39-X39+Z39+AA39 -> 2800
A40: 3 | B40: IVAN MOGUEL PULIDO | C40: VERSA|2023|PLATA|NCT814A | D40: OHLM023012487 | E40: ASHC | F40: ASHC | G40: UBER | H40: 9859.83 | I40: -121.6 | J40: 0 | K40: 0 | L40: -4486.28 | M40: -197.1966 | N40: -217.97 | O40: =SUM(H40:N40) -> 4836.7834 | P40: -2500 | Q40: -1500 | R40: 0 | S40: 0 | T40: -500 | U40: 0 | V40: 0 | W40: =+O40+SUM(P40:V40) -> 336.7834 | X40: =IF(W40>=0,W40,0) -> 336.7834 | Y40: =IF(W40<=0,W40,0) -> 0 | Z40: 0 | AA40: =+Y40+Z40 -> 0 | AB40: =+O40-X40+Z40+AA40 -> 4500
A41: 3 | B41: JORGE VAZQUEZ HERNANDEZ | C41: AVEO|2018|GRIS|X59AWG | D41: - | E41: ASHC | F41: ASHC | G41: UBER | H41: 861.11 | I41: 0 | J41: 0 | K41: 0 | L41: -251.63 | M41: -17.2222 | N41: 0 | O41: =SUM(H41:N41) -> 592.2578 | P41: -357.15 | Q41: 0 | R41: 0 | S41: 0 | T41: 0 | U41: 0 | V41: 0 | W41: =+O41+SUM(P41:V41) -> 235.1078 | X41: =IF(W41>=0,W41,0) -> 235.1078 | Y41: =IF(W41<=0,W41,0) -> 0 | Z41: 0 | AA41: =+Y41+Z41 -> 0 | AB41: =+O41-X41+Z41+AA41 -> 357.15
A42: 3 | B42: JOSE GUADALUPE GARCIA MORALES | C42: MARCH|2020|TURQ|N15BKD | D42: OHLM031409071 | E42: ASHC | F42: ASHC | G42: UBER | H42: 5945.25 | I42: 0 | J42: 0 | K42: 0 | L42: -2654.06 | M42: -90.41875 | N42: 0 | O42: =SUM(H42:N42) -> 3200.7713 | P42: -2500 | Q42: -1153 | R42: 0 | S42: 0 | T42: 0 | U42: 0 | V42: 0 | W42: =+O42+SUM(P42:V42) -> -452.22875 | X42: =IF(W42>=0,W42,0) -> 0 | Y42: =IF(W42<=0,W42,0) -> -452.22875 | Z42: 453 | AA42: =+Y42+Z42 -> 0.77125 | AB42: =+O42-X42+Z42+AA42 -> 3654.5425
A43: 3 | B43: JOSE GUILLERMO HERNANDEZ RAMIREZ | C43: AVEO|2018|ROJO|R51BKD | D43: OHLM017365206 | E43: U64 | F43: ASHC | G43: UBER | H43: 7475.53 | I43: -199.2 | J43: 0 | K43: 0 | L43: -3393.99 | M43: -149.5106 | N43: 0 | O43: =SUM(H43:N43) -> 3732.8294 | P43: -2500 | Q43: 0 | R43: 0 | S43: 0 | T43: -500 | U43: 0 | V43: 0 | W43: =+O43+SUM(P43:V43) -> 732.8294 | X43: =IF(W43>=0,W43,0) -> 732.8294 | Y43: =IF(W43<=0,W43,0) -> 0 | Z43: 0 | AA43: =+Y43+Z43 -> 0 | AB43: =+O43-X43+Z43+AA43 -> 3000
A44: 3 | B44: JOSE JUAN HERNANDEZ MEJIA | C44: VERSA|2017|ACERO|X24APU | D44: OHLM023720345 | E44: ASHC | F44: ASHC | G44: UBER | H44: 4692.05 | I44: 0 | J44: 0 | K44: 0 | L44: -2385.04 | M44: -70.38075 | N44: 0 | O44: =SUM(H44:N44) -> 2236.6293 | P44: -2500 | Q44: -559 | R44: -500 | S44: 0 | T44: 0 | U44: 0 | V44: 0 | W44: =+O44+SUM(P44:V44) -> -1322.3707 | X44: =IF(W44>=0,W44,0) -> 0 | Y44: =IF(W44<=0,W44,0) -> -1322.3707 | Z44: 1322 | AA44: =+Y44+Z44 -> -0.37075 | AB44: =+O44-X44+Z44+AA44 -> 3558.2585
A45: 3 | B45: JUAN CARLOS MUÑOZ | C45: AVEO|2019|BLANCO|NBS225A | D45: OHLM023720287 | E45: ASHC | F45: IVETH | G45: UBER | H45: 3798.92 | I45: 0 | J45: 0 | K45: 0 | L45: -2545.8 | M45: -71.8792 | N45: 0 | O45: =SUM(H45:N45) -> 1181.2408 | P45: -1252 | Q45: 0 | R45: 0 | S45: 0 | T45: 0 | U45: 0 | V45: 0 | W45: =+O45+SUM(P45:V45) -> -70.7592 | X45: =IF(W45>=0,W45,0) -> 0 | Y45: =IF(W45<=0,W45,0) -> -70.7592 | Z45: 105 | AA45: =+Y45+Z45 -> 34.2408 | AB45: =+O45-X45+Z45+AA45 -> 1320.4816
A46: 3 | B46: OSCAR BLANCAS NORIEGA | C46: VENTO|2017|GRIS|NZV7888 | D46: OHLM023720279 | E46: ASHC | F46: ASHC | G46: UBER | H46: 4987.69 | I46: -61.6 | J46: 0 | K46: 0 | L46: -2062.35 | M46: -74.81535 | N46: -97 | O46: =SUM(H46:N46) -> 2691.9246 | P46: -2300 | Q46: 0 | R46: 0 | S46: -500 | T46: 0 | U46: 0 | V46: 0 | W46: =+O46+SUM(P46:V46) -> -108.07535 | X46: =IF(W46>=0,W46,0) -> 0 | Y46: =IF(W46<=0,W46,0) -> -108.07535 | Z46: 108 | AA46: =+Y46+Z46 -> -0.07535 | AB46: =+O46-X46+Z46+AA46 -> 2799.8493
A47: 3 | B47: ULISES ITIEL CASTILLO AVILA | C47: KIA RIO|2020|GRIS|NCK475B | D47: OHLM031397326 | E47: ASHC | F47: ASHC | G47: UBER | H47: 4374.64 | I47: -53.6 | J47: 0 | K47: 0 | L47: -2304.06 | M47: -87.4928 | N47: 0 | O47: =SUM(H47:N47) -> 1929.4872 | P47: -1071 | Q47: 0 | R47: 0 | S47: 0 | T47: 0 | U47: 0 | V47: 0 | W47: =+O47+SUM(P47:V47) -> 858.4872 | X47: =IF(W47>=0,W47,0) -> 858.4872 | Y47: =IF(W47<=0,W47,0) -> 0 | Z47: 0 | AA47: =+Y47+Z47 -> 0 | AB47: =+O47-X47+Z47+AA47 -> 1071
A48: 3 | B48: ULISES ITIEL CASTILLO AVILA | C48: KIA RIO|2020|GRIS|NCK475B | D48: OHLM031397326 | E48: ASHC | F48: IVETH | G48: UBER | H48: 3116.48 | I48: -72.8 | J48: 0 | K48: 0 | L48: -1226.18 | M48: -62.3296 | N48: -10.78 | O48: =SUM(H48:N48) -> 1744.3904 | P48: -1429 | Q48: 0 | R48: 0 | S48: 0 | T48: 0 | U48: 0 | V48: 0 | W48: =+O48+SUM(P48:V48) -> 315.3904 | X48: =IF(W48>=0,W48,0) -> 315.3904 | Y48: =IF(W48<=0,W48,0) -> 0 | Z48: 0 | AA48: =+Y48+Z48 -> 0 | AB48: =+O48-X48+Z48+AA48 -> 1429
... A51: 4 | B51: CESAR PIÑA BARONA | C51: HYUNDAI|2022|PLATA|D40BKD | D51: OHLM023658024 | E51: ASHC | F51: IVETH | G51: UBER | H51: 0 | I51: 0 | J51: 0 | K51: 0 | L51: 0 | M51: 0 | N51: 0 | O51: =SUM(H51:N51) -> 0 | P51: -2500 | Q51: 0 | R51: 0 | S51: 0 | T51: 0 | U51: 0 | V51: 0 | W51: =+O51+SUM(P51:V51) -> -2500 | X51: =IF(W51>=0,W51,0) -> 0 | Y51: =IF(W51<=0,W51,0) -> -2500 | Z51: 0 | AA51: =+Y51+Z51 -> -2500 | AB51: =+O51-X51+Z51+AA51 -> -2500
A52: 4 | B52: DIEGO SANCHEZ | C52: VENTO|2020|GRIS|R66BER | D52: OHLM023720329 | E52: ASHC | F52: ASHC | G52: UBER | H52: 3186.86 | I52: 0 | J52: 0 | K52: 0 | L52: -1760.81 | M52: -25 | N52: 0 | O52: =SUM(H52:N52) -> 1401.05 | P52: -2500 | Q52: 0 | R52: -500 | S52: 0 | T52: 0 | U52: 0 | V52: 0 | W52: =+O52+SUM(P52:V52) -> -1598.95 | X52: =IF(W52>=0,W52,0) -> 0 | Y52: =IF(W52<=0,W52,0) -> -1598.95 | Z52: 1599 | AA52: =+Y52+Z52 -> 0.05 | AB52: =+O52-X52+Z52+AA52 -> 3000.1 | AC52: PAGADO | 30 ENE
A53: 4 | B53: EDGAR GEOVANY URIBE | C53: AVEO|2019|PLATA|NEL860A | D53: OHLM023720337 | E53: ASHC | F53: ASHC | G53: UBER | H53: 7979.51 | I53: -94.4 | J53: 0 | K53: 0 | L53: -1948.64 | M53: -60.83 | N53: 0 | O53: =SUM(H53:N53) -> 5875.64 | P53: -2500 | Q53: 0 | R53: 0 | S53: -500 | T53: 0 | U53: 0 | V53: 0 | W53: =+O53+SUM(P53:V53) -> 2875.64 | X53: =IF(W53>=0,W53,0) -> 2875.64 | Y53: =IF(W53<=0,W53,0) -> 0 | Z53: 0 | AA53: =+Y53+Z53 -> 0 | AB53: =+O53-X53+Z53+AA53 -> 3000
A54: 4 | B54: FERNANDO ESQUIVEL SOSA | C54: VENTO|2018|AMARILLO|PED1652 | D54: OHLM031409055 | E54: ASHC | F54: ASHC | G54: UBER | H54: 6015.72 | I54: -96 | J54: 0 | K54: 0 | L54: -2519.47 | M54: -40 | N54: -68 | O54: =SUM(H54:N54) -> 3292.25 | P54: -2500 | Q54: 0 | R54: -500 | S54: 0 | T54: 0 | U54: 0 | V54: 0 | W54: =+O54+SUM(P54:V54) -> 292.25 | X54: =IF(W54>=0,W54,0) -> 292.25 | Y54: =IF(W54<=0,W54,0) -> 0 | Z54: 0 | AA54: =+Y54+Z54 -> 0 | AB54: =+O54-X54+Z54+AA54 -> 3000
A55: 4 | B55: IRAM HERNANDEZ | C55: AVEO|2022|AZUL|MUF515A | D55: OHLM023720311 | E55: ASHC | F55: ASHC | G55: UBER | H55: 5446.08 | I55: 0 | J55: 0 | K55: 0 | L55: -1740.95 | M55: -45 | N55: -111 | O55: =SUM(H55:N55) -> 3549.13 | P55: -2500 | Q55: 0 | R55: 0 | S55: -500 | T55: 0 | U55: 0 | V55: 0 | W55: =+O55+SUM(P55:V55) -> 549.13 | X55: =IF(W55>=0,W55,0) -> 549.13 | Y55: =IF(W55<=0,W55,0) -> 0 | Z55: 0 | AA55: =+Y55+Z55 -> 0 | AB55: =+O55-X55+Z55+AA55 -> 3000
A56: 4 | B56: IVAN MOGUEL PULIDO | C56: VERSA|2023|PLATA|NCT814A | D56: OHLM023012487 | E56: ASHC | F56: ASHC | G56: UBER | H56: 10172.05 | I56: -184 | J56: 0 | K56: 0 | L56: -4557.47 | M56: -97.57 | N56: -503.08 | O56: =SUM(H56:N56) -> 4829.93 | P56: -2500 | Q56: 0 | R56: 0 | S56: 0 | T56: -500 | U56: 0 | V56: 0 | W56: =+O56+SUM(P56:V56) -> 1829.93 | X56: =IF(W56>=0,W56,0) -> 1829.93 | Y56: =IF(W56<=0,W56,0) -> 0 | Z56: 0 | AA56: =+Y56+Z56 -> 0 | AB56: =+O56-X56+Z56+AA56 -> 3000
A57: 4 | B57: JOSE GUADALUPE GARCIA MORALES | C57: MARCH|2020|TURQ|N15BKD | D57: OHLM031409071 | E57: ASHC | F57: ASHC | G57: UBER | H57: 4194.92 | I57: 0 | J57: 0 | K57: 0 | L57: -2079.62 | M57: -35 | N57: 0 | O57: =SUM(H57:N57) -> 2080.3 | P57: -2500 | Q57: 0 | R57: 0 | S57: 0 | T57: 0 | U57: 0 | V57: 0 | W57: =+O57+SUM(P57:V57) -> -419.7 | X57: =IF(W57>=0,W57,0) -> 0 | Y57: =IF(W57<=0,W57,0) -> -419.7 | Z57: 0 | AA57: =+Y57+Z57 -> -419.7 | AB57: =+O57-X57+Z57+AA57 -> 1660.6 | AC57: PAGADO | 4 FEB
A58: 4 | B58: JOSE GUILLERMO HERNANDEZ RAMIREZ | C58: AVEO|2018|ROJO|R51BKD | D58: OHLM017365206 | E58: U64 | F58: ASHC | G58: UBER | H58: 7059.17 | I58: -155.2 | J58: 0 | K58: 0 | L58: -3771.6 | M58: -50 | N58: 0 | O58: =SUM(H58:N58) -> 3082.37 | P58: -2500 | Q58: 0 | R58: 0 | S58: 0 | T58: 0 | U58: 0 | V58: 0 | W58: =+O58+SUM(P58:V58) -> 582.37 | X58: =IF(W58>=0,W58,0) -> 582.37 | Y58: =IF(W58<=0,W58,0) -> 0 | Z58: 0 | AA58: =+Y58+Z58 -> 0 | AB58: =+O58-X58+Z58+AA58 -> 2500
A59: 4 | B59: JOSE JUAN HERNANDEZ MEJIA | C59: VERSA|2017|ACERO|X24APU | D59: OHLM023720345 | E59: ASHC | F59: ASHC | G59: UBER | H59: 4787.08 | I59: -29.31 | J59: 0 | K59: 0 | L59: -1967.22 | M59: -30 | N59: 0 | O59: =SUM(H59:N59) -> 2760.55 | P59: -2500 | Q59: 0 | R59: -500 | S59: 0 | T59: 0 | U59: 0 | V59: 0 | W59: =+O59+SUM(P59:V59) -> -239.45 | X59: =IF(W59>=0,W59,0) -> 0 | Y59: =IF(W59<=0,W59,0) -> -239.45 | Z59: 181 | AA59: =+Y59+Z59 -> -58.45 | AB59: =+O59-X59+Z59+AA59 -> 2883.1 | AC59: PAGADO | 4 FEB
A60: 4 | B60: JUAN CARLOS MUÑOZ | C60: AVEO|2019|BLANCO|NBS225A | D60: OHLM023720287 | E60: ASHC | F60: IVETH | G60: UBER | H60: 5743.67 | I60: 0 | J60: 0 | K60: 0 | L60: -2576.79 | M60: -45 | N60: -58 | O60: =SUM(H60:N60) -> 3063.88 | P60: -2500 | Q60: 0 | R60: 0 | S60: 0 | T60: 0 | U60: 0 | V60: 0 | W60: =+O60+SUM(P60:V60) -> 563.88 | X60: =IF(W60>=0,W60,0) -> 563.88 | Y60: =IF(W60<=0,W60,0) -> 0 | Z60: 0 | AA60: =+Y60+Z60 -> 0 | AB60: =+O60-X60+Z60+AA60 -> 2500
A61: 4 | B61: OSCAR BLANCAS NORIEGA | C61: VENTO|2017|GRIS|NZV7888 | D61: OHLM023720279 | E61: ASHC | F61: ASHC | G61: UBER | H61: 3430.61 | I61: -16 | J61: 0 | K61: 0 | L61: -2162.82 | M61: -25 | N61: 0 | O61: =SUM(H61:N61) -> 1226.79 | P61: -2300 | Q61: 120 | R61: 0 | S61: -500 | T61: 0 | U61: 0 | V61: 0 | W61: =+O61+SUM(P61:V61) -> -1453.21 | X61: =IF(W61>=0,W61,0) -> 0 | Y61: =IF(W61<=0,W61,0) -> -1453.21 | Z61: 1421 | AA61: =+Y61+Z61 -> -32.21 | AB61: =+O61-X61+Z61+AA61 -> 2615.58 | AC61: PAGADO | 29 ENE |4 FEB
A62: 4 | B62: SIN CONDUCTOR | C62: BEAT|2020|GRIS|NFN014B | D62: - | E62: U64 | F62: ASHC | G62: UBER | H62: 0 | I62: 0 | J62: 0 | K62: 0 | L62: 0 | M62: 0 | N62: 0 | O62: =SUM(H62:N62) -> 0 | P62: 0 | Q62: 0 | R62: 0 | S62: 0 | T62: 0 | U62: 0 | V62: 0 | W62: =+O62+SUM(P62:V62) -> 0 | X62: =IF(W62>=0,W62,0) -> 0 | Y62: =IF(W62<=0,W62,0) -> 0 | Z62: 0 | AA62: =+Y62+Z62 -> 0 | AB62: =+O62-X62+Z62+AA62 -> 0
A63: 4 | B63: ULISES ITIEL CASTILLO AVILA | C63: KIA RIO|2020|GRIS|NCK475B | D63: OHLM031397326 | E63: ASHC | F63: IVETH | G63: UBER | H63: 5452.14 | I63: -67.2 | J63: 0 | K63: 0 | L63: -1513.04 | M63: -78 | N63: -75.21 | O63: =SUM(H63:N63) -> 3718.69 | P63: -2500 | Q63: 0 | R63: 0 | S63: 0 | T63: 0 | U63: 0 | V63: 0 | W63: =+O63+SUM(P63:V63) -> 1218.69 | X63: =IF(W63>=0,W63,0) -> 1218.69 | Y63: =IF(W63<=0,W63,0) -> 0 | Z63: 0 | AA63: =+Y63+Z63 -> 0 | AB63: =+O63-X63+Z63+AA63 -> 2500
A64: 5 | B64: ADOLFO LOPEZ MARTINEZ | C64: AVEO|2021|OCRE|NEB156A | D64: OHLM023012552 | E64: ASHC | F64: IVETH | G64: UBER | H64: 675.51 | I64: 9.15 | J64: 0 | K64: 0 | L64: 0 | M64: -19 | N64: 0 | O64: =SUM(H64:N64) -> 665.66 | P64: -2500 | Q64: 0 | R64: 0 | S64: 0 | T64: 0 | U64: 0 | V64: 0 | W64: =+O64+SUM(P64:V64) -> -1834.34 | X64: =IF(W64>=0,W64,0) -> 0 | Y64: =IF(W64<=0,W64,0) -> -1834.34 | Z64: 1834 | AA64: =+Y64+Z64 -> -0.34 | AB64: =+O64-X64+Z64+AA64 -> 2499.32
A65: 5 | B65: ARACELI CASTILLO GUERRERO | C65: AVEO|2018|GRIS|X59AWG | D65: - | E65: ASHC | F65: ASHC | G65: UBER | H65: 0 | I65: 0 | J65: 0 | K65: 0 | L65: 0 | M65: 0 | N65: 0 | O65: =SUM(H65:N65) -> 0 | P65: 0 | Q65: 0 | R65: 0 | S65: 0 | T65: 0 | U65: 0 | V65: 0 | W65: =+O65+SUM(P65:V65) -> 0 | X65: =IF(W65>=0,W65,0) -> 0 | Y65: =IF(W65<=0,W65,0) -> 0 | Z65: 0 | AA65: =+Y65+Z65 -> 0 | AB65: =+O65-X65+Z65+AA65 -> 0
A66: 5 | B66: CESAR PIÑA BARONA | C66: HYUNDAI|2022|PLATA|D40BKD | D66: OHLM023658024 | E66: ASHC | F66: IVETH | G66: UBER | H66: 0 | I66: 0 | J66: 0 | K66: 0 | L66: 0 | M66: 0 | N66: 0 | O66: =SUM(H66:N66) -> 0 | P66: -2500 | Q66: 0 | R66: 0 | S66: 0 | T66: 0 | U66: 0 | V66: 0 | W66: =+O66+SUM(P66:V66) -> -2500 | X66: =IF(W66>=0,W66,0) -> 0 | Y66: =IF(W66<=0,W66,0) -> -2500 | Z66: 5000 | AA66: =+Y66+Z66 -> 2500 | AB66: =+O66-X66+Z66+AA66 -> 7500
A67: 5 | B67: DIEGO SANCHEZ | C67: VENTO|2020|GRIS|R66BER | D67: OHLM023720329 | E67: ASHC | F67: ASHC | G67: UBER | H67: 4292.37 | I67: 0 | J67: 0 | K67: 0 | L67: -1767.76 | M67: -35 | N67: -55 | O67: =SUM(H67:N67) -> 2434.61 | P67: -2500 | Q67: 0 | R67: -25 | S67: 0 | T67: 0 | U67: 0 | V67: 0 | W67: =+O67+SUM(P67:V67) -> -90.39 | X67: =IF(W67>=0,W67,0) -> 0 | Y67: =IF(W67<=0,W67,0) -> -90.39 | Z67: 0 | AA67: =+Y67+Z67 -> -90.39 | AB67: =+O67-X67+Z67+AA67 -> 2344.22 | AC67: PAGADO 8 FEB
A68: 5 | B68: EDGAR GEOVANY URIBE | C68: AVEO|2019|PLATA|NEL860A | D68: OHLM023720337 | E68: ASHC | F68: ASHC | G68: UBER | H68: 8172.09 | I68: 206.4 | J68: 0 | K68: 0 | L68: -1598.72 | M68: -95 | N68: -15.1 | O68: =SUM(H68:N68) -> 6669.67 | P68: -2500 | Q68: 0 | R68: 0 | S68: -500 | T68: 0 | U68: 0 | V68: 0 | W68: =+O68+SUM(P68:V68) -> 3669.67 | X68: =IF(W68>=0,W68,0) -> 3669.67 | Y68: =IF(W68<=0,W68,0) -> 0 | Z68: 0 | AA68: =+Y68+Z68 -> 0 | AB68: =+O68-X68+Z68+AA68 -> 3000
A69: 5 | B69: FERNANDO ESQUIVEL SOSA | C69: VENTO|2018|AMARILLO|PED1652 | D69: OHLM031409055 | E69: ASHC | F69: ASHC | G69: UBER | H69: 5850.36 | I69: 120 | J69: 0 | K69: 0 | L69: -2290.38 | M69: -49 | N69: -68 | O69: =SUM(H69:N69) -> 3562.98 | P69: -2500 | Q69: 465 | R69: -500 | S69: 0 | T69: 0 | U69: 0 | V69: 0 | W69: =+O69+SUM(P69:V69) -> 1027.98 | X69: =IF(W69>=0,W69,0) -> 1027.98 | Y69: =IF(W69<=0,W69,0) -> 0 | Z69: 0 | AA69: =+Y69+Z69 -> 0 | AB69: =+O69-X69+Z69+AA69 -> 2535 | AC69: PAGADO
A70: 5 | B70: IRAM HERNANDEZ | C70: AVEO|2022|AZUL|MUF515A | D70: OHLM031491772 | E70: ASHC | F70: ASHC | G70: UBER | H70: 4096.64 | I70: 0 | J70: 0 | K70: 0 | L70: -1452.54 | M70: -45 | N70: -91 | O70: =SUM(H70:N70) -> 2508.1 | P70: -1964.2857 | Q70: 0 | R70: 0 | S70: -300 | T70: 0 | U70: 0 | V70: 0 | W70: =+O70+SUM(P70:V70) -> 243.81429 | X70: =IF(W70>=0,W70,0) -> 243.81429 | Y70: =IF(W70<=0,W70,0) -> 0 | Z70: 0 | AA70: =+Y70+Z70 -> 0 | AB70: =+O70-X70+Z70+AA70 -> 2264.2857
A71: 5 | B71: IVAN MOGUEL PULIDO | C71: VERSA|2023|PLATA|NCT814A | D71: OHLM031491780 | E71: ASHC | F71: ASHC | G71: UBER | H71: 10628.31 | I71: 223.2 | J71: 0 | K71: 0 | L71: -4537.27 | M71: -90 | N71: -328.97 | O71: =SUM(H71:N71) -> 5895.27 | P71: -2500 | Q71: 0 | R71: 0 | S71: 0 | T71: -500 | U71: 0 | V71: 0 | W71: =+O71+SUM(P71:V71) -> 2895.27 | X71: =IF(W71>=0,W71,0) -> 2895.27 | Y71: =IF(W71<=0,W71,0) -> 0 | Z71: 0 | AA71: =+Y71+Z71 -> 0 | AB71: =+O71-X71+Z71+AA71 -> 3000
A72: 5 | B72: JOSE GUADALUPE GARCIA MORALES | C72: MARCH|2020|TURQ|N15BKD | D72: OHLM031409071 | E72: ASHC | F72: ASHC | G72: UBER | H72: 5033.08 | I72: 0 | J72: 0 | K72: 0 | L72: -1722.51 | M72: -58.83 | N72: 0 | O72: =SUM(H72:N72) -> 3251.74 | P72: -2500 | Q72: -420 | R72: 0 | S72: 0 | T72: 0 | U72: 0 | V72: 0 | W72: =+O72+SUM(P72:V72) -> 331.74 | X72: =IF(W72>=0,W72,0) -> 331.74 | Y72: =IF(W72<=0,W72,0) -> 0 | Z72: 0 | AA72: =+Y72+Z72 -> 0 | AB72: =+O72-X72+Z72+AA72 -> 2920 | AC72: PAGADO
A73: 5 | B73: JOSE GUILLERMO HERNANDEZ RAMIREZ | C73: AVEO|2018|ROJO|R51BKD | D73: OHLM017365206 | E73: U64 | F73: ASHC | G73: UBER | H73: 6762.66 | I73: 100 | J73: 0 | K73: 0 | L73: -4033.67 | M73: -48 | N73: 0 | O73: =SUM(H73:N73) -> 2780.99 | P73: -2500 | Q73: 28 | R73: 0 | S73: 0 | T73: 0 | U73: 0 | V73: 0 | W73: =+O73+SUM(P73:V73) -> 308.99 | X73: =IF(W73>=0,W73,0) -> 308.99 | Y73: =IF(W73<=0,W73,0) -> 0 | Z73: 0 | AA73: =+Y73+Z73 -> 0 | AB73: =+O73-X73+Z73+AA73 -> 2472 | AC73: RETIRO CAJERO
A74: 5 | B74: JOSE JUAN HERNANDEZ MEJIA | C74: VERSA|2017|ACERO|X24APU | D74: OHLM023720345 | E74: ASHC | F74: ASHC | G74: UBER | H74: 4727.71 | I74: 0 | J74: 0 | K74: 0 | L74: -1513.29 | M74: -55 | N74: 0 | O74: =SUM(H74:N74) -> 3159.42 | P74: -2500 | Q74: 0 | R74: -500 | S74: 0 | T74: 0 | U74: 0 | V74: 0 | W74: =+O74+SUM(P74:V74) -> 159.42 | X74: =IF(W74>=0,W74,0) -> 159.42 | Y74: =IF(W74<=0,W74,0) -> 0 | Z74: 0 | AA74: =+Y74+Z74 -> 0 | AB74: =+O74-X74+Z74+AA74 -> 3000 | AC74: COMPENSACIÓN DE SALDOS
A75: 5 | B75: JUAN CARLOS MUÑOZ | C75: AVEO|2019|BLANCO|NBS225A | D75: OHLM023720287 | E75: ASHC | F75: IVETH | G75: UBER | H75: 6000.31 | I75: 0 | J75: 0 | K75: 0 | L75: -3123.9 | M75: 0 | N75: -43 | O75: =SUM(H75:N75) -> 2833.41 | P75: -2500 | Q75: 0 | R75: -500 | S75: 0 | T75: 0 | U75: 0 | V75: 0 | W75: =+O75+SUM(P75:V75) -> -166.59 | X75: =IF(W75>=0,W75,0) -> 0 | Y75: =IF(W75<=0,W75,0) -> -166.59 | Z75: 0 | AA75: =+Y75+Z75 -> -166.59 | AB75: =+O75-X75+Z75+AA75 -> 2666.82
A76: 5 | B76: OSCAR BLANCAS NORIEGA | C76: VENTO|2017|GRIS|NZV7888 | D76: OHLM023720279 | E76: ASHC | F76: ASHC | G76: UBER | H76: 3945.89 | I76: 24 | J76: 0 | K76: 0 | L76: -1941.72 | M76: -30 | N76: -4.97 | O76: =SUM(H76:N76) -> 1993.2 | P76: -2300 | Q76: 0 | R76: 0 | S76: -500 | T76: 0 | U76: 0 | V76: 0 | W76: =+O76+SUM(P76:V76) -> -806.8 | X76: =IF(W76>=0,W76,0) -> 0 | Y76: =IF(W76<=0,W76,0) -> -806.8 | Z76: 0 | AA76: =+Y76+Z76 -> -806.8 | AB76: =+O76-X76+Z76+AA76 -> 1186.4 | AC76: PAGADO 5 FEB
A77: 5 | B77: SIN CONDUCTOR | C77: BEAT|2020|GRIS|NFN014B | D77: - | E77: U64 | F77: ASHC | G77: UBER | H77: 0 | I77: 0 | J77: 0 | K77: 0 | L77: 0 | M77: 0 | N77: 0 | O77: =SUM(H77:N77) -> 0 | P77: 0 | Q77: 0 | R77: 0 | S77: 0 | T77: 0 | U77: 0 | V77: 0 | W77: =+O77+SUM(P77:V77) -> 0 | X77: =IF(W77>=0,W77,0) -> 0 | Y77: =IF(W77<=0,W77,0) -> 0 | Z77: 0 | AA77: =+Y77+Z77 -> 0 | AB77: =+O77-X77+Z77+AA77 -> 0
A78: 5 | B78: ULISES ITIEL CASTILLO AVILA | C78: KIA RIO|2020|GRIS|NCK475B | D78: OHLM031397326 | E78: ASHC | F78: IVETH | G78: UBER | H78: 6031.51 | I78: 63.2 | J78: 0 | K78: 0 | L78: -2551.25 | M78: 0 | N78: -381.72 | O78: =SUM(H78:N78) -> 3161.74 | P78: -2500 | Q78: 0 | R78: 0 | S78: 0 | T78: 0 | U78: 0 | V78: 0 | W78: =+O78+SUM(P78:V78) -> 661.74 | X78: =IF(W78>=0,W78,0) -> 661.74 | Y78: =IF(W78<=0,W78,0) -> 0 | Z78: 0 | AA78: =+Y78+Z78 -> 0 | AB78: =+O78-X78+Z78+AA78 -> 2500
A79: 6 | B79: ADOLFO LOPEZ MARTINEZ | C79: AVEO|2021|OCRE|NEB156A | D79: OHLM023012552 | E79: ASHC | F79: IVETH | G79: UBER | H79: 0 | I79: 0 | J79: 0 | K79: 0 | L79: 0 | M79: 0 | N79: 0 | O79: =SUM(H79:N79) -> 0 | P79: -2500 | Q79: 0 | R79: 0 | S79: 0 | T79: 0 | U79: 0 | V79: 0 | W79: =+O79+SUM(P79:V79) -> -2500 | X79: =IF(W79>=0,W79,0) -> 0 | Y79: =IF(W79<=0,W79,0) -> -2500 | Z79: 2500 | AA79: =+Y79+Z79 -> 0 | AB79: =+O79-X79+Z79+AA79 -> 2500 | AC79: Pendiente
A80: 6 | B80: CESAR PIÑA BARONA | C80: HYUNDAI|2022|PLATA|D40BKD | D80: OHLM023658024 | E80: ASHC | F80: IVETH | G80: UBER | H80: 0 | I80: 0 | J80: 0 | K80: 0 | L80: 0 | M80: 0 | N80: 0 | O80: =SUM(H80:N80) -> 0 | P80: -2500 | Q80: 0 | R80: 0 | S80: 0 | T80: 0 | U80: 0 | V80: 0 | W80: =+O80+SUM(P80:V80) -> -2500 | X80: =IF(W80>=0,W80,0) -> 0 | Y80: =IF(W80<=0,W80,0) -> -2500 | Z80: 2500 | AA80: =+Y80+Z80 -> 0 | AB80: =+O80-X80+Z80+AA80 -> 2500 | AC80: PENDIENTE
A81: 6 | B81: DIEGO SANCHEZ | C81: VENTO|2020|GRIS|R66BER | D81: OHLM023720329 | E81: ASHC | F81: ASHC | G81: UBER | H81: 4542.31 | I81: 0 | J81: 0 | K81: 0 | L81: -2505.74 | M81: 0 | N81: 0 | O81: =SUM(H81:N81) -> 2036.57 | P81: -2500 | Q81: 0 | R81: 0 | S81: 0 | T81: 0 | U81: 0 | V81: 0 | W81: =+O81+SUM(P81:V81) -> -463.43 | X81: =IF(W81>=0,W81,0) -> 0 | Y81: =IF(W81<=0,W81,0) -> -463.43 | Z81: 0 | AA81: =+Y81+Z81 -> -463.43 | AB81: =+O81-X81+Z81+AA81 -> 1573.14
A82: 6 | B82: EDGAR GEOVANY URIBE | C82: AVEO|2019|PLATA|NEL860A | D82: OHLM023720337 | E82: ASHC | F82: ASHC | G82: UBER | H82: 7372.52 | I82: 139.2 | J82: 0 | K82: 0 | L82: -1389.35 | M82: -96 | N82: 0 | O82: =SUM(H82:N82) -> 6026.37 | P82: -2500 | Q82: 0 | R82: 0 | S82: -343 | T82: 0 | U82: 0 | V82: 0 | W82: =+O82+SUM(P82:V82) -> 3183.37 | X82: =IF(W82>=0,W82,0) -> 3183.37 | Y82: =IF(W82<=0,W82,0) -> 0 | Z82: 0 | AA82: =+Y82+Z82 -> 0 | AB82: =+O82-X82+Z82+AA82 -> 2843
A83: 6 | B83: FERNANDO ESQUIVEL SOSA | C83: VENTO|2018|AMARILLO|PED1652 | D83: OHLM031409055 | E83: ASHC | F83: ASHC | G83: UBER | H83: 3023.97 | I83: 0 | J83: 0 | K83: 0 | L83: -588.19 | M83: 0 | N83: 0 | O83: =SUM(H83:N83) -> 2435.78 | P83: -2500 | Q83: 0 | R83: -500 | S83: 0 | T83: 0 | U83: 0 | V83: 0 | W83: =+O83+SUM(P83:V83) -> -564.22 | X83: =IF(W83>=0,W83,0) -> 0 | Y83: =IF(W83<=0,W83,0) -> -564.22 | Z83: 545 | AA83: =+Y83+Z83 -> -19.22 | AB83: =+O83-X83+Z83+AA83 -> 2961.56
A84: 6 | B84: IRAM HERNANDEZ | C84: AVEO|2022|AZUL|MUF515A | D84: OHLM031491772 | E84: ASHC | F84: ASHC | G84: UBER | H84: 4975.22 | I84: 0 | J84: 0 | K84: 0 | L84: -1753.47 | M84: -56 | N84: 0 | O84: =SUM(H84:N84) -> 3165.75 | P84: -2500 | Q84: 0 | R84: 0 | S84: -500 | T84: 0 | U84: 0 | V84: 0 | W84: =+O84+SUM(P84:V84) -> 165.75 | X84: =IF(W84>=0,W84,0) -> 165.75 | Y84: =IF(W84<=0,W84,0) -> 0 | Z84: 0 | AA84: =+Y84+Z84 -> 0 | AB84: =+O84-X84+Z84+AA84 -> 3000
A85: 6 | B85: IVAN MOGUEL PULIDO | C85: VERSA|2023|PLATA|NCT814A | D85: OHLM031491780 | E85: ASHC | F85: ASHC | G85: UBER | H85: 8889.43 | I85: 89.6 | J85: -54 | K85: 0 | L85: -4457.29 | M85: -85 | N85: -172.05 | O85: =SUM(H85:N85) -> 4210.69 | P85: -2500 | Q85: 0 | R85: 0 | S85: -500 | T85: -65 | U85: 0 | V85: 0 | W85: =+O85+SUM(P85:V85) -> 1145.69 | X85: =IF(W85>=0,W85,0) -> 1145.69 | Y85: =IF(W85<=0,W85,0) -> 0 | Z85: 0 | AA85: =+Y85+Z85 -> 0 | AB85: =+O85-X85+Z85+AA85 -> 3065
A86: 6 | B86: JOSE GUADALUPE GARCIA MORALES | C86: MARCH|2020|TURQ|N15BKD | D86: OHLM031409071 | E86: ASHC | F86: ASHC | G86: UBER | H86: 4661.12 | I86: 0 | J86: 0 | K86: 0 | L86: -2350.13 | M86: -45 | N86: 0 | O86: =SUM(H86:N86) -> 2265.99 | P86: -2500 | Q86: 0 | R86: 0 | S86: 0 | T86: 0 | U86: 0 | V86: 0 | W86: =+O86+SUM(P86:V86) -> -234.01 | X86: =IF(W86>=0,W86,0) -> 0 | Y86: =IF(W86<=0,W86,0) -> -234.01 | Z86: 234 | AA86: =+Y86+Z86 -> -0.01 | AB86: =+O86-X86+Z86+AA86 -> 2499.98
A87: 6 | B87: JOSE GUILLERMO HERNANDEZ RAMIREZ | C87: AVEO|2018|ROJO|R51BKD | D87: OHLM017365206 | E87: U64 | F87: ASHC | G87: UBER | H87: 6463.43 | I87: 117.6 | J87: 0 | K87: 0 | L87: -3597.86 | M87: -78 | N87: 0 | O87: =SUM(H87:N87) -> 2905.17 | P87: -2500 | Q87: 9 | R87: 0 | S87: 0 | T87: 0 | U87: 0 | V87: 0 | W87: =+O87+SUM(P87:V87) -> 414.17 | X87: =IF(W87>=0,W87,0) -> 414.17 | Y87: =IF(W87<=0,W87,0) -> 0 | Z87: 0 | AA87: =+Y87+Z87 -> 0 | AB87: =+O87-X87+Z87+AA87 -> 2491
A88: 6 | B88: JOSE JUAN HERNANDEZ MEJIA | C88: VERSA|2017|ACERO|X24APU | D88: OHLM023720345 | E88: ASHC | F88: ASHC | G88: UBER | H88: 3144.49 | I88: 0 | J88: 0 | K88: 0 | L88: -831.67 | M88: 0 | N88: -75 | O88: =SUM(H88:N88) -> 2237.82 | P88: -2321.4286 | Q88: 0 | R88: -500 | S88: 0 | T88: 0 | U88: 0 | V88: 0 | W88: =+O88+SUM(P88:V88) -> -583.60857 | X88: =IF(W88>=0,W88,0) -> 0 | Y88: =IF(W88<=0,W88,0) -> -583.60857 | Z88: 584 | AA88: =+Y88+Z88 -> 0.39142857 | AB88: =+O88-X88+Z88+AA88 -> 2822.2114
A89: 6 | B89: JUAN CARLOS MUÑOZ | C89: AVEO|2019|BLANCO|NBS225A | D89: OHLM023720287 | E89: ASHC | F89: IVETH | G89: UBER | H89: 659.52 | I89: 0 | J89: 0 | K89: 0 | L89: -220 | M89: 0 | N89: -114 | O89: =SUM(H89:N89) -> 325.52 | P89: -1786 | Q89: 0 | R89: 0 | S89: 0 | T89: 0 | U89: 0 | V89: 0 | W89: =+O89+SUM(P89:V89) -> -1460.48 | X89: =IF(W89>=0,W89,0) -> 0 | Y89: =IF(W89<=0,W89,0) -> -1460.48 | Z89: 3167 | AA89: =+Y89+Z89 -> 1706.52 | AB89: =+O89-X89+Z89+AA89 -> 5199.04 | AC89: Devolución Fianza
A90: 6 | B90: MARIO ALBERTO ROJAS | C90: AVEO|2018|GRIS|X59AWG | D90: - | E90: ASHC | F90: ASHC | G90: UBER | H90: 3054.64 | I90: 0.31 | J90: 0 | K90: 0 | L90: -1378.41 | M90: -0.83 | N90: 0 | O90: =SUM(H90:N90) -> 1675.71 | P90: -1785.7143 | Q90: 0 | R90: -500 | S90: 0 | T90: 0 | U90: 0 | V90: 0 | W90: =+O90+SUM(P90:V90) -> -610.00429 | X90: =IF(W90>=0,W90,0) -> 0 | Y90: =IF(W90<=0,W90,0) -> -610.00429 | Z90: 0 | AA90: =+Y90+Z90 -> -610.00429 | AB90: =+O90-X90+Z90+AA90 -> 1065.7057
A91: 6 | B91: OSCAR BLANCAS NORIEGA | C91: VENTO|2017|GRIS|NZV7888 | D91: OHLM023720279 | E91: ASHC | F91: ASHC | G91: UBER | H91: 5375.28 | I91: 28.8 | J91: 0 | K91: 0 | L91: -1997.86 | M91: -67 | N91: 0 | O91: =SUM(H91:N91) -> 3339.22 | P91: -2300 | Q91: 0 | R91: 0 | S91: -500 | T91: 0 | U91: 0 | V91: 0 | W91: =+O91+SUM(P91:V91) -> 539.22 | X91: =IF(W91>=0,W91,0) -> 539.22 | Y91: =IF(W91<=0,W91,0) -> 0 | Z91: 0 | AA91: =+Y91+Z91 -> 0 | AB91: =+O91-X91+Z91+AA91 -> 2800
A92: 6 | B92: RODOLFO AVANTES | C92: BEAT|2020|GRIS|NFN014B | D92: SIN TAG | E92: U64 | F92: ASHC | G92: UBER | H92: 2278.65 | I92: 0 | J92: 0 | K92: 0 | L92: -1184.24 | M92: 0 | N92: 0 | O92: =SUM(H92:N92) -> 1094.41 | P92: -1785.7143 | Q92: 0 | R92: -500 | S92: 0 | T92: 0 | U92: 0 | V92: 0 | W92: =+O92+SUM(P92:V92) -> -1191.3043 | X92: =IF(W92>=0,W92,0) -> 0 | Y92: =IF(W92<=0,W92,0) -> -1191.3043 | Z92: 0 | AA92: =+Y92+Z92 -> -1191.3043 | AB92: =+O92-X92+Z92+AA92 -> -96.894286
A93: 6 | B93: ULISES ITIEL CASTILLO AVILA | C93: KIA RIO|2020|GRIS|NCK475B | D93: OHLM031397326 | E93: ASHC | F93: IVETH | G93: UBER | H93: 4559.7 | I93: 8 | J93: 0 | K93: 0 | L93: -1681.88 | M93: 0 | N93: 0 | O93: =SUM(H93:N93) -> 2885.82 | P93: -2500 | Q93: 0 | R93: 0 | S93: 0 | T93: 0 | U93: 0 | V93: 0 | W93: =+O93+SUM(P93:V93) -> 385.82 | X93: =IF(W93>=0,W93,0) -> 385.82 | Y93: =IF(W93<=0,W93,0) -> 0 | Z93: 0 | AA93: =+Y93+Z93 -> 0 | AB93: =+O93-X93+Z93+AA93 -> 2500
A94: 7 | B94: ADOLFO LOPEZ MARTINEZ | C94: AVEO|2021|OCRE|NEB156A | D94: OHLM023012552 | E94: ASHC | F94: IVETH | G94: UBER | H94: 0 | I94: 0 | J94: 0 | K94: 0 | L94: 0 | M94: 0 | N94: 0 | O94: =SUM(H94:N94) -> 0 | P94: 0 | Q94: 0 | R94: 0 | S94: 0 | T94: 0 | U94: 0 | V94: 0 | W94: =+O94+SUM(P94:V94) -> 0 | X94: =IF(W94>=0,W94,0) -> 0 | Y94: =IF(W94<=0,W94,0) -> 0 | Z94: 0 | AA94: =+Y94+Z94 -> 0 | AB94: =+O94-X94+Z94+AA94 -> 0
A95: 7 | B95: CESAR PIÑA BARONA | C95: HYUNDAI|2022|PLATA|D40BKD | D95: OHLM023658024 | E95: ASHC | F95: IVETH | G95: UBER | H95: 0 | I95: 0 | J95: 0 | K95: 0 | L95: 0 | M95: 0 | N95: 0 | O95: =SUM(H95:N95) -> 0 | P95: -2500 | Q95: 0 | R95: 0 | S95: 0 | T95: 0 | U95: 0 | V95: 0 | W95: =+O95+SUM(P95:V95) -> -2500 | X95: =IF(W95>=0,W95,0) -> 0 | Y95: =IF(W95<=0,W95,0) -> -2500 | Z95: 2500 | AA95: =+Y95+Z95 -> 0 | AB95: =+O95-X95+Z95+AA95 -> 2500
A96: 7 | B96: DIEGO SANCHEZ | C96: VENTO|2020|GRIS|R66BER | D96: OHLM023720329 | E96: ASHC | F96: ASHC | G96: UBER | H96: 3240.77 | I96: 0 | J96: 0 | K96: 0 | L96: -1738.57 | M96: -26 | N96: -295.29 | O96: =SUM(H96:N96) -> 1180.91 | P96: -2500 | Q96: 0 | R96: 0 | S96: 0 | T96: 0 | U96: 0 | V96: 0 | W96: =+O96+SUM(P96:V96) -> -1319.09 | X96: =IF(W96>=0,W96,0) -> 0 | Y96: =IF(W96<=0,W96,0) -> -1319.09 | Z96: 0 | AA96: =+Y96+Z96 -> -1319.09 | AB96: =+O96-X96+Z96+AA96 -> -138.18
A97: 7 | B97: EDGAR GEOVANY URIBE | C97: AVEO|2019|PLATA|NEL860A | D97: OHLM023720337 | E97: ASHC | F97: ASHC | G97: UBER | H97: 5003.53 | I97: 0 | J97: 0 | K97: 0 | L97: -731.26 | M97: -45 | N97: -8.73 | O97: =SUM(H97:N97) -> 4218.54 | P97: -96 | Q97: 0 | R97: 0 | S97: 0 | T97: 0 | U97: 0 | V97: 0 | W97: =+O97+SUM(P97:V97) -> 4122.54 | X97: =IF(W97>=0,W97,0) -> 4122.54 | Y97: =IF(W97<=0,W97,0) -> 0 | Z97: 0 | AA97: =+Y97+Z97 -> 0 | AB97: =+O97-X97+Z97+AA97 -> 96
A98: 7 | B98: FERNANDO ESQUIVEL SOSA | C98: VENTO|2018|AMARILLO|PED1652 | D98: OHLM031409055 | E98: ASHC | F98: ASHC | G98: UBER | H98: 79.68 | I98: 0 | J98: 0 | K98: 0 | L98: 0 | M98: 0 | N98: -71 | O98: =SUM(H98:N98) -> 8.68 | P98: 0 | Q98: 0 | R98: 0 | S98: 0 | T98: 0 | U98: 0 | V98: 0 | W98: =+O98+SUM(P98:V98) -> 8.68 | X98: =IF(W98>=0,W98,0) -> 8.68 | Y98: =IF(W98<=0,W98,0) -> 0 | Z98: 0 | AA98: =+Y98+Z98 -> 0 | AB98: =+O98-X98+Z98+AA98 -> 0
A99: 7 | B99: IRAM HERNANDEZ | C99: AVEO|2022|AZUL|MUF515A | D99: OHLM031491772 | E99: ASHC | F99: ASHC | G99: UBER | H99: 4390.43 | I99: 0 | J99: 0 | K99: 0 | L99: -1581.18 | M99: 0 | N99: 0 | O99: =SUM(H99:N99) -> 2809.25 | P99: -56 | Q99: 0 | R99: 0 | S99: -300 | T99: 0 | U99: 0 | V99: 0 | W99: =+O99+SUM(P99:V99) -> 2453.25 | X99: =IF(W99>=0,W99,0) -> 2453.25 | Y99: =IF(W99<=0,W99,0) -> 0 | Z99: 0 | AA99: =+Y99+Z99 -> 0 | AB99: =+O99-X99+Z99+AA99 -> 356
A100: 7 | B100: IVAN MOGUEL PULIDO | C100: VERSA|2023|PLATA|NCT814A | D100: OHLM031491780 | E100: ASHC | F100: ASHC | G100: UBER | H100: 9463.2 | I100: -55.2 | J100: 0 | K100: 0 | L100: -5047.87 | M100: -98 | N100: -431.45 | O100: =SUM(H100:N100) -> 3830.68 | P100: -85 | Q100: -500 | R100: 0 | S100: -500 | T100: 0 | U100: 0 | V100: 0 | W100: =+O100+SUM(P100:V100) -> 2745.68 | X100: =IF(W100>=0,W100,0) -> 2745.68 | Y100: =IF(W100<=0,W100,0) -> 0 | Z100: 0 | AA100: =+Y100+Z100 -> 0 | AB100: =+O100-X100+Z100+AA100 -> 1085
A101: 7 | B101: JOSE GUADALUPE GARCIA MORALES | C101: MARCH|2020|TURQ|N15BKD | D101: OHLM031409071 | E101: ASHC | F101: ASHC | G101: UBER | H101: 5882.5 | I101: 0 | J101: 0 | K101: 0 | L101: -2894.54 | M101: -49 | N101: 0 | O101: =SUM(H101:N101) -> 2938.96 | P101: -45 | Q101: 0 | R101: 0 | S101: 0 | T101: 0 | U101: 0 | V101: 0 | W101: =+O101+SUM(P101:V101) -> 2893.96 | X101: =IF(W101>=0,W101,0) -> 2893.96 | Y101: =IF(W101<=0,W101,0) -> 0 | Z101: 0 | AA101: =+Y101+Z101 -> 0 | AB101: =+O101-X101+Z101+AA101 -> 45
... A116: 8 | B116: IVAN MOGUEL PULIDO | C116: VERSA|2023|PLATA|NCT814A | D116: OHLM031491780 | E116: ASHC | F116: ASHC | G116: UBER | H116: 10899.63 | I116: -137.6 | J116: 0 | K116: 0 | L116: -5571.2 | M116: -75 | N116: -466.22 | O116: =SUM(H116:N116) -> 4649.61 | P116: -2500 | Q116: -500 | R116: 0 | S116: -500 | T116: 0 | U116: 0 | V116: 0 | W116: =+O116+SUM(P116:V116) -> 1149.61 | X116: =IF(W116>=0,W116,0) -> 1149.61 | Y116: =IF(W116<=0,W116,0) -> 0 | Z116: 0 | AA116: =+Y116+Z116 -> 0 | AB116: =+O116-X116+Z116+AA116 -> 3500
...

Sheet UBER 2026
A1: SEM | B1: CONDUCTOR | C1: LLAVE | D1: TAG | E1: SOCIO | F1: PLATAFORMA | G1: APP | H1: GANANCIA | I1: EFECTIVO | J1: IMPUESTOS | K1: P. A ANT | L1: SEGURO | M1: P T | N1: TAG | O1: UBERG | P1: RENTA | Q1: SEM A | R1: FIANZA | S1: MULTA | T1: HOJALAT | U1: DESC | V1: PRÉST | W1: TOTAL | X1: A PAGAR | Y1: DEV | Z1: PAGADO | AA1: ADEUDO | AB1: GANAN T | AC1: ANT F | AD1: COMENTARIOS
A2: 1 | B2: ALEJANDRO PAZ CAMACHO | C2: MARCH|2020|TURQ|N15BKD | D2: OHLM038285789 | E2: ASHC | F2: ASHC | G2: DIDI | H2: 4784.74 | I2: -6209.03 | J2: -620 | K2: 0 | L2: 0 | M2: -95 | N2: 0 | O2: =IF(H2+I2<0,SUM(J2:N2),SUM(H2:N2)) -> -715 | P2: -2600 | Q2: -2771.97 | R2: 0 | S2: 0 | T2: 0 | U2: 0 | V2: 0 | W2: =SUM(O2:V2) -> -6086.97 | X2: =IF(W2>=0,W2,0) -> 0 | Y2: =IF(W2<=0,W2,0) -> -6086.97 | Z2: =800+2357 -> 3157 | AA2: =+Y2+Z2 -> -2929.97 | AB2: =+O2-X2+Z2+AA2 -> -487.97 | AD2: SE CONDONA ADEUDO Y SE AJUSTA DEUDO 2025 | AG2: preguntar si pago 2352
A3: 1 | B3: RAUL FRANCISCO VAZQUEZ CORTE | C3: V DRIVE|2023|GRIS|MXW453C | D3: OHLM038626776 | E3: ASHC | F3: ASHC | G3: DIDI | H3: 176.49 | I3: -130.25 | J3: -13 | K3: 0 | L3: 0 | M3: -65 | N3: 0 | O3: =IF(H3+I3<0,SUM(J3:N3),SUM(H3:N3)) -> -31.76 | P3: -2500 | Q3: -94 | R3: 0 | S3: 0 | T3: -500 | U3: 0 | V3: 0 | W3: =SUM(O3:V3) -> -3125.76 | X3: =IF(W3>=0,W3,0) -> 0 | Y3: =IF(W3<=0,W3,0) -> -3125.76 | Z3: 2800 | AA3: =+Y3+Z3 -> -325.76 | AB3: =+O3-X3+Z3+AA3 -> 2442.48 | AD3: DA RENTA POR FUERA HOJALATERIA 11/18, PAGA 2,800 11 ENE
A4: 1 | B4: FRANCISCO RODOLFO GOMEZ URQUIZA ESCALANTE | C4: KIA RIO|2020|AZUL|LUE960C | D4: OHLM035935635 | E4: ASHC | F4: ASHC | G4: DIDI | H4: 2721.77 | I4: -2373.6 | J4: -237 | K4: 0 | L4: 0 | M4: -95 | N4: 0 | O4: =IF(H4+I4<0,SUM(J4:N4),SUM(H4:N4)) -> 16.17 | P4: -2600 | Q4: 0 | R4: 0 | S4: 0 | T4: 0 | U4: 0 | V4: 0 | W4: =SUM(O4:V4) -> -2583.83 | X4: =IF(W4>=0,W4,0) -> 0 | Y4: =IF(W4<=0,W4,0) -> -2583.83 | Z4: 2857 | AA4: =+Y4+Z4 -> 273.17 | AB4: =+O4-X4+Z4+AA4 -> 3146.34 | AD4: TRABAJA DIDI-ASHC, PAGO 2,857 10 ENE (273 DE DIDI ATRASOS)
A5: 1 | B5: FRANCISCO ISLAS CHAVEZ | C5: AVEO|2024|GRIS|LRL009C | D5: OHLM032762171 | E5: ASHC | F5: ASHC | G5: DIDI | H5: 5249.01 | I5: -6142.27 | J5: -614 | K5: 0 | L5: 0 | M5: -95 | N5: 0 | O5: =IF(H5+I5<0,SUM(J5:N5),SUM(H5:N5)) -> -709 | P5: -2600 | Q5: 0 | R5: 0 | S5: 0 | T5: 0 | U5: 0 | V5: 0 | W5: =SUM(O5:V5) -> -3309 | X5: =IF(W5>=0,W5,0) -> 0 | Y5: =IF(W5<=0,W5,0) -> -3309 | Z5: =1200+1000 -> 2200 | AA5: =+Y5+Z5 -> -1109 | AB5: =+O5-X5+Z5+AA5 -> 382 | AD5: TRABAJA AMBAS APPS | PAGO 7 ENE 1,200 + 1,000 10 ENE GESTIONAR PAGO URGE
A6: 1 | B6: ADALBERTO BELLO NAVARRO | C6: AVEO|2025|PERSUASION|MXM510C | D6: OHLM038285821 | E6: ASHC | F6: ASHC | G6: UBER | H6: 8443.13 | I6: -5565.59 | J6: -20.8 | K6: 0 | L6: 0 | M6: -60 | N6: 0 | O6: =IF(H6+I6<0,SUM(J6:N6),SUM(H6:N6)) -> 2796.74 | P6: -2700 | Q6: 0 | R6: 0 | S6: 0 | T6: 0 | U6: 0 | V6: 0 | W6: =SUM(O6:V6) -> 96.74 | X6: =IF(W6>=0,W6,0) -> 96.74 | Y6: =IF(W6<=0,W6,0) -> 0 | Z6: 0 | AA6: =+Y6+Z6 -> 0 | AB6: =+O6-X6+Z6+AA6 -> 2700
A7: 1 | B7: ADRIAN CRUZ CUADROS | C7: AVEO|2025|PERSUASION|MXM503C | D7: OHLM038285813 | E7: ASHC | F7: ASHC | G7: UBER | H7: 6903.68 | I7: 0 | J7: -66.72 | K7: 19.58 | L7: 0 | M7: -77 | N7: -89 | O7: =IF(H7+I7<0,SUM(J7:N7),SUM(H7:N7)) -> 6690.54 | P7: -2700 | Q7: 0 | R7: 0 | S7: 0 | T7: 0 | U7: 0 | V7: 0 | W7: =SUM(O7:V7) -> 3990.54 | X7: =IF(W7>=0,W7,0) -> 3990.54 | Y7: =IF(W7<=0,W7,0) -> 0 | Z7: 0 | AA7: =+Y7+Z7 -> 0 | AB7: =+O7-X7+Z7+AA7 -> 2700
A8: 1 | B8: ALBERTO ARRIAGA MEJIA | C8: AVEO|2020|AZUL|D28BET | D8: OHLM032370140 | E8: ASHC | F8: ASHC | G8: UBER | H8: 1020.36 | I8: -59.93 | J8: -11.2 | K8: 0 | L8: 0 | M8: -63 | N8: -71 | O8: =IF(H8+I8<0,SUM(J8:N8),SUM(H8:N8)) -> 815.23 | P8: -2500 | Q8: 0 | R8: -500 | S8: 0 | T8: 0 | U8: 0 | V8: 0 | W8: =SUM(O8:V8) -> -2184.77 | X8: =IF(W8>=0,W8,0) -> 0 | Y8: =IF(W8<=0,W8,0) -> -2184.77 | Z8: =1100+1085 -> 2185 | AA8: =+Y8+Z8 -> 0.23 | AB8: =+O8-X8+Z8+AA8 -> 3000.46 | AD8: FIANZA 7/11 PAGO 7 ENE 1,100 + 1,085 8 ENE
A9: 1 | B9: ANGEL ALCANTARA CRUZ | C9: AVEO|2025|PERSUASION|MZN091C | D9: OHLM038626768 | E9: ASHC | F9: ASHC | G9: UBER | H9: 668.17 | I9: -29.99 | J9: -4.48 | K9: 0 | L9: 0 | M9: -60 | N9: 0 | O9: =IF(H9+I9<0,SUM(J9:N9),SUM(H9:N9)) -> 573.7 | P9: 0 | Q9: -737 | R9: 0 | S9: 0 | T9: 0 | U9: 0 | V9: 0 | W9: =SUM(O9:V9) -> -163.3 | X9: =IF(W9>=0,W9,0) -> 0 | Y9: =IF(W9<=0,W9,0) -> -163.3 | Z9: 0 | AA9: =+Y9+Z9 -> -163.3 | AB9: =+O9-X9+Z9+AA9 -> 410.4 | AD9: ADEUDO SEM ANT - PROB FAM HIJA LEUSEM PAGA EL LUNES SE CONDONA LA CUENTA
A10: 1 | B10: ARMANDO MARTINEZ VELAZQUEZ | C10: HYUNDAI|2022|PLATA|D40BKD | D10: OHLM023658024 | E10: ASHC | F10: ASHC | G10: UBER | H10: 922.84 | I10: 0 | J10: -4.48 | K10: 0 | L10: -8.49 | M10: -60 | N10: 0 | O10: =IF(H10+I10<0,SUM(J10:N10),SUM(H10:N10)) -> 849.87 | P10: -357.14286 | Q10: 0 | R10: 0 | S10: 0 | T10: -600 | U10: 0 | V10: 0 | W10: =SUM(O10:V10) -> -107.27286 | X10: =IF(W10>=0,W10,0) -> 0 | Y10: =IF(W10<=0,W10,0) -> -107.27286 | Z10: 0 | AA10: =+Y10+Z10 -> -107.27286 | AB10: =+O10-X10+Z10+AA10 -> 742.59714 | AD10: HOJALATERIA 2/5 PAGA HASTA LA SEM 3 SIN DESC DE HOJ
A11: 1 | B11: CAMILO IESUA MEJIA DIAZ | C11: KIA RIO|2020|GRIS|NCK475B | D11: OHLM032370124 | E11: ASHC | F11: ASHC | G11: UBER | H11: 2560.11 | I11: -491.67 | J11: -16.96 | K11: 106.1 | L11: 0 | M11: -60 | N11: 0 | O11: =IF(H11+I11<0,SUM(J11:N11),SUM(H11:N11)) -> 2097.58 | P11: -2500 | Q11: 0 | R11: -500 | S11: 0 | T11: 0 | U11: 0 | V11: 0 | W11: =SUM(O11:V11) -> -902.42 | X11: =IF(W11>=0,W11,0) -> 0 | Y11: =IF(W11<=0,W11,0) -> -902.42 | Z11: 902 | AA11: =+Y11+Z11 -> -0.42 | AB11: =+O11-X11+Z11+AA11 -> 2999.16 | AD11: FIANZA 5/10 PAGO 7 ENE 902
A12: 1 | B12: DAVID ARTURO GONZALEZ TELLEZ | C12: AVEO|2025|PERSUASION|MXM502C | D12: OHLM038285805 | E12: ASHC | F12: ASHC | G12: UBER | H12: 1605.6 | I12: -1702.64 | J12: -9.44 | K12: 0 | L12: 0 | M12: -86 | N12: -125.49 | O12: =IF(H12+I12<0,SUM(J12:N12),SUM(H12:N12)) -> -220.93 | P12: -771.42 | Q12: -4976 | R12: 0 | S12: 0 | T12: -700 | U12: 0 | V12: 0 | W12: =SUM(O12:V12) -> -6668.35 | X12: =IF(W12>=0,W12,0) -> 0 | Y12: =IF(W12<=0,W12,0) -> -6668.35 | Z12: =1000+1300+1000 -> 3300 | AA12: =+Y12+Z12 -> -3368.35 | AB12: =+O12-X12+Z12+AA12 -> -289.28 | AD12: CTA PROP 2 DIAS PQ SALIO CDMX,HOJALATERIA 11/26 - 1,300 9 ENE + 1,000 11 ENE 8ene 1000
A13: 1 | B13: FERNANDO FUENTES OTERO | C13: AVEOH|2024|BLANCO|MWV156C | D13: OHLM038626743 | E13: ASHC | F13: ASHC | G13: UBER | H13: 309.82 | I13: 0 | J13: 0 | K13: 0 | L13: 0 | M13: -60 | N13: 0 | O13: =IF(H13+I13<0,SUM(J13:N13),SUM(H13:N13)) -> 249.82 | P13: -2500 | Q13: -250 | R13: 0 | S13: 0 | T13: 0 | U13: 0 | V13: 0 | W13: =SUM(O13:V13) -> -2500.18 | X13: =IF(W13>=0,W13,0) -> 0 | Y13: =IF(W13<=0,W13,0) -> -2500.18 | Z13: =610+473+375+400+500+306 -> 2664 | AA13: =+Y13+Z13 -> 163.82 | AB13: =+O13-X13+Z13+AA13 -> 3077.64 | AD13: PAGO TRANSF ASHC 5 ENE 610, 473 9 ENE, 375 10 ENE, 400 10 ENE, 500 11 ENE, 306 11 ENE
A14: 1 | B14: FRANCISCO GOMEZ URQUIZA SILVA | C14: VERSA|2023|PLATA|NCT814A | D14: OHLM031491780 | E14: ASHC | F14: ASHC | G14: UBER | H14: 4543.72 | I14: -2246.92 | J14: -31.84 | K14: 0 | L14: 0 | M14: -65 | N14: 0 | O14: =IF(H14+I14<0,SUM(J14:N14),SUM(H14:N14)) -> 2199.96 | P14: -2500 | Q14: 0 | R14: -500 | S14: 0 | T14: 0 | U14: 0 | V14: 0 | W14: =SUM(O14:V14) -> -800.04 | X14: =IF(W14>=0,W14,0) -> 0 | Y14: =IF(W14<=0,W14,0) -> -800.04 | Z14: 800 | AA14: =+Y14+Z14 -> -0.04 | AB14: =+O14-X14+Z14+AA14 -> 2999.92 | AD14: FIANZA 5/10 - PAGO 800 6 ENE
A15: 1 | B15: FRANCISCO ISLAS CHAVEZ | C15: AVEO|2024|GRIS|LRL009C | D15: OHLM032762171 | E15: ASHC | F15: ASHC | G15: UBER | H15: 95.23 | I15: -80.21 | J15: 0 | K15: 0 | L15: 0 | M15: -15 | N15: 0 | O15: =IF(H15+I15<0,SUM(J15:N15),SUM(H15:N15)) -> 0.02 | P15: 0 | Q15: 0 | R15: 0 | S15: 0 | T15: 0 | U15: 0 | V15: 0 | W15: =SUM(O15:V15) -> 0.02 | X15: =IF(W15>=0,W15,0) -> 0.02 | Y15: =IF(W15<=0,W15,0) -> 0 | Z15: 0 | AA15: =+Y15+Z15 -> 0 | AB15: =+O15-X15+Z15+AA15 -> 0 | AD15: SE COBRA CTA COMPL EN DIDI
A16: 1 | B16: GERMAN LUSARRETA ROMERO | C16: AVEO|2021|GRIS|D51BHV | D16: OHLM037480324 | E16: ASHC | F16: ASHC | G16: UBER | H16: 5101.6 | I16: -1716.25 | J16: -23.84 | K16: 311.99 | L16: 0 | M16: -66.5 | N16: -25.87 | O16: =IF(H16+I16<0,SUM(J16:N16),SUM(H16:N16)) -> 3581.13 | P16: -2500 | Q16: 0 | R16: -500 | S16: 0 | T16: 0 | U16: 0 | V16: 0 | W16: =SUM(O16:V16) -> 581.13 | X16: =IF(W16>=0,W16,0) -> 581.13 | Y16: =IF(W16<=0,W16,0) -> 0 | Z16: 0 | AA16: =+Y16+Z16 -> 0 | AB16: =+O16-X16+Z16+AA16 -> 3000 | AD16: FIANZA 6/11
A17: 1 | B17: JESUS ROSALES GARCIA | C17: AVEOH|2026|ACERO|NEJ996C | D17: SIN TAG | E17: ASHC | F17: ASHC | G17: UBER | H17: 10752.02 | I17: -5054.19 | J17: -36.48 | K17: 0 | L17: 0 | M17: -65 | N17: 0 | O17: =IF(H17+I17<0,SUM(J17:N17),SUM(H17:N17)) -> 5596.35 | P17: =-357.14-2314.28 -> -2671.42 | Q17: 0 | R17: -500 | S17: 0 | T17: 0 | U17: 0 | V17: 0 | W17: =SUM(O17:V17) -> 2424.93 | X17: =IF(W17>=0,W17,0) -> 2424.93 | Y17: =IF(W17<=0,W17,0) -> 0 | Z17: 0 | AA17: =+Y17+Z17 -> 0 | AB17: =+O17-X17+Z17+AA17 -> 3171.42 | AD17: CTA PROPDEL LUNES 2,500, RESTO DE SEM 2700
A18: 1 | B18: JONATHAN BERNAL RODRIGUEZ | C18: AVEO|2018|GRIS|X59AWG | D18: OHLM031409063 | E18: ASHC | F18: ASHC | G18: UBER | H18: 2245.26 | I18: -363.75 | J18: 0 | K18: 0 | L18: -24.09 | M18: -140 | N18: -378.18 | O18: =IF(H18+I18<0,SUM(J18:N18),SUM(H18:N18)) -> 1339.24 | P18: -2500 | Q18: -627 | R18: -500 | S18: 0 | T18: 0 | U18: 0 | V18: 0 | W18: =SUM(O18:V18) -> -2287.76 | X18: =IF(W18>=0,W18,0) -> 0 | Y18: =IF(W18<=0,W18,0) -> -2287.76 | Z18: 1800 | AA18: =+Y18+Z18 -> -487.76 | AB18: =+O18-X18+Z18+AA18 -> 2651.48 | AD18: PAGA 1,800 10 ENE
A19: 1 | B19: JOSE GUILLERMO HERNANDEZ RAMIREZ | C19: AVEO|2023|GRIS|MLC126A | D19: OHLM037480332 | E19: ASHC | F19: ASHC | G19: UBER | H19: 7594.7 | I19: -3449.65 | J19: -36.48 | K19: 0 | L19: 0 | M19: -65 | N19: 0 | O19: =IF(H19+I19<0,SUM(J19:N19),SUM(H19:N19)) -> 4043.57 | P19: -1250 | Q19: -360 | R19: 0 | S19: 0 | T19: 0 | U19: 0 | V19: 0 | W19: =SUM(O19:V19) -> 2433.57 | X19: =IF(W19>=0,W19,0) -> 2433.57 | Y19: =IF(W19<=0,W19,0) -> 0 | Z19: 0 | AA19: =+Y19+Z19 -> 0 | AB19: =+O19-X19+Z19+AA19 -> 1610 | AD19: REDUCCION DE CTA 1/2
A20: 1 | B20: JOSE JUAN HERNANDEZ MEJIA | C20: VENTO|2020|GRIS|A19BDY | D20: OHLM038626750 | E20: ASHC | F20: ASHC | G20: UBER | H20: 7690.57 | I20: -3610.68 | J20: -76.96 | K20: 0 | L20: 0 | M20: -65 | N20: 0 | O20: =IF(H20+I20<0,SUM(J20:N20),SUM(H20:N20)) -> 3937.93 | P20: -2500 | Q20: -210 | R20: 0 | S20: 0 | T20: 0 | U20: 0 | V20: 0 | W20: =SUM(O20:V20) -> 1227.93 | X20: =IF(W20>=0,W20,0) -> 1227.93 | Y20: =IF(W20<=0,W20,0) -> 0 | Z20: 0 | AA20: =+Y20+Z20 -> 0 | AB20: =+O20-X20+Z20+AA20 -> 2710
A21: 1 | B21: JUAN CARLOS ZEA CRUZ | C21: AVEO|2019|PLATA|NEL860A | D21: OHLM032370132 | E21: ASHC | F21: ASHC | G21: UBER | H21: 2373.01 | I21: -218.08 | J21: 0 | K21: 0 | L21: 0 | M21: -60 | N21: 0 | O21: =IF(H21+I21<0,SUM(J21:N21),SUM(H21:N21)) -> 2094.93 | P21: -2500 | Q21: 0 | R21: -500 | S21: 0 | T21: 0 | U21: 0 | V21: 0 | W21: =SUM(O21:V21) -> -905.07 | X21: =IF(W21>=0,W21,0) -> 0 | Y21: =IF(W21<=0,W21,0) -> -905.07 | Z21: 605 | AA21: =+Y21+Z21 -> -300.07 | AB21: =+O21-X21+Z21+AA21 -> 2399.86 | AD21: FIANZA 3/11 PAGO 7 ENE 605 NO CONTESTA
A22: 1 | B22: KRISTOPHER ALEXANDER TORREALBA RAMOS | C22: VENTO|2017|GRIS|MMA672C | D22: OHLM023720279 | E22: ASHC | F22: ASHC | G22: UBER | H22: 3703.3 | I22: -2282.87 | J22: 0 | K22: 0 | L22: 0 | M22: -60 | N22: 0 | O22: =IF(H22+I22<0,SUM(J22:N22),SUM(H22:N22)) -> 1360.43 | P22: -1360 | Q22: 0 | R22: 0 | S22: 0 | T22: 0 | U22: 0 | V22: 0 | W22: =SUM(O22:V22) -> 0.43 | X22: =IF(W22>=0,W22,0) -> 0.43 | Y22: =IF(W22<=0,W22,0) -> 0 | Z22: 0 | AA22: =+Y22+Z22 -> 0 | AB22: =+O22-X22+Z22+AA22 -> 1360 | AD22: CTA PROPAL JUEVES, ABANDONA AUTO, NO SE LE REGRESA FIANZA NI PAGO.
A23: 1 | B23: MARCO ANTONIO FARIAS AVILES | C23: BEAT|2019|OCRE|MAY730C | D23: OHLM036759058 | E23: U64 | F23: ASHC | G23: UBER | H23: 1577.88 | I23: 0 | J23: -9.28 | K23: 0 | L23: 0 | M23: -65 | N23: 0 | O23: =IF(H23+I23<0,SUM(J23:N23),SUM(H23:N23)) -> 1503.6 | P23: -2500 | Q23: -76 | R23: -500 | S23: 0 | T23: 0 | U23: 0 | V23: 0 | W23: =SUM(O23:V23) -> -1572.4 | X23: =IF(W23>=0,W23,0) -> 0 | Y23: =IF(W23<=0,W23,0) -> -1572.4 | Z23: =1000+500 -> 1500 | AA23: =+Y23+Z23 -> -72.4 | AB23: =+O23-X23+Z23+AA23 -> 2931.2 | AD23: FIANZA 3/10 PAGO 7 ENE 1,000 Y 500 11 ENE
A24: 1 | B24: OSCAR BLANCAS NORIEGA | C24: VENTO|2020|GRIS|R66BER | D24: OHLM023720329 | E24: ASHC | F24: ASHC | G24: UBER | H24: 2073.67 | I24: -619.58 | J24: -14.4 | K24: 0 | L24: 0 | M24: -11 | N24: 0 | O24: =IF(H24+I24<0,SUM(J24:N24),SUM(H24:N24)) -> 1428.69 | P24: -1428.57 | Q24: 0 | R24: 0 | S24: 0 | T24: 0 | U24: 0 | V24: 0 | W24: =SUM(O24:V24) -> 0.12 | X24: =IF(W24>=0,W24,0) -> 0.12 | Y24: =IF(W24<=0,W24,0) -> 0 | Z24: 0 | AA24: =+Y24+Z24 -> 0 | AB24: =+O24-X24+Z24+AA24 -> 1428.57 | AD24: CTA PROP 4 DÍAS, SE BAJA VIE, ADEUDA HOJTRIA, LLAVE, Y LAV INTER (SIN DEV DE FIANZA)
A25: 1 | B25: RAYMUNDO CHAVEZ DELGADO | C25: AVEOH|2026|ACERO|NEJ971C | D25: SIN TAG | E25: ASHC | F25: ASHC | G25: UBER | H25: 3451.27 | I25: -1775.14 | J25: -16.96 | K25: 127.04 | L25: -42.97 | M25: -65 | N25: 0 | O25: =IF(H25+I25<0,SUM(J25:N25),SUM(H25:N25)) -> 1678.24 | P25: =-357.14-2314.28 -> -2671.42 | Q25: 0 | R25: -500 | S25: 0 | T25: 0 | U25: 0 | V25: 0 | W25: =SUM(O25:V25) -> -1493.18 | X25: =IF(W25>=0,W25,0) -> 0 | Y25: =IF(W25<=0,W25,0) -> -1493.18 | Z25: 0 | AA25: =+Y25+Z25 -> -1493.18 | AB25: =+O25-X25+Z25+AA25 -> 185.06 | AD25: CTA LUNES 2,500, MAR-DOM 2700, FIANZA 10/10 - QUEDA CON ROUS PAGO EN DOS EXHIBISIONES S2 746.5 Y S3 746.5 +12%
A26: 1 | B26: RICARDO HERNANDEZ ARIAS | C26: AVEO|2019|BLANCO|NBS225A | D26: OHLM038285797 | E26: ASHC | F26: ASHC | G26: UBER | H26: 7279.62 | I26: -277.08 | J26: -42.02 | K26: -5.32 | L26: 0 | M26: -65 | N26: 0 | O26: =IF(H26+I26<0,SUM(J26:N26),SUM(H26:N26)) -> 6890.2 | P26: -2500 | Q26: 0 | R26: 0 | S26: 0 | T26: -700 | U26: 0 | V26: 0 | W26: =SUM(O26:V26) -> 3690.2 | X26: =IF(W26>=0,W26,0) -> 3690.2 | Y26: =IF(W26<=0,W26,0) -> 0 | Z26: 0 | AA26: =+Y26+Z26 -> 0 | AB26: =+O26-X26+Z26+AA26 -> 3200 | AD26: HOJALATERIA 11/23
A27: 1 | B27: SAUL DOMINGUEZ VAZQUEZ | C27: VERSA|2020|BLANCO|A35BHD | D27: OHLM032370082 | E27: ASHC | F27: ASHC | G27: UBER | H27: 2853.66 | I27: -428.05 | J27: -34.56 | K27: 0 | L27: -23.35 | M27: -60 | N27: 0 | O27: =IF(H27+I27<0,SUM(J27:N27),SUM(H27:N27)) -> 2307.7 | P27: -2500 | Q27: 0 | R27: 0 | S27: 0 | T27: 0 | U27: 0 | V27: 0 | W27: =SUM(O27:V27) -> -192.3 | X27: =IF(W27>=0,W27,0) -> 0 | Y27: =IF(W27<=0,W27,0) -> -192.3 | Z27: 192 | AA27: =+Y27+Z27 -> -0.3 | AB27: =+O27-X27+Z27+AA27 -> 2499.4 | AD27: PAGA 192 6 ENE
A28: 1 | B28: SERGIO BALDERAS BAEZ | C28: AVEO|2022|AZUL|NZY685B | D28: OHLM032370116 | E28: ASHC | F28: ASHC | G28: UBER | H28: 5549.21 | I28: -1856.39 | J28: -18.88 | K28: 0 | L28: 0 | M28: -65 | N28: 0 | O28: =IF(H28+I28<0,SUM(J28:N28),SUM(H28:N28)) -> 3608.94 | P28: -2500 | Q28: 0 | R28: -500 | S28: 0 | T28: 0 | U28: -1000 | V28: 0 | W28: =SUM(O28:V28) -> -391.06 | X28: =IF(W28>=0,W28,0) -> 0 | Y28: =IF(W28<=0,W28,0) -> -391.06 | Z28: 391 | AA28: =+Y28+Z28 -> -0.06 | AB28: =+O28-X28+Z28+AA28 -> 3999.88 | AD28: FIANZA 7/10, PAGA ADEUDO 2/2 | PAGO 7 ENE 391
A29: 1 | B29: YOSHUA JARETH VALDEZ HERNANDEZ | C29: KIA RIO|2017|ROJO|MYE912A | D29: OHLM032762130 | E29: U64 | F29: BYER | G29: UBER | H29: 1169.28 | I29: -370.52 | J29: -4.48 | K29: 0 | L29: 0 | M29: -65 | N29: 0 | O29: =IF(H29+I29<0,SUM(J29:N29),SUM(H29:N29)) -> 729.28 | P29: -2500 | Q29: 871 | R29: 0 | S29: 0 | T29: 0 | U29: 0 | V29: 0 | W29: =SUM(O29:V29) -> -899.72 | X29: =IF(W29>=0,W29,0) -> 0 | Y29: =IF(W29<=0,W29,0) -> -899.72 | Z29: 900 | AA29: =+Y29+Z29 -> 0.28 | AB29: =+O29-X29+Z29+AA29 -> 1629.56 | AD29: SEM 817 A FAVOR, ADEUDO DE GOLPE 2018, $5000 SEMANALES - DEPOSITA 3,000 6 ENE (900 A CUENTA Y 2,100 GLPE PED)
A30: 1 | B30: JOSE AGUILAR SOTO | C30: AVEO|2020|AZUL|D28BET | D30: OHLM032370140 | E30: ASHC | F30: ASHC | G30: UBER | H30: 0 | I30: 0 | J30: 0 | K30: 0 | L30: 0 | M30: 0 | N30: 0 | O30: =IF(H30+I30<0,SUM(J30:N30),SUM(H30:N30)) -> 0 | P30: 0 | Q30: 0 | R30: 500 | S30: 0 | T30: 0 | U30: 0 | V30: 0 | W30: =SUM(O30:V30) -> 500 | X30: =IF(W30>=0,W30,0) -> 500 | Y30: =IF(W30<=0,W30,0) -> 0 | Z30: 0 | AA30: =+Y30+Z30 -> 0 | AB30: =+O30-X30+Z30+AA30 -> -500 | AD30: DEV FIANZA 7/10
A31: 1 | B31: RUBEN BERMEJO | C31: AVEO|2022|VINO|P62BHW | D31: OHLM037480340 | E31: ASHC | F31: BYER | G31: UBER | H31: 0 | I31: 0 | J31: 0 | K31: 0 | L31: 0 | M31: 0 | N31: 0 | O31: =IF(H31+I31<0,SUM(J31:N31),SUM(H31:N31)) -> 0 | P31: 0 | Q31: 0 | R31: 500 | S31: 0 | T31: 0 | U31: 0 | V31: 0 | W31: =SUM(O31:V31) -> 500 | X31: =IF(W31>=0,W31,0) -> 500 | Y31: =IF(W31<=0,W31,0) -> 0 | Z31: 0 | AA31: =+Y31+Z31 -> 0 | AB31: =+O31-X31+Z31+AA31 -> -500 | AD31: ULTIMO PAGO DE FIANZA
A32: 1 | B32: FIDEL ALEJANDRO SANCHEZ VERGARA | C32: VERSA|2023|PLATA|NCT814A | D32: OHLM031491780 | E32: ASHC | F32: ASHC | G32: UBER | H32: 0 | I32: 0 | J32: 0 | K32: 0 | L32: 0 | M32: 0 | N32: 0 | O32: =IF(H32+I32<0,SUM(J32:N32),SUM(H32:N32)) -> 0 | P32: 0 | Q32: 0 | R32: 500 | S32: 0 | T32: 0 | U32: 0 | V32: 0 | W32: =SUM(O32:V32) -> 500 | X32: =IF(W32>=0,W32,0) -> 500 | Y32: =IF(W32<=0,W32,0) -> 0 | Z32: 0 | AA32: =+Y32+Z32 -> 0 | AB32: =+O32-X32+Z32+AA32 -> -500 | AD32: DEV DE FIANZA 3/7
A33: 1 | B33: JOSE LUIS HERNANDEZ MEDINA | C33: AVEO|2018|GRIS|X59AWG | D33: OHLM031409063 | E33: ASHC | F33: ASHC | G33: UBER | H33: 0 | I33: 0 | J33: 0 | K33: 0 | L33: 0 | M33: 0 | N33: 0 | O33: =IF(H33+I33<0,SUM(J33:N33),SUM(H33:N33)) -> 0 | P33: 0 | Q33: 0 | R33: 0 | S33: 0 | T33: -700 | U33: 0 | V33: 0 | W33: =SUM(O33:V33) -> -700 | X33: =IF(W33>=0,W33,0) -> 0 | Y33: =IF(W33<=0,W33,0) -> -700 | Z33: 700 | AA33: =+Y33+Z33 -> 0 | AB33: =+O33-X33+Z33+AA33 -> 700 | AD33: TRABAJA APP JG UBER, HOJALATERIA 12/15 - PAGA 700 7 ENE
A34: 1 | B34: ALFONSO GONZALEZ MORALES | C34: SWIFT|2017|ROJO|X89ALV | D34: OHLM032370090 | E34: BYER | F34: BYER | G34: UBER | H34: 5950.53 | I34: -2088.56 | J34: -14.4 | K34: 14.69 | L34: 0 | M34: -62 | N34: 0 | O34: =IF(H34+I34<0,SUM(J34:N34),SUM(H34:N34)) -> 3800.26 | P34: -2500 | Q34: -600 | R34: 0 | S34: 0 | T34: -700 | U34: 0 | V34: 0 | W34: =SUM(O34:V34) -> 0.26 | X34: =IF(W34>=0,W34,0) -> 0.26 | Y34: =IF(W34<=0,W34,0) -> 0 | Z34: 0 | AA34: =+Y34+Z34 -> 0 | AB34: =+O34-X34+Z34+AA34 -> 3800 | AD34: ADEUDO SEMANA PASADA A 12%,HOJALATERIA 7/8
A35: 1 | B35: CRISTIAN HERNANDEZ MUNGUIA | C35: AVEOH|2026|ACERO|NEJ990C | D35: SIN TAG | E35: ASHC | F35: ASHC | G35: UBER | H35: 5116.35 | I35: -556.69 | J35: -11.68 | K35: 0 | L35: 0 | M35: -60 | N35: 0 | O35: =IF(H35+I35<0,SUM(J35:N35),SUM(H35:N35)) -> 4487.98 | P35: -1764.42 | Q35: 0 | R35: -500 | S35: 0 | T35: 0 | U35: 0 | V35: 0 | W35: =SUM(O35:V35) -> 2223.56 | X35: =IF(W35>=0,W35,0) -> 2223.56 | Y35: =IF(W35<=0,W35,0) -> 0 | Z35: 0 | AA35: =+Y35+Z35 -> 0 | AB35: =+O35-X35+Z35+AA35 -> 2264.42 | AD35: CTA PROP TRABAJO EN PLAT 1 DÍA 2,500 SEM RESTANTE 2,700.. FIANZA 6/11
A36: 1 | B36: EDUARDO LICONA GODINEZ | C36: KIA RIO|2020|ROJO|MFP751C | D36: OHLM036759090 | E36: ASHC | F36: ASHC | G36: UBER | H36: 5671.6 | I36: -4668.93 | J36: -18.88 | K36: 11.27 | L36: -64.21 | M36: -65 | N36: 0 | O36: =IF(H36+I36<0,SUM(J36:N36),SUM(H36:N36)) -> 865.85 | P36: -2500 | Q36: 6 | R36: -500 | S36: 0 | T36: 0 | U36: 0 | V36: 0 | W36: =SUM(O36:V36) -> -2128.15 | X36: =IF(W36>=0,W36,0) -> 0 | Y36: =IF(W36<=0,W36,0) -> -2128.15 | Z36: 2128 | AA36: =+Y36+Z36 -> -0.15 | AB36: =+O36-X36+Z36+AA36 -> 2993.7 | AD36: FIANZA 4/9 - PAGA 2,182 7 ENE
A37: 1 | B37: FERNANDO GARRIDO GARNICA | C37: AVEO|2018|ROJO|R51BKD | D37: OHLM032762106 | E37: U64 | F37: BYER | G37: UBER | H37: 5154.64 | I37: -2256.03 | J37: -17.28 | K37: 0 | L37: 0 | M37: -65 | N37: 0 | O37: =IF(H37+I37<0,SUM(J37:N37),SUM(H37:N37)) -> 2816.33 | P37: -2500 | Q37: 0 | R37: -500 | S37: 0 | T37: 0 | U37: 0 | V37: 0 | W37: =SUM(O37:V37) -> -183.67 | X37: =IF(W37>=0,W37,0) -> 0 | Y37: =IF(W37<=0,W37,0) -> -183.67 | Z37: 0 | AA37: =+Y37+Z37 -> -183.67 | AB37: =+O37-X37+Z37+AA37 -> 2632.66 | AD37: FIANZA 4/11
... A39: 1 | B39: IVAN MOGUEL PULIDO | C39: KIA RIO|2023|ROJO|H99BLC | D39: OHLM035993526 | E39: U64 | F39: BYER | G39: UBER | H39: 6575.11 | I39: -4131.59 | J39: -14.88 | K39: 0 | L39: -65.54 | M39: -65 | N39: 0 | O39: =IF(H39+I39<0,SUM(J39:N39),SUM(H39:N39)) -> 2298.1 | P39: -1250 | Q39: 0 | R39: 0 | S39: 0 | T39: 0 | U39: 0 | V39: 0 | W39: =SUM(O39:V39) -> 1048.1 | X39: =IF(W39>=0,W39,0) -> 1048.1 | Y39: =IF(W39<=0,W39,0) -> 0 | Z39: 0 | AA39: =+Y39+Z39 -> 0 | AB39: =+O39-X39+Z39+AA39 -> 1250 | AD39: REDUCCION DE CTA 1/2
A40: 1 | B40: RUBI ROBLES SALMERON | C40: BEAT|2020|GRIS|NFN014B | D40: OHLM032762148 | E40: U64 | F40: BYER | G40: UBER | H40: 4207.92 | I40: -1148.34 | J40: -18.88 | K40: 0 | L40: 0 | M40: -65 | N40: 0 | O40: =IF(H40+I40<0,SUM(J40:N40),SUM(H40:N40)) -> 2975.7 | P40: -2500 | Q40: -679 | R40: 0 | S40: 0 | T40: -500 | U40: 0 | V40: 0 | W40: =SUM(O40:V40) -> -703.3 | X40: =IF(W40>=0,W40,0) -> 0 | Y40: =IF(W40<=0,W40,0) -> -703.3 | Z40: =503+200 -> 703 | AA40: =+Y40+Z40 -> -0.3 | AB40: =+O40-X40+Z40+AA40 -> 3678.4 | AD40: HOJALATERIA 7/18,PROMESA DE PAGO DIA MARTES NO CONTESTA. PAGA 503 10 ENE Y 200 11 ENE
A41: 1 | B41: VICTOR HUGO RUIZ CASTILLO | C41: VERSA|2021|BLANCO|MEE228C | D41: OHLM036759082 | E41: ASHC | F41: BYER | G41: UBER | H41: 1302.83 | I41: -269.92 | J41: -4.48 | K41: 0 | L41: -18.81 | M41: -65 | N41: 0 | O41: =IF(H41+I41<0,SUM(J41:N41),SUM(H41:N41)) -> 944.62 | P41: -2500 | Q41: -87 | R41: -500 | S41: 0 | T41: 0 | U41: 0 | V41: 0 | W41: =SUM(O41:V41) -> -2142.38 | X41: =IF(W41>=0,W41,0) -> 0 | Y41: =IF(W41<=0,W41,0) -> -2142.38 | Z41: 2000 | AA41: =+Y41+Z41 -> -142.38 | AB41: =+O41-X41+Z41+AA41 -> 2802.24 | AD41: FIANZA 4/10, PROM PAGO DIA MARTES, PAGA 2,000 7 ENE
A42: 1 | B42: TOLENTINO JOSETH PEREZ GONZALEZ | C42: MARCH|2019|TURQ|MAY737C | D42: OHLM0367590666 | E42: BYER | F42: BYER | G42: UBER | H42: 1641.99 | I42: 0 | J42: -17.6 | K42: 0 | L42: -16.39 | M42: -60 | N42: 0 | O42: =IF(H42+I42<0,SUM(J42:N42),SUM(H42:N42)) -> 1548 | P42: -2500 | Q42: -2800 | R42: 0 | S42: 0 | T42: 0 | U42: 0 | V42: 0 | W42: =SUM(O42:V42) -> -3752 | X42: =IF(W42>=0,W42,0) -> 0 | Y42: =IF(W42<=0,W42,0) -> -3752 | Z42: 0 | AA42: =+Y42+Z42 -> -3752 | AB42: =+O42-X42+Z42+AA42 -> -2204 | AD42: NO CONTESTA
A43: 1 | B43: ADOLFO LOPEZ MARTINEZ | C43: VERSA|2020|ROJO|NLP172B | D43: OHLM032370108 | E43: ASHC | F43: ASHC | G43: UBER | H43: 0 | I43: 0 | J43: 0 | K43: 0 | L43: 0 | M43: 0 | N43: 0 | O43: =IF(H43+I43<0,SUM(J43:N43),SUM(H43:N43)) -> 0 | P43: -2500 | Q43: 0 | R43: 0 | S43: 0 | T43: 0 | U43: 0 | V43: 0 | W43: =SUM(O43:V43) -> -2500 | X43: =IF(W43>=0,W43,0) -> 0 | Y43: =IF(W43<=0,W43,0) -> -2500 | Z43: 2500 | AA43: =+Y43+Z43 -> 0 | AB43: =+O43-X43+Z43+AA43 -> 2500 | AD43: PAGO 7 ENE 2,500
A44: 1 | B44: NICASIO EMOS CONTRERAS | C44: AVEO|2025|PERSUASION|MZN057C | D44: OHLM038626735 | E44: ASHC | F44: ASHC | G44: UBER | H44: 0 | I44: 0 | J44: 0 | K44: 0 | L44: 0 | M44: 0 | N44: 0 | O44: =IF(H44+I44<0,SUM(J44:N44),SUM(H44:N44)) -> 0 | P44: -2000 | Q44: 0 | R44: 0 | S44: 0 | T44: 0 | U44: 0 | V44: 0 | W44: =SUM(O44:V44) -> -2000 | X44: =IF(W44>=0,W44,0) -> 0 | Y44: =IF(W44<=0,W44,0) -> -2000 | Z44: 2000 | AA44: =+Y44+Z44 -> 0 | AB44: =+O44-X44+Z44+AA44 -> 2000 | AD44: PAGO 5 ENE 2,000
A45: 1 | B45: OSCAR CONTRERAS ZUÑIGA | C45: AVEO|2022|VINO|P62BHW | D45: OHLM037480340 | E45: ASHC | F45: BYER | G45: UBER | H45: 10687.44 | I45: -6128.28 | J45: -65.92 | K45: 0 | L45: 0 | M45: -65 | N45: 0 | O45: =IF(H45+I45<0,SUM(J45:N45),SUM(H45:N45)) -> 4428.24 | P45: -2229 | Q45: 0 | R45: -429 | S45: 0 | T45: 0 | U45: 0 | V45: 0 | W45: =SUM(O45:V45) -> 1770.24 | X45: =IF(W45>=0,W45,0) -> 1770.24 | Y45: =IF(W45<=0,W45,0) -> 0 | Z45: 0 | AA45: =+Y45+Z45 -> 0 | AB45: =+O45-X45+Z45+AA45 -> 2658 | AD45: CTA PROP 5.5 DÍAS, FIANZA 1/8
A46: 1 | B46: DIEGO ISAID PULIDO | C46: AVEO|2023|VINO|R22BMR | D46: OHML037480316 | E46: ASHC | F46: ASHC | G46: UBER | H46: 3558.12 | I46: -1633.62 | J46: 0 | K46: 0 | L46: 0 | M46: -60 | N46: 0 | O46: =IF(H46+I46<0,SUM(J46:N46),SUM(H46:N46)) -> 1864.5 | P46: -2042.85 | Q46: 0 | R46: -393 | S46: 0 | T46: 0 | U46: 0 | V46: 0 | W46: =SUM(O46:V46) -> -571.35 | X46: =IF(W46>=0,W46,0) -> 0 | Y46: =IF(W46<=0,W46,0) -> -571.35 | Z46: 571 | AA46: =+Y46+Z46 -> -0.35 | AB46: =+O46-X46+Z46+AA46 -> 2435.15 | AD46: CTA PROP 5 DÍAS, FIANZA 1/10 PAGA 571 6 ENE
A47: 1 | B47: XAVIER ALAN LARA JIMENEZ | C47: AVEO|2022|AZUL|NZY685B | D47: OHLM032370116 | E47: ASHC | F47: ASHC | G47: UBER | H47: 2744.62 | I47: -1421.22 | J47: -20.48 | K47: 0 | L47: 0 | M47: -60 | N47: 0 | O47: =IF(H47+I47<0,SUM(J47:N47),SUM(H47:N47)) -> 1242.92 | P47: =-2500+357 -> -2143 | Q47: 0 | R47: -500 | S47: 0 | T47: 0 | U47: 0 | V47: 0 | W47: =SUM(O47:V47) -> -1400.08 | X47: =IF(W47>=0,W47,0) -> 0 | Y47: =IF(W47<=0,W47,0) -> -1400.08 | Z47: 1400 | AA47: =+Y47+Z47 -> -0.08 | AB47: =+O47-X47+Z47+AA47 -> 2642.84 | AD47: FIANZA 7/11 - PAGA 1,400 6 ENE
A48: 1 | B48: CRISTIAN HERNANDEZ MUNGUIA | C48: AVEO|2022|VINO|P62BHW | D48: OHLM037480340 | E48: ASHC | F48: BYER | G48: UBER | H48: 896.74 | I48: 0 | J48: -9.44 | K48: 19.58 | L48: 0 | M48: 0 | N48: 0 | O48: =IF(H48+I48<0,SUM(J48:N48),SUM(H48:N48)) -> 906.88 | P48: -907 | Q48: 0 | R48: 0 | S48: 0 | T48: 0 | U48: 0 | V48: 0 | W48: =SUM(O48:V48) -> -0.12 | X48: =IF(W48>=0,W48,0) -> 0 | Y48: =IF(W48<=0,W48,0) -> -0.12 | Z48: 0 | AA48: =+Y48+Z48 -> -0.12 | AB48: =+O48-X48+Z48+AA48 -> 906.76 | AD48: CTA PROP TRABAJO EN FLOTILLA
A49: 1 | B49: JESUS AURELIO NUNGARAY CASTILLO | C49: MARCH|2021|ROJO|NZU5163 | D49: OHLM03237015 | E49: ASHC | F49: ASHC | G49: DIDI | H49: 0 | I49: 0 | J49: 0 | K49: 0 | L49: 0 | M49: 0 | N49: 0 | O49: =IF(H49+I49<0,SUM(J49:N49),SUM(H49:N49)) -> 0 | P49: -2500 | Q49: 0 | R49: 0 | S49: 0 | T49: 0 | U49: 0 | V49: 0 | W49: =SUM(O49:V49) -> -2500 | X49: =IF(W49>=0,W49,0) -> 0 | Y49: =IF(W49<=0,W49,0) -> -2500 | Z49: 2500 | AA49: =+Y49+Z49 -> 0 | AB49: =+O49-X49+Z49+AA49 -> 2500 | AD49: GENERA EN DIDI COMO SOCIO
A50: 2 | B50: RAUL FRANCISCO VAZQUEZ CORTE | C50: V DRIVE|2023|GRIS|MXW453C | D50: OHLM038626776 | E50: ASHC | F50: ASHC | G50: DIDI | H50: 0 | I50: 0 | J50: 0 | K50: 0 | L50: 0 | M50: 0 | N50: 0 | O50: =IF(H50+I50<0,SUM(J50:N50),SUM(H50:N50)) -> 0 | P50: -2500 | Q50: =-326*1.12 -> -365.12 | R50: 0 | S50: 0 | T50: 0 | U50: 0 | V50: 0 | W50: =SUM(O50:V50) -> -2865.12 | X50: =IF(W50>=0,W50,0) -> 0 | Y50: =IF(W50<=0,W50,0) -> -2865.12 | Z50: 0 | AA50: =+Y50+Z50 -> -2865.12 | AB50: =+O50-X50+Z50+AA50 -> -2865.12 | AD50: PAGA EL DOMINGO
A51: 2 | B51: RAUL FRANCISCO VAZQUEZ CORTE | C51: VENTO|2017|GRIS|MMA672C | D51: OHLM023720279 | E51: ASHC | F51: ASHC | G51: DIDI | H51: 0 | I51: 0 | J51: 0 | K51: 0 | L51: 0 | M51: 0 | N51: 0 | O51: =IF(H51+I51<0,SUM(J51:N51),SUM(H51:N51)) -> 0 | P51: 0 | Q51: 0 | R51: 0 | S51: 0 | T51: -500 | U51: 0 | V51: 0 | W51: =SUM(O51:V51) -> -500 | X51: =IF(W51>=0,W51,0) -> 0 | Y51: =IF(W51<=0,W51,0) -> -500 | Z51: 0 | AA51: =+Y51+Z51 -> -500 | AB51: =+O51-X51+Z51+AA51 -> -500 | AD51: PAGA EL DOMINGO
A52: 2 | B52: FRANCISCO ISLAS CHAVEZ | C52: AVEO|2024|GRIS|LRL009C | D52: OHLM032762171 | E52: ASHC | F52: ASHC | G52: DIDI | H52: 4397 | I52: -4448 | J52: -444 | K52: 0 | L52: 0 | M52: -65 | N52: 0 | O52: =IF(H52+I52<0,SUM(J52:N52),SUM(H52:N52)) -> -509 | P52: -2600 | Q52: =-2002*1.12 -> -2242.24 | R52: 0 | S52: 0 | T52: 0 | U52: 0 | V52: 0 | W52: =SUM(O52:V52) -> -5351.24 | X52: =IF(W52>=0,W52,0) -> 0 | Y52: =IF(W52<=0,W52,0) -> -5351.24 | Z52: =600+700+1000+1300 -> 3600 | AA52: =+Y52+Z52 -> -1751.24 | AB52: =+O52-X52+Z52+AA52 -> 1339.76 | AD52: P12ENE 600 P14ENE 700 P16ENE 1000 P18ENE 1300
A53: 2 | B53: ADALBERTO BELLO NAVARRO | C53: AVEO|2025|PERSUASION|MXM510C | D53: OHLM038285821 | E53: ASHC | F53: ASHC | G53: UBER | H53: 4908 | I53: -3232 | J53: 0 | K53: 0 | L53: 0 | M53: -40 | N53: 0 | O53: =IF(H53+I53<0,SUM(J53:N53),SUM(H53:N53)) -> 1636 | P53: -2700 | Q53: 0 | R53: 0 | S53: 0 | T53: 0 | U53: 0 | V53: 0 | W53: =SUM(O53:V53) -> -1064 | X53: =IF(W53>=0,W53,0) -> 0 | Y53: =IF(W53<=0,W53,0) -> -1064 | Z53: 1000 | AA53: =+Y53+Z53 -> -64 | AB53: =+O53-X53+Z53+AA53 -> 2572 | AD53: PAGO 15 ENE 1000
A54: 2 | B54: ADRIAN CRUZ CUADROS | C54: AVEO|2025|PERSUASION|MXM503C | D54: OHLM038285813 | E54: ASHC | F54: ASHC | G54: UBER | H54: 5768 | I54: 0 | J54: -36 | K54: 31 | L54: 0 | M54: -85 | N54: -120 | O54: =IF(H54+I54<0,SUM(J54:N54),SUM(H54:N54)) -> 5558 | P54: -2700 | Q54: 0 | R54: 0 | S54: 0 | T54: 0 | U54: 0 | V54: 0 | W54: =SUM(O54:V54) -> 2858 | X54: =IF(W54>=0,W54,0) -> 2858 | Y54: =IF(W54<=0,W54,0) -> 0 | Z54: 0 | AA54: =+Y54+Z54 -> 0 | AB54: =+O54-X54+Z54+AA54 -> 2700
A55: 2 | B55: KEVIN ALEXIS MERLOS CORTES | C55: VENTO|2020|GRIS|R66BER | D55: OHLM02372032 | E55: ASHC | F55: ASHC | G55: UBER | H55: 4060 | I55: -2036 | J55: -54 | K55: 0 | L55: 0 | M55: -45 | N55: 0 | O55: =IF(H55+I55<0,SUM(J55:N55),SUM(H55:N55)) -> 1925 | P55: =-357.14*3 -> -1071.42 | Q55: 0 | R55: =-214 -> -214 | S55: 0 | T55: 0 | U55: 0 | V55: 0 | W55: =SUM(O55:V55) -> 639.58 | X55: =IF(W55>=0,W55,0) -> 639.58 | Y55: =IF(W55<=0,W55,0) -> 0 | Z55: 0 | AA55: =+Y55+Z55 -> 0 | AB55: =+O55-X55+Z55+AA55 -> 1285.42 | AC55: 2000 | AD55: SE DIO 2,000 DE FIANZA EN EFECTIVO
A56: 2 | B56: OSCAR IVAN MIÑON RAMIREZ | C56: MARCH|2020|TURQ|N15BKD | D56: OHLM03140907 | E56: ASHC | F56: ASHC | G56: UBER | H56: 6925 | I56: -3099 | J56: -139 | K56: 0 | L56: 0 | M56: -45 | N56: 0 | O56: =IF(H56+I56<0,SUM(J56:N56),SUM(H56:N56)) -> 3642 | P56: =(-2500/7)*5 -> -1785.7143 | Q56: 0 | R56: -357 | S56: 0 | T56: 0 | U56: 0 | V56: 0 | W56: =SUM(O56:V56) -> 1499.2857 | X56: =IF(W56>=0,W56,0) -> 1499.2857 | Y56: =IF(W56<=0,W56,0) -> 0 | Z56: 0 | AA56: =+Y56+Z56 -> 0 | AB56: =+O56-X56+Z56+AA56 -> 2142.7143 | AD56: INICIA MIER 7 26_CTA Y FIANZ PROP 5 DÍAS
A57: 2 | B57: DANIEL CASTAÑEDA LOPEZ | C57: AVEO|2020|AZUL|D28BET | D57: OHLM032370140 | E57: ASHC | F57: ASHC | G57: UBER | H57: 4467 | I57: -2397 | J57: 0 | K57: 0 | L57: 0 | M57: -55 | N57: 0 | O57: =IF(H57+I57<0,SUM(J57:N57),SUM(H57:N57)) -> 2015 | P57: =(-2500/7)*5.5 -> -1964.2857 | Q57: 0 | R57: =(-500/7)*5.5 -> -392.85714 | S57: 0 | T57: 0 | U57: 0 | V57: 0 | W57: =SUM(O57:V57) -> -342.14286 | X57: =IF(W57>=0,W57,0) -> 0 | Y57: =IF(W57<=0,W57,0) -> -342.14286 | Z57: 342 | AA57: =+Y57+Z57 -> -0.14285714 | AB57: =+O57-X57+Z57+AA57 -> 2356.8571 | AD57: INICIA MAR 6 26_CTA Y FIANZ PROP 5.5 DÍAS DEJA EN GARANTÍA 2 CARTERAS ORIG TOMY Y MKOR PAGO 16 ENE
A58: 2 | B58: JOEL RAUL PEREA PEÑA | C58: AVEO|2019|BLANCO|NBS225A | D58: OHLM038285797 | E58: ASHC | F58: ASHC | G58: UBER | H58: 1853 | I58: -1145 | J58: 0 | K58: 0 | M58: -45 | N58: 0 | O58: =IF(H58+I58<0,SUM(J58:N58),SUM(H58:N58)) -> 663 | P58: =(-2500/7)*3.5 -> -1250 | Q58: 0 | R58: =((-500/7)*3.5) -> -250 | S58: 0 | T58: 0 | U58: 0 | V58: 0 | W58: =SUM(O58:V58) -> -837 | X58: =IF(W58>=0,W58,0) -> 0 | Y58: =IF(W58<=0,W58,0) -> -837 | Z58: 0 | AA58: =+Y58+Z58 -> -837 | AB58: =+O58-X58+Z58+AA58 -> -174 | AC58: 1000 | AD58: INICIA JUE 8 26 ENTREGA 1000 FIANZA EN EFE MAÑANA PAGA UNA PARTE
A59: 2 | B59: JAVIER MEDINA JAIMES | C59: AVEO|2021|GRIS|D51BHV | D59: OHLM037480324 | E59: ASHC | F59: ASHC | G59: UBER | H59: 7562 | I59: -4538 | J59: 0 | K59: 0 | L59: 0 | M59: -55 | O59: =IF(H59+I59<0,SUM(J59:N59),SUM(H59:N59)) -> 2969 | P59: =(-2500/7)*6.5 -> -2321.4286 | Q59: 0 | R59: =(-500/7)*6.5 -> -464.28571 | S59: 0 | T59: 0 | U59: 0 | V59: 0 | W59: =SUM(O59:V59) -> 183.28571 | X59: =IF(W59>=0,W59,0) -> 183.28571 | Y59: =IF(W59<=0,W59,0) -> 0 | Z59: 0 | AA59: =+Y59+Z59 -> 0 | AB59: =+O59-X59+Z59+AA59 -> 2785.7143 | AD59: INICIA 5 ENE 26 DEJA EN GARANTÍA LAPTOP
A60: 2 | B60: ALBERTO ARRIAGA MEJIA | C60: AVEO|2020|AZUL|D28BET | D60: OHLM03864557 | E60: ASHC | F60: ASHC | G60: UBER | H60: 2482 | I60: -836 | J60: 0 | K60: 0 | L60: 0 | M60: -83 | N60: -71 | O60: =IF(H60+I60<0,SUM(J60:N60),SUM(H60:N60)) -> 1492 | P60: -2700 | Q60: 0 | R60: 0 | S60: 0 | T60: 0 | U60: 0 | V60: 0 | W60: =SUM(O60:V60) -> -1208 | X60: =IF(W60>=0,W60,0) -> 0 | Y60: =IF(W60<=0,W60,0) -> -1208 | AA60: =+Y60+Z60 -> -1208 | AB60: =+O60-X60+Z60+AA60 -> 284 | AD60: FIANZA 8/11 SE BAJA DEL AUTO 15 ENE CON ADEUDO Y NOS QUEDAMOS CON LA FIANZA
A61: 2 | B61: ANGEL ALCANTARA CRUZ | C61: AVEO|2025|PERSUASION|MZN091C | D61: OHLM038626768 | E61: ASHC | F61: ASHC | G61: UBER | H61: 2939 | I61: -866 | J61: 0 | K61: 0 | L61: 0 | M61: -45 | N61: 0 | O61: =IF(H61+I61<0,SUM(J61:N61),SUM(H61:N61)) -> 2028 | P61: -2700 | Q61: =-163 -> -163 | R61: 0 | S61: 0 | T61: 0 | U61: 0 | V61: 0 | W61: =SUM(O61:V61) -> -835 | X61: =IF(W61>=0,W61,0) -> 0 | Y61: =IF(W61<=0,W61,0) -> -835 | Z61: 835 | AA61: =+Y61+Z61 -> 0 | AB61: =+O61-X61+Z61+AA61 -> 2863 | AD61: PAGO 14 ENE 835
A62: 2 | B62: ARMANDO MARTINEZ VELAZQUEZ | C62: HYUNDAI|2022|PLATA|D40BKD | D62: OHLM023658024 | E62: ASHC | F62: ASHC | G62: UBER | H62: 3152 | I62: -100 | J62: -15 | K62: 0 | L62: -30 | M62: -45 | N62: 0 | O62: =IF(H62+I62<0,SUM(J62:N62),SUM(H62:N62)) -> 2962 | P62: =(-2500/7)*5 -> -1785.7143 | Q62: -120 | R62: 0 | S62: 0 | T62: 0 | U62: 0 | V62: 0 | W62: =SUM(O62:V62) -> 1056.2857 | X62: =IF(W62>=0,W62,0) -> 1056.2857 | Y62: =IF(W62<=0,W62,0) -> 0 | Z62: 0 | AA62: =+Y62+Z62 -> 0 | AB62: =+O62-X62+Z62+AA62 -> 1905.7143 | AD62: PIDIO Q EL DESC FUERA HASTA LA SEM 3
A63: 2 | B63: CAMILO IESUA MEJIA DIAZ | C63: KIA RIO|2020|GRIS|NCK475B | D63: OHLM032370124 | E63: ASHC | F63: ASHC | G63: UBER | H63: 2681 | I63: 0 | J63: 0 | K63: 0 | L63: 0 | M63: -55 | N63: 0 | O63: =IF(H63+I63<0,SUM(J63:N63),SUM(H63:N63)) -> 2626 | P63: -2500 | Q63: 0 | R63: -500 | S63: 0 | T63: 0 | U63: 0 | V63: 0 | W63: =SUM(O63:V63) -> -374 | X63: =IF(W63>=0,W63,0) -> 0 | Y63: =IF(W63<=0,W63,0) -> -374 | Z63: 374 | AA63: =+Y63+Z63 -> 0 | AB63: =+O63-X63+Z63+AA63 -> 3000 | AD63: FIANZA 6/10 PAGO 15 ENE EN EFECTIVO A ASHC
A64: 2 | B64: DAVID ARTURO GONZALEZ TELLEZ | C64: AVEO|2025|PERSUASION|MXM502C | D64: OHLM038285805 | E64: ASHC | F64: ASHC | G64: UBER | H64: 2331 | I64: -1666 | J64: 0 | K64: 0 | L64: 0 | M64: -62 | N64: -25 | O64: =IF(H64+I64<0,SUM(J64:N64),SUM(H64:N64)) -> 578 | P64: =-2700/7*4 -> -1542.8571 | Q64: =-3465*1.12 -> -3880.8 | R64: 0 | S64: 0 | T64: 0 | U64: 0 | V64: 0 | W64: =SUM(O64:V64) -> -4845.6571 | X64: =IF(W64>=0,W64,0) -> 0 | Y64: =IF(W64<=0,W64,0) -> -4845.6571 | Z64: =1400+500+1300+500 -> 3700 | AA64: =+Y64+Z64 -> -1145.6571 | AB64: =+O64-X64+Z64+AA64 -> 3132.3429 | AD64: P14ENE 1000|P14ENE 1400|P18ENE 1300
A65: 2 | B65: DAVID ARTURO GONZALEZ TELLEZ | C65: KIA RIO|2020|GRIS|NCK475B | D65: OHLM032370124 | E65: ASHC | F65: ASHC | G65: UBER | H65: 0 | I65: 0 | J65: 0 | K65: 0 | L65: 0 | M65: 0 | N65: 0 | O65: =IF(H65+I65<0,SUM(J65:N65),SUM(H65:N65)) -> 0 | P65: 0 | Q65: 0 | R65: 0 | S65: 0 | T65: -500 | U65: 0 | V65: 0 | W65: =SUM(O65:V65) -> -500 | X65: =IF(W65>=0,W65,0) -> 0 | Y65: =IF(W65<=0,W65,0) -> -500 | Z65: 500 | AA65: =+Y65+Z65 -> 0 | AB65: =+O65-X65+Z65+AA65 -> 500 | AD65: HOJALATERIA 12/26 P14ENE 1000 P18N 500
A66: 2 | B66: FERNANDO FUENTES OTERO | C66: AVEOH|2024|BLANCO|MWV156C | D66: OHLM038626743 | E66: ASHC | F66: ASHC | G66: UBER | H66: 127 | I66: 0 | J66: -3 | K66: 0 | L66: 0 | M66: -45 | N66: 0 | O66: =IF(H66+I66<0,SUM(J66:N66),SUM(H66:N66)) -> 79 | P66: -2500 | Q66: 164 | R66: 0 | S66: 0 | T66: 0 | U66: 0 | V66: 0 | W66: =SUM(O66:V66) -> -2257 | X66: =IF(W66>=0,W66,0) -> 0 | Y66: =IF(W66<=0,W66,0) -> -2257 | Z66: 0 | AA66: =+Y66+Z66 -> -2257 | AB66: =+O66-X66+Z66+AA66 -> -2178 | AD66: HOY PAGA
A67: 2 | B67: FERNANDO FUENTES OTERO | C67: KIA RIO|2020|ROJO|MFP751C | D67: OHLM036759090 | E67: ASHC | F67: ASHC | G67: UBER | H67: 0 | I67: 0 | J67: 0 | K67: 0 | L67: 0 | M67: 0 | N67: 0 | O67: =IF(H67+I67<0,SUM(J67:N67),SUM(H67:N67)) -> 0 | P67: 0 | Q67: 0 | R67: 0 | S67: 0 | T67: -500 | U67: 0 | V67: 0 | W67: =SUM(O67:V67) -> -500 | X67: =IF(W67>=0,W67,0) -> 0 | Y67: =IF(W67<=0,W67,0) -> -500 | Z67: 0 | AA67: =+Y67+Z67 -> -500 | AB67: =+O67-X67+Z67+AA67 -> -500 | AD67: HOJALAT 1/6 SE EMPIEZA A DESCONTAR DEBIDO A QUE NO FUE ARREGLADO A LA FECHA ACORDADA CON ROSA QUE ES 15DIC25| PENDIENTE COMPRA DE ANTENA Y DESCUENTO A CONDUCTOR
A68: 2 | B68: FRANCISCO GOMEZ URQUIZA SILVA | C68: VERSA|2023|PLATA|NCT814A | D68: OHLM031491780 | E68: ASHC | F68: ASHC | G68: UBER | H68: 4301 | I68: -1115 | J68: 0 | K68: 0 | L68: 0 | M68: -55 | N68: 0 | O68: =IF(H68+I68<0,SUM(J68:N68),SUM(H68:N68)) -> 3131 | P68: -1964 | Q68: 0 | R68: -500 | S68: 0 | T68: 0 | U68: 0 | V68: 0 | W68: =SUM(O68:V68) -> 667 | X68: =IF(W68>=0,W68,0) -> 667 | Y68: =IF(W68<=0,W68,0) -> 0 | Z68: 0 | AA68: =+Y68+Z68 -> 0 | AB68: =+O68-X68+Z68+AA68 -> 2464 | AD68: SE DESC 1.5 POR INGRESAR MECANC FIANZA 6/10
A69: 2 | B69: GERMAN LUSARRETA ROMERO | C69: AVEOH|2026|ROJO|NEZ108C | D69: OHLM037480324 | E69: ASHC | F69: ASHC | G69: UBER | H69: 5360 | I69: -2245 | J69: 0 | K69: 0 | L69: 0 | M69: -55 | N69: 0 | O69: =IF(H69+I69<0,SUM(J69:N69),SUM(H69:N69)) -> 3060 | P69: -2700 | Q69: 0 | R69: -500 | S69: 0 | T69: 0 | U69: 0 | V69: 0 | W69: =SUM(O69:V69) -> -140 | X69: =IF(W69>=0,W69,0) -> 0 | Y69: =IF(W69<=0,W69,0) -> -140 | Z69: 140 | AA69: =+Y69+Z69 -> 0 | AB69: =+O69-X69+Z69+AA69 -> 3200 | AD69: FIANZA 7/11 - PAGO 14 ENE 140
A70: 2 | B70: JESUS ROSALES GARCIA | C70: AVEOH|2026|ACERO|NEJ996C | D70: SIN TAG | E70: ASHC | F70: ASHC | G70: UBER | H70: 11323 | I70: -6879 | J70: -130 | K70: 0 | L70: 0 | M70: -55 | N70: 0 | O70: =IF(H70+I70<0,SUM(J70:N70),SUM(H70:N70)) -> 4259 | P70: -2700 | Q70: 0 | R70: -500 | S70: 0 | T70: 0 | U70: 0 | V70: 0 | W70: =SUM(O70:V70) -> 1059 | X70: =IF(W70>=0,W70,0) -> 1059 | Y70: =IF(W70<=0,W70,0) -> 0 | Z70: 0 | AA70: =+Y70+Z70 -> 0 | AB70: =+O70-X70+Z70+AA70 -> 3200 | AD70: FIANZA 7/10
A71: 2 | B71: JONATHAN BERNAL RODRIGUEZ | C71: AVEO|2018|GRIS|X59AWG | D71: OHLM031409063 | E71: ASHC | F71: ASHC | G71: UBER | H71: 1318 | I71: 0 | J71: 0 | K71: 0 | L71: -15 | M71: -140 | N71: -378 | O71: =IF(H71+I71<0,SUM(J71:N71),SUM(H71:N71)) -> 785 | P71: -2500 | Q71: =-488*1.12 -> -546.56 | R71: -500 | S71: 0 | T71: -700 | U71: 0 | V71: 0 | W71: =SUM(O71:V71) -> -3461.56 | X71: =IF(W71>=0,W71,0) -> 0 | Y71: =IF(W71<=0,W71,0) -> -3461.56 | Z71: 0 | AA71: =+Y71+Z71 -> -3461.56 | AB71: =+O71-X71+Z71+AA71 -> -2676.56 | AD71: FIANZA 4/11| HOJALATERIA 3 DE 11 ACUERDO CON ASHC
A72: 2 | B72: JOSE GUILLERMO HERNANDEZ RAMIREZ | C72: AVEO|2023|GRIS|MLC126A | D72: OHLM037480332 | E72: ASHC | F72: ASHC | G72: UBER | H72: 7847 | I72: -3913 | J72: -58 | K72: 0 | L72: 0 | M72: -55 | N72: 0 | O72: =IF(H72+I72<0,SUM(J72:N72),SUM(H72:N72)) -> 3821 | P72: -1250 | Q72: 34 | R72: 0 | S72: 0 | T72: 0 | U72: 0 | V72: 0 | W72: =SUM(O72:V72) -> 2605 | X72: =IF(W72>=0,W72,0) -> 2605 | Y72: =IF(W72<=0,W72,0) -> 0 | Z72: 0 | AA72: =+Y72+Z72 -> 0 | AB72: =+O72-X72+Z72+AA72 -> 1216 | AD72: REDUCCION DE CTA 2/2
A73: 2 | B73: JOSE JUAN HERNANDEZ MEJIA | C73: VENTO|2020|GRIS|A19BDY | D73: OHLM038626750 | E73: ASHC | F73: ASHC | G73: UBER | H73: 2216 | I73: -1483 | J73: 0 | K73: 0 | L73: 0 | M73: -55 | N73: 0 | O73: =IF(H73+I73<0,SUM(J73:N73),SUM(H73:N73)) -> 678 | P73: -2500 | Q73: 0 | R73: 0 | S73: 0 | T73: 0 | U73: 0 | V73: 0 | W73: =SUM(O73:V73) -> -1822 | X73: =IF(W73>=0,W73,0) -> 0 | Y73: =IF(W73<=0,W73,0) -> -1822 | Z73: 0 | AA73: =+Y73+Z73 -> -1822 | AB73: =+O73-X73+Z73+AA73 -> -1144 | AD73: SE COMUNICARÁ MÁS TARDE
A74: 2 | B74: JUAN CARLOS ZEA CRUZ | C74: AVEO|2019|PLATA|NEL860A | D74: OHLM032370132 | E74: ASHC | F74: ASHC | G74: UBER | H74: 2576 | I74: -1176 | J74: 0 | K74: 0 | L74: 0 | M74: -55 | N74: 0 | O74: =IF(H74+I74<0,SUM(J74:N74),SUM(H74:N74)) -> 1345 | P74: -2500 | Q74: =-300*1.12 -> -336 | R74: -500 | S74: 0 | T74: 0 | U74: 0 | V74: 0 | W74: =SUM(O74:V74) -> -1991 | X74: =IF(W74>=0,W74,0) -> 0 | Y74: =IF(W74<=0,W74,0) -> -1991 | Z74: 0 | AA74: =+Y74+Z74 -> -1991 | AB74: =+O74-X74+Z74+AA74 -> -646 | AD74: FIANZA 4/11 SE TUVO CONTACTO Y HASTA EL DOM PAGA
A75: 2 | B75: MARCO ANTONIO FARIAS AVILES | C75: BEAT|2019|OCRE|MAY730C | D75: OHLM036759058 | E75: U64 | F75: ASHC | G75: UBER | H75: 83 | I75: 0 | J75: 0 | K75: 0 | L75: 0 | M75: -65 | N75: 0 | O75: =IF(H75+I75<0,SUM(J75:N75),SUM(H75:N75)) -> 18 | P75: -2500 | Q75: =-72*1.12 -> -80.64 | R75: -500 | S75: 0 | T75: 0 | U75: 0 | V75: 0 | W75: =SUM(O75:V75) -> -3062.64 | X75: =IF(W75>=0,W75,0) -> 0 | Y75: =IF(W75<=0,W75,0) -> -3062.64 | Z75: =1450+1150 -> 2600 | AA75: =+Y75+Z75 -> -462.64 | AB75: =+O75-X75+Z75+AA75 -> 2155.36 | AD75: FIANZA 4/10 PAGA 13 ENE 1400 PAGO MIER 15 1150
A76: 2 | B76: RAYMUNDO CHAVEZ DELGADO | C76: AVEOH|2026|ACERO|NEJ971C | D76: SIN TAG | E76: ASHC | F76: ASHC | G76: UBER | H76: 5369 | I76: -1733 | J76: 0 | K76: 121 | L76: -70 | M76: -55 | N76: 0 | O76: =IF(H76+I76<0,SUM(J76:N76),SUM(H76:N76)) -> 3632 | P76: -2121 | Q76: =-746*1.12 -> -835.52 | R76: 0 | S76: 0 | T76: 0 | U76: -200 | V76: 0 | W76: =SUM(O76:V76) -> 475.48 | X76: =IF(W76>=0,W76,0) -> 475.48 | Y76: =IF(W76<=0,W76,0) -> 0 | Z76: 0 | AA76: =+Y76+Z76 -> 0 | AB76: =+O76-X76+Z76+AA76 -> 3156.52 | AD76: DESC 1 DÍA INACTIVO|REPARACIÓN ESTEREO|1/2 DEV SEM 1 746
A77: 2 | B77: RICARDO HERNANDEZ ARIAS | C77: VERSA|2022|GRIS|NES596C | D77: OHLM038285797 | E77: ASHC | F77: ASHC | G77: UBER | H77: 5975 | I77: -270 | J77: -24 | K77: 0 | L77: 0 | M77: -55 | N77: 0 | O77: =IF(H77+I77<0,SUM(J77:N77),SUM(H77:N77)) -> 5626 | P77: -2500 | Q77: 0 | R77: 0 | S77: 0 | T77: -700 | U77: 0 | V77: 0 | W77: =SUM(O77:V77) -> 2426 | X77: =IF(W77>=0,W77,0) -> 2426 | Y77: =IF(W77<=0,W77,0) -> 0 | Z77: 0 | AA77: =+Y77+Z77 -> 0 | AB77: =+O77-X77+Z77+AA77 -> 3200 | AD77: HOJALAT 12/23 ADEUDO AUT JGD
A78: 2 | B78: SAUL DOMINGUEZ VAZQUEZ | C78: VERSA|2020|BLANCO|A35BHD | D78: OHLM032370082 | E78: ASHC | F78: ASHC | G78: UBER | H78: 3225 | I78: -215 | J78: -8 | K78: 0 | L78: -28 | M78: -45 | N78: 0 | O78: =IF(H78+I78<0,SUM(J78:N78),SUM(H78:N78)) -> 2929 | P78: -2500 | Q78: 0 | R78: 0 | S78: 0 | T78: 0 | U78: 0 | V78: 0 | W78: =SUM(O78:V78) -> 429 | X78: =IF(W78>=0,W78,0) -> 429 | Y78: =IF(W78<=0,W78,0) -> 0 | Z78: 0 | AA78: =+Y78+Z78 -> 0 | AB78: =+O78-X78+Z78+AA78 -> 2500 | AD78: PENDIENTE ARREGLO DE CAJUELA SEM 3
A79: 2 | B79: SERGIO BALDERAS BAEZ | C79: AVEO|2022|AZUL|NZY685B | D79: OHLM032370116 | E79: ASHC | F79: ASHC | G79: UBER | H79: 3384 | I79: -1555 | J79: 0 | K79: 0 | L79: 0 | M79: -65 | N79: 0 | O79: =IF(H79+I79<0,SUM(J79:N79),SUM(H79:N79)) -> 1764 | P79: -2500 | Q79: 0 | R79: -500 | S79: 0 | T79: 0 | U79: 0 | V79: 0 | W79: =SUM(O79:V79) -> -1236 | X79: =IF(W79>=0,W79,0) -> 0 | Y79: =IF(W79<=0,W79,0) -> -1236 | Z79: 0 | AA79: =+Y79+Z79 -> -1236 | AB79: =+O79-X79+Z79+AA79 -> 528 | AD79: FIANZA 8/10 PAGA 236 CON INTERÉS
A80: 2 | B80: CRISTIAN HERNANDEZ MUNGUIA | C80: AVEOH|2026|ACERO|NEJ990C | D80: OHLM038645594 | E80: ASHC | F80: ASHC | G80: UBER | H80: 4400 | I80: -1177 | J80: -48 | K80: -120 | L80: 0 | M80: -175 | N80: -442 | O80: =IF(H80+I80<0,SUM(J80:N80),SUM(H80:N80)) -> 2438 | P80: -2700 | Q80: 0 | R80: -500 | S80: 0 | T80: 0 | U80: 0 | V80: 0 | W80: =SUM(O80:V80) -> -762 | X80: =IF(W80>=0,W80,0) -> 0 | Y80: =IF(W80<=0,W80,0) -> -762 | Z80: 762 | AA80: =+Y80+Z80 -> 0 | AB80: =+O80-X80+Z80+AA80 -> 3200 | AD80: FIANZA 7/11 PAGO 14 ENE 762
A81: 2 | B81: EDUARDO LICONA GODINEZ | C81: KIA RIO|2020|ROJO|MFP751C | D81: OHLM036759090 | E81: ASHC | F81: ASHC | G81: UBER | H81: 6079 | I81: -3904 | J81: -32 | K81: 0 | L81: -63 | M81: -55 | N81: 0 | O81: =IF(H81+I81<0,SUM(J81:N81),SUM(H81:N81)) -> 2025 | P81: -2321 | Q81: 0 | R81: -500 | S81: 0 | T81: 0 | U81: 0 | V81: 0 | W81: =SUM(O81:V81) -> -796 | X81: =IF(W81>=0,W81,0) -> 0 | Y81: =IF(W81<=0,W81,0) -> -796 | Z81: 796 | AA81: =+Y81+Z81 -> 0 | AB81: =+O81-X81+Z81+AA81 -> 2821 | AD81: FIANZA 5/9
A82: 2 | B82: RUBI ROBLES SALMERON | C82: VERSA|2021|BLANCO|MEE228C | D82: OHLM036759082 | E82: ASHC | F82: ASHC | G82: UBER | H82: 1733 | I82: -1446 | J82: 42 | K82: 0 | L82: 0 | M82: -45 | N82: 0 | O82: =IF(H82+I82<0,SUM(J82:N82),SUM(H82:N82)) -> 284 | P82: =(-2500/7)*4 -> -1428.5714 | Q82: 0 | R82: 0 | S82: 0 | T82: -500 | U82: 0 | V82: 0 | W82: =SUM(O82:V82) -> -1644.5714 | X82: =IF(W82>=0,W82,0) -> 0 | Y82: =IF(W82<=0,W82,0) -> -1644.5714 | Z82: 0 | AA82: =+Y82+Z82 -> -1644.5714 | AB82: =+O82-X82+Z82+AA82 -> -1360.5714 | AD82: CTA PROP 4 DÍAS HOLT 8/9 RUBÍ CON ADEUDO + INTERÉS
A83: 2 | B83: DIEGO ISAID PULIDO | C83: AVEO|2023|VINO|R22BMR | D83: OHML037480316 | E83: ASHC | F83: ASHC | G83: UBER | H83: 4271 | I83: -2461 | J83: 0 | K83: 0 | L83: 0 | M83: -55 | N83: 0 | O83: =IF(H83+I83<0,SUM(J83:N83),SUM(H83:N83)) -> 1755 | P83: -2500 | Q83: 0 | R83: -500 | S83: 0 | T83: 0 | U83: 0 | V83: 0 | W83: =SUM(O83:V83) -> -1245 | X83: =IF(W83>=0,W83,0) -> 0 | Y83: =IF(W83<=0,W83,0) -> -1245 | Z83: 1150 | AA83: =+Y83+Z83 -> -95 | AB83: =+O83-X83+Z83+AA83 -> 2810 | AD83: FIANZA 2/10 PAGO 14 ENE 1150
A84: 2 | B84: XAVIER ALAN LARA JIMENEZ | C84: AVEO|2022|AZUL|MUF515A | D84: OHLM032370116 | E84: ASHC | F84: ASHC | G84: UBER | H84: 2584 | I84: -379 | J84: 0 | K84: 0 | L84: 0 | M84: -45 | N84: 0 | O84: =IF(H84+I84<0,SUM(J84:N84),SUM(H84:N84)) -> 2160 | P84: -2500 | Q84: 0 | R84: -500 | S84: 0 | T84: 0 | U84: 0 | V84: 0 | W84: =SUM(O84:V84) -> -840 | X84: =IF(W84>=0,W84,0) -> 0 | Y84: =IF(W84<=0,W84,0) -> -840 | Z84: 840 | AA84: =+Y84+Z84 -> 0 | AB84: =+O84-X84+Z84+AA84 -> 3000 | AD84: FIANZA 8/11 TRANSF
A85: 2 | B85: ADOLFO LOPEZ MARTINEZ | C85: VERSA|2020|ROJO|NLP172B | D85: OHLM032370108 | E85: ASHC | F85: ASHC | G85: UBER | H85: 0 | I85: 0 | J85: 0 | K85: 0 | L85: 0 | M85: 0 | N85: 0 | O85: =IF(H85+I85<0,SUM(J85:N85),SUM(H85:N85)) -> 0 | P85: -2500 | Q85: 0 | R85: 0 | S85: 0 | T85: 0 | U85: 0 | V85: 0 | W85: =SUM(O85:V85) -> -2500 | X85: =IF(W85>=0,W85,0) -> 0 | Y85: =IF(W85<=0,W85,0) -> -2500 | Z85: 2500 | AA85: =+Y85+Z85 -> 0 | AB85: =+O85-X85+Z85+AA85 -> 2500 | AD85: PAGA 2,500 13 ENE
A86: 2 | B86: NICASIO EMOS CONTRERAS | C86: AVEO|2025|PERSUASION|MZN057C | D86: OHLM038626735 | E86: ASHC | F86: ASHC | G86: UBER | H86: 0 | I86: 0 | J86: 0 | K86: 0 | L86: 0 | M86: 0 | N86: 0 | O86: =IF(H86+I86<0,SUM(J86:N86),SUM(H86:N86)) -> 0 | P86: -2000 | Q86: 0 | R86: 0 | S86: 0 | T86: 0 | U86: 0 | V86: 0 | W86: =SUM(O86:V86) -> -2000 | X86: =IF(W86>=0,W86,0) -> 0 | Y86: =IF(W86<=0,W86,0) -> -2000 | Z86: 2000 | AA86: =+Y86+Z86 -> 0 | AB86: =+O86-X86+Z86+AA86 -> 2000 | AD86: PAGO 14 ENE 2000
A87: 2 | B87: JOSE LUIS HERNANDEZ MEDINA | C87: AVEO|2018|GRIS|X59AWG | D87: OHLM031409063 | E87: ASHC | F87: ASHC | G87: UBER | H87: 0 | I87: 0 | J87: 0 | K87: 0 | L87: 0 | M87: 0 | N87: 0 | O87: =IF(H87+I87<0,SUM(J87:N87),SUM(H87:N87)) -> 0 | P87: 0 | Q87: 0 | R87: 0 | S87: 0 | T87: -700 | U87: 0 | V87: 0 | W87: =SUM(O87:V87) -> -700 | X87: =IF(W87>=0,W87,0) -> 0 | Y87: =IF(W87<=0,W87,0) -> -700 | Z87: 700 | AA87: =+Y87+Z87 -> 0 | AB87: =+O87-X87+Z87+AA87 -> 700 | AD87: HOJALATERIA 13 DE 15
A88: 2 | B88: JOSE AGUILAR SOTO | C88: AVEO|2020|AZUL|D28BET | D88: OHLM032370140 | E88: ASHC | F88: ASHC | G88: UBER | H88: 0 | I88: 0 | J88: 0 | K88: 0 | L88: 0 | M88: 0 | N88: 0 | O88: =IF(H88+I88<0,SUM(J88:N88),SUM(H88:N88)) -> 0 | P88: 0 | Q88: 0 | R88: 500 | S88: 0 | T88: 0 | U88: 0 | V88: 0 | W88: =SUM(O88:V88) -> 500 | X88: =IF(W88>=0,W88,0) -> 500 | Y88: =IF(W88<=0,W88,0) -> 0 | Z88: 0 | AA88: =+Y88+Z88 -> 0 | AB88: =+O88-X88+Z88+AA88 -> -500 | AD88: DEV FIANZA 8/10 PAGO 14 ENE
A89: 2 | B89: FIDEL ALEJANDRO SANCHEZ VERGARA | C89: VERSA|2023|PLATA|NCT814A | D89: OHLM031491780 | E89: ASHC | F89: ASHC | G89: UBER | H89: 0 | I89: 0 | J89: 0 | K89: 0 | L89: 0 | M89: 0 | N89: 0 | O89: =IF(H89+I89<0,SUM(J89:N89),SUM(H89:N89)) -> 0 | P89: 0 | Q89: 0 | R89: 500 | S89: 0 | T89: 0 | U89: 0 | V89: 0 | W89: =SUM(O89:V89) -> 500 | X89: =IF(W89>=0,W89,0) -> 500 | Y89: =IF(W89<=0,W89,0) -> 0 | Z89: 0 | AA89: =+Y89+Z89 -> 0 | AB89: =+O89-X89+Z89+AA89 -> -500 | AD89: DEV DE FIANZA 4/7
A90: 2 | B90: RUBI ROBLES SALMERON | C90: BEAT|2020|GRIS|NFN014B | D90: OHLM032762148 | E90: U64 | F90: BYER | G90: UBER | H90: 1239.72 | I90: -477.02 | J90: 0 | K90: 0 | L90: 0 | M90: -13 | N90: 0 | O90: =IF(H90+I90<0,SUM(J90:N90),SUM(H90:N90)) -> 749.7 | P90: =(-2500/7)*3 -> -1071.4286 | Q90: 0 | R90: 0 | S90: 0 | T90: 0 | U90: 0 | V90: 0 | W90: =SUM(O90:V90) -> -321.72857 | X90: =IF(W90>=0,W90,0) -> 0 | Y90: =IF(W90<=0,W90,0) -> -321.72857 | Z90: 0 | AA90: =+Y90+Z90 -> -321.72857 | AB90: =+O90-X90+Z90+AA90 -> 427.97143 | AD90: CTA PROP 3 DÍAS SE PASA A ASHC
A91: 2 | B91: ALFONSO GONZALEZ MORALES | C91: SWIFT|2017|ROJO|X89ALV | D91: OHLM032370090 | E91: BYER | F91: BYER | G91: UBER | H91: 4267.65 | I91: -1721.5 | J91: 0 | K91: 0 | L91: 0 | M91: -65 | N91: 0 | O91: =IF(H91+I91<0,SUM(J91:N91),SUM(H91:N91)) -> 2481.15 | P91: -2500 | Q91: 0 | R91: 0 | S91: 0 | T91: -700 | U91: 0 | V91: 0 | W91: =SUM(O91:V91) -> -718.85 | X91: =IF(W91>=0,W91,0) -> 0 | Y91: =IF(W91<=0,W91,0) -> -718.85 | Z91: 0 | AA91: =+Y91+Z91 -> -718.85 | AB91: =+O91-X91+Z91+AA91 -> 1762.3 | AD91: ULTIMO PAGO HOJALATERIA EN VISTO
A92: 2 | B92: FERNANDO GARRIDO GARNICA | C92: AVEO|2018|ROJO|R51BKD | D92: OHLM032762106 | E92: U64 | F92: BYER | G92: UBER | H92: 3021.98 | I92: -1761.68 | J92: 0 | K92: 0 | L92: 0 | M92: -65 | N92: 0 | O92: =IF(H92+I92<0,SUM(J92:N92),SUM(H92:N92)) -> 1195.3 | P92: -2500 | Q92: =-184*1.12 -> -206.08 | R92: -500 | S92: 0 | T92: 0 | U92: 0 | V92: 0 | W92: =SUM(O92:V92) -> -2010.78 | X92: =IF(W92>=0,W92,0) -> 0 | Y92: =IF(W92<=0,W92,0) -> -2010.78 | Z92: 0 | AA92: =+Y92+Z92 -> -2010.78 | AB92: =+O92-X92+Z92+AA92 -> -815.48 | AD92: NO CONTESTA
A93: 2 | B93: GABRIEL JIMENEZ BAUTISTA | C93: BYD|2026|VERDE|78F032 | D93: OHLM038628194 | E93: ASHC | F93: BYER | G93: UBER | H93: 5181.27 | I93: 0 | J93: 0 | K93: 9.79 | L93: 0 | M93: 0 | N93: 0 | O93: =IF(H93+I93<0,SUM(J93:N93),SUM(H93:N93)) -> 5191.06 | P93: -5191 | Q93: 0 | R93: 0 | S93: 0 | T93: 0 | U93: 0 | V93: 0 | W93: =SUM(O93:V93) -> 0.06 | X93: =IF(W93>=0,W93,0) -> 0.06 | Y93: =IF(W93<=0,W93,0) -> 0 | Z93: 0 | AA93: =+Y93+Z93 -> 0 | AB93: =+O93-X93+Z93+AA93 -> 5191 | AD93: GOLPE KIA Y BYD PENDIENTE CON ASHC
A94: 2 | B94: IVAN MOGUEL PULIDO | C94: KIA RIO|2023|ROJO|H99BLC | D94: OHLM035993526 | E94: U64 | F94: BYER | G94: UBER | H94: 7676.14 | I94: -2792.78 | J94: -80 | K94: 19.58 | L94: -84.32 | M94: -65 | N94: 0 | O94: =IF(H94+I94<0,SUM(J94:N94),SUM(H94:N94)) -> 4673.62 | P94: -1250 | Q94: 0 | R94: 0 | S94: 0 | T94: 0 | U94: 0 | V94: 0 | W94: =SUM(O94:V94) -> 3423.62 | X94: =IF(W94>=0,W94,0) -> 3423.62 | Y94: =IF(W94<=0,W94,0) -> 0 | Z94: 0 | AA94: =+Y94+Z94 -> 0 | AB94: =+O94-X94+Z94+AA94 -> 1250 | AD94: REDUCCION DE CTA 2/2
A95: 2 | B95: VICTOR HUGO RUIZ CASTILLO | C95: VERSA|2021|BLANCO|MEE228C | D95: OHLM036759082 | E95: ASHC | F95: BYER | G95: UBER | H95: 131.11 | I95: 0 | J95: 0 | K95: 0 | L95: -1.48 | M95: -40 | N95: 0 | O95: =IF(H95+I95<0,SUM(J95:N95),SUM(H95:N95)) -> 89.63 | P95: =(-2500/7)*4 -> -1428.5714 | Q95: =-142*1.12 -> -159.04 | R95: -500 | S95: 0 | T95: 0 | U95: 0 | V95: 0 | W95: =SUM(O95:V95) -> -1997.9814 | X95: =IF(W95>=0,W95,0) -> 0 | Y95: =IF(W95<=0,W95,0) -> -1997.9814 | Z95: 694 | AA95: =+Y95+Z95 -> -1303.9814 | AB95: =+O95-X95+Z95+AA95 -> -520.35143 | AD95: GOLPE FASCIA PENDIENTE 1500 POR KIA, PEND Q CONFIRME SEM DE ARREGLO PAGA 16
A96: 2 | B96: TOLENTINO JOSETH PEREZ GONZALEZ | C96: MARCH|2019|TURQ|MAY737C | D96: OHLM0367590666 | E96: BYER | F96: BYER | G96: UBER | H96: 2542.21 | I96: -328.85 | J96: 0 | K96: 0 | L96: -26.74 | M96: -35 | N96: 0 | O96: =IF(H96+I96<0,SUM(J96:N96),SUM(H96:N96)) -> 2151.62 | P96: -2500 | Q96: =-3752*1.12 -> -4202.24 | R96: 0 | S96: 0 | T96: 0 | U96: 0 | V96: 0 | W96: =SUM(O96:V96) -> -4550.62 | X96: =IF(W96>=0,W96,0) -> 0 | Y96: =IF(W96<=0,W96,0) -> -4550.62 | Z96: 0 | AA96: =+Y96+Z96 -> -4550.62 | AB96: =+O96-X96+Z96+AA96 -> -2399 | AD96: PROMESA DE PAGO 19 ENE ACUERDO CON BYER
A97: 2 | B97: OSCAR CONTRERAS ZUÑIGA | C97: AVEO|2022|VINO|P62BHW | D97: OHLM037480340 | E97: ASHC | F97: BYER | G97: UBER | H97: 11557.6 | I97: -5195.35 | J97: -64 | K97: 0 | L97: 0 | M97: -72 | N97: 0 | O97: =IF(H97+I97<0,SUM(J97:N97),SUM(H97:N97)) -> 6226.25 | P97: -2500 | Q97: 0 | R97: -500 | S97: 0 | T97: 0 | U97: 0 | V97: 0 | W97: =SUM(O97:V97) -> 3226.25 | X97: =IF(W97>=0,W97,0) -> 3226.25 | Y97: =IF(W97<=0,W97,0) -> 0 | Z97: 0 | AA97: =+Y97+Z97 -> 0 | AB97: =+O97-X97+Z97+AA97 -> 3000
A98: 2 | B98: YOSHUA JARETH VALDEZ HERNANDEZ | C98: KIA RIO|2017|ROJO|MYE912A | D98: OHLM032762130 | E98: U64 | F98: BYER | G98: UBER | H98: 2249.15 | I98: -238.94 | J98: 0 | K98: 0 | L98: 0 | M98: -20 | N98: 0 | O98: =IF(H98+I98<0,SUM(J98:N98),SUM(H98:N98)) -> 1990.21 | P98: -2500 | Q98: 0 | R98: 0 | S98: 0 | T98: 0 | U98: 0 | V98: 0 | W98: =SUM(O98:V98) -> -509.79 | X98: =IF(W98>=0,W98,0) -> 0 | Y98: =IF(W98<=0,W98,0) -> -509.79 | Z98: 510 | AA98: =+Y98+Z98 -> 0.21 | AB98: =+O98-X98+Z98+AA98 -> 2500.42 | AD98: PENDIENTE CAMBIO DE COCHE VENTO O KIA PAGO 16 ENE 510
A99: 2 | B99: JUAN PABLO COLIN HERMENEGILDO | C99: VENTO|2017|GRIS|MMA672C | D99: OHLM023720279 | E99: ASHC | F99: BYER | G99: UBER | H99: 411.71 | I99: -106.37 | J99: 0 | K99: 0 | L99: 0 | M99: -19 | N99: 0 | O99: =IF(H99+I99<0,SUM(J99:N99),SUM(H99:N99)) -> 286.34 | P99: =(-2300/7)*1.5 -> -492.85714 | Q99: 0 | R99: 0 | S99: 0 | T99: 0 | U99: 0 | V99: 0 | W99: =SUM(O99:V99) -> -206.51714 | X99: =IF(W99>=0,W99,0) -> 0 | Y99: =IF(W99<=0,W99,0) -> -206.51714 | Z99: 207 | AA99: =+Y99+Z99 -> 0.48285714 | AB99: =+O99-X99+Z99+AA99 -> 493.82286 | AD99: INGRESA MIE 7 SE CONSIDERA 1.5 DÍAS PAGO 14 ENE 207
A100: 2 | B100: JESUS AURELIO NUNGARAY CASTILLO | C100: MARCH|2021|ROJO|NZU5163 | D100: OHLM03237015 | E100: ASHC | F100: ASHC | G100: DIDI | H100: 0 | I100: 0 | J100: 0 | K100: 0 | L100: 0 | M100: 0 | N100: 0 | O100: =IF(H100+I100<0,SUM(J100:N100),SUM(H100:N100)) -> 0 | P100: -2500 | Q100: 0 | R100: 0 | S100: 0 | T100: 0 | U100: 0 | V100: 0 | W100: =SUM(O100:V100) -> -2500 | X100: =IF(W100>=0,W100,0) -> 0 | Y100: =IF(W100<=0,W100,0) -> -2500 | Z100: 2500 | AA100: =+Y100+Z100 -> 0 | AB100: =+O100-X100+Z100+AA100 -> 2500 | AD100: GENERA EN DIDI COMO SOCIO
A101: 3 | B101: RAUL FRANCISCO VAZQUEZ CORTE | C101: V DRIVE|2023|GRIS|MXW453C | D101: OHLM038626776 | E101: ASHC | F101: ASHC | G101: DIDI | H101: 0 | I101: 0 | J101: 0 | K101: 0 | L101: 0 | M101: 0 | N101: 0 | O101: =IF(H101+I101<0,SUM(J101:N101),SUM(H101:N101)) -> 0 | P101: -2500 | Q101: =-2865*1.12 -> -3208.8 | R101: 0 | S101: 0 | T101: 0 | U101: 0 | V101: 0 | W101: =SUM(O101:V101) -> -5708.8 | X101: =IF(W101>=0,W101,0) -> 0 | Y101: =IF(W101<=0,W101,0) -> -5708.8 | Z101: =1940+2000+1150+850 -> 5940 | AA101: =+Y101+Z101 -> 231.2 | AB101: =+O101-X101+Z101+AA101 -> 6171.2 | AD101: ADEUDO DE LAS SEM2 +12% - P 20ENE $1000 P21ENE$1000-P22ENE $1000-P24ENE $2000 P26$1150 P27 $850
...

Sheet Gastos 2025
A1: Semana | B1: MES | C1: Fecha | D1: Solicitante | E1: CONCEPTO | F1: DETALLE | G1: CONDUCTOR | H1: DETALLE | I1: PTTO | J1: SOCIO | K1: METODO DE PAGO | L1: PLAN | M1: REAL | N1: INGRESOS | O1: COMERCIO | P1: COMENTARIOS | Q1: ADICIONAL
A2: =WEEKNUM(C2) -> 36 | B2: 9 | C2: 45901 | D2: NAYE | F2: PRESUPUESTOS | H2: ADMINISTRATIVO | J2: ASHC | N2: =21060+1500+500+330+15100 -> 38490 | P2: VARIOS PRESUPUESTOS | Q2: 21,060 DEPOSITO NAYE BBVA, 1,500 EFECTIVO YUL, 500 EFECTIVO YUL, 330 CUENTA DE FERNANDO F, 15,100 DEPOISITO 11-09
A3: =WEEKNUM(C3) -> 34 | B3: 8 | C3: 45891 | D3: NAYE | F3: PAGO DE GESTORIA JG | H3: VENTO|2019|BLANCO|MGC410C | I3: REAL | J3: JGD | M3: 1300 | P3: PAGA SANTIAGO CON BBVA ORO | Q3: -
A4: =WEEKNUM(C4) -> 34 | B4: 8 | C4: 45891 | D4: NAYE | F4: PAGO DE GESTORIA JG | H4: VENTO|2020|GRIS|MGC414C | I4: REAL | J4: JGD | M4: 1300 | P4: PAGA SANTIAGO CON BBVA ORO | Q4: -
A5: =WEEKNUM(C5) -> 34 | B5: 8 | C5: 45891 | D5: NAYE | F5: PAGO DE GESTORIA JG | H5: MARCH|2021|BLANCO|MGC417C | I5: REAL | J5: JGD | M5: 1300 | P5: PAGA SANTIAGO CON BBVA ORO | Q5: -
A6: =WEEKNUM(C6) -> 34 | B6: 8 | C6: 45892 | D6: NAYE | F6: SOLDADURA DEL PEDAL DEL CLUTCH | H6: MARCH|2020|TURQ|NI5BKD | I6: REAL | J6: ASHC | M6: 400 | P6: PENDIENTE NAYE | Q6: -
A7: =WEEKNUM(C7) -> 35 | B7: 8 | C7: 45899 | D7: NAYE | F7: BASURA | H7: ADMINISTRATIVO | I7: REAL | J7: ASHC | M7: 50 | P7: PENDIENTE NAYE | Q7: -
A8: =WEEKNUM(C8) -> 36 | B8: 9 | C8: 45902 | D8: NAYE | F8: PAGO DE HOJALATERIA | H8: CAMIONETA SUSUKI EXTERNA | I8: REAL | J8: ASHC | M8: 4800 | P8: SE PAGA CON EL SALDO DE SANTIAGO | Q8: -
A9: =WEEKNUM(C9) -> 36 | B9: 9 | C9: 45902 | D9: NAYE | F9: GASOLINA PARA MOTO VENTO OP. | H9: MOTO OPERATIVA | I9: REAL | J9: ASHC | M9: 100 | P9: PENDIENTE A GABRIEL | Q9: -
A10: =WEEKNUM(C10) -> 36 | B10: 9 | C10: 45902 | D10: NAYE | F10: VENTA DE GASOLINA +10% | H10: VERSA|2023|PLATA|NCT814A | I10: REAL | J10: ASHC | M10: 1000 | P10: PENDIENTE NAYE | Q10: -
A11: =WEEKNUM(C11) -> 36 | B11: 9 | C11: 45902 | D11: NAYE | F11: REPARACIÓN DE LLANTA | H11: MARCH|2020|TURQ|MAY737C | I11: REAL | J11: BYER | M11: 350 | P11: DESCUENTO A YOSHUA | Q11: -
A12: =WEEKNUM(C12) -> 36 | B12: 9 | C12: 45902 | D12: NAYE | F12: BALERO DELANTERO IZQUIERDO | H12: VERSA|2020|ROJO|NLP172B | I12: REAL | J12: ASHC | M12: 270 | P12: PENDIENTE A ANGEL | Q12: -
A13: =WEEKNUM(C13) -> 36 | B13: 9 | C13: 45902 | D13: NAYE | F13: FOCO PARA DIRECCIONAL | H13: MARCH|2020|TURQ|NI5BKD | I13: REAL | J13: ASHC | M13: 40 | P13: PENDIENTE A ANGEL | Q13: -
A14: =WEEKNUM(C14) -> 36 | B14: 9 | C14: 45902 | D14: NAYE | F14: TALACHA DE LLANTA TRASERA | H14: AVEO|2018|GRIS|X59AWG | I14: REAL | J14: ASHC | M14: 100 | P14: PENDIENTE NAYE | Q14: -
... A35: =WEEKNUM(C35) -> 37 | B35: 9 | C35: 45908 | D35: NAYE | F35: MANO DE OBRA CAMBIO DE BALERO | H35: VERSA|2023|PLATA|NCT814A | I35: REAL | J35: ASHC | M35: 120 | P35: 1500 EFECTIVO YUL | Q35: -
A36: =WEEKNUM(C36) -> 37 | B36: 9 | C36: 45908 | D36: NAYE | E36: AFINACION | F36: LIQUIDO DE FRENOS | H36: KIA RIO|2020|AZUL|LUE960C | I36: REAL | J36: JGD | M36: 100 | P36: 1500 EFECTIVO YUL | Q36: -
A37: =WEEKNUM(C37) -> 37 | B37: 9 | C37: 45909 | D37: NAYE | F37: GOMAS DE PISTON CALPIS TRASERO DERECHO | H37: KIA RIO|2020|AZUL|LUE960C | I37: REAL | J37: JGD | M37: 363 | P37: 1500 EFECTIVO YUL | Q37: -
A38: =WEEKNUM(C38) -> 37 | B38: 9 | C38: 45909 | D38: NAYE | F38: TALACHA DE LLANTA TRASERA Y REFACCION | H38: HYUNDAI|2022|PLATA|D40BKD | I38: REAL | J38: ASHC | M38: 150 | P38: 1500 EFECTIVO YUL | Q38: -
A39: =WEEKNUM(C39) -> 37 | B39: 9 | C39: 45910 | D39: NAYE | F39: AMORTIGUADOR IZQUIERDO | H39: VENTO|2018|AMARILLO|PED1652 | I39: REAL | J39: ASHC | L39: 600 | M39: 600 | P39: 500 EFECT YUL | Q39: -
A40: =WEEKNUM(C40) -> 37 | B40: 9 | C40: 45910 | D40: NAYE | F40: 20 LITROS DE GASOLINA | H40: AVEO|2021|GRIS|MLC126A | I40: REAL | J40: ASHC | L40: 250 | M40: 479.8 | P40: PENDIENTE YUL | Q40: BBVA
A41: =WEEKNUM(C41) -> 37 | B41: 9 | C41: 45910 | D41: NAYE | F41: BASURA | H41: ADMINISTRATIVO | I41: REAL | J41: ASHC | L41: 0 | M41: 50 | P41: 15,100 PPTO | Q41: -
A42: =WEEKNUM(C42) -> 37 | B42: 9 | C42: 45911 | D42: NAYE | F42: GALON DE ACEITE | H42: AVEO|2018|GRIS|X59AWG | I42: REAL | J42: ASHC | L42: 555 | M42: 550 | P42: PENDIENTE YUL | Q42: BBVA SE REALIZA CAMBIO EL 12 DE SEP
A43: =WEEKNUM(C43) -> 37 | B43: 9 | C43: 45911 | D43: NAYE | E43: AFINACION | F43: BUJIAS | H43: AVEO|2018|GRIS|X59AWG | I43: REAL | J43: ASHC | L43: 280 | M43: =82*4 -> 328 | P43: PENDIENTE YUL | Q43: BBVA SE CAMBIAN POR MAS REFACCIONES (EN 3 MESES)
A44: =WEEKNUM(C44) -> 37 | B44: 9 | C44: 45911 | D44: NAYE | F44: FILTRO DE AIRE | H44: AVEO|2018|GRIS|X59AWG | I44: REAL | J44: ASHC | L44: 50 | M44: 0 | P44: EN TALLER | Q44: SE REALIZA CAMBIO EL 12 DE SEP
A45: =WEEKNUM(C45) -> 37 | B45: 9 | C45: 45911 | D45: NAYE | F45: FILTRO DE ACEITE | H45: AVEO|2018|GRIS|X59AWG | I45: REAL | J45: ASHC | L45: 35 | M45: 124 | P45: PENDIENTE YUL | Q45: BBVA SE REALIZA CAMBIO EL 12 DE SEP
A46: =WEEKNUM(C46) -> 37 | B46: 9 | C46: 45911 | D46: NAYE | E46: AFINACION | F46: BALATAS DELANTERAS | H46: AVEO|2018|GRIS|X59AWG | I46: REAL | J46: ASHC | L46: 410 | M46: 397 | P46: PENDIENTE YUL | Q46: BBVA SE REALIZA CAMBIO EL 12 DE SEP
A47: =WEEKNUM(C47) -> 37 | B47: 9 | C47: 45911 | D47: NAYE | E47: AFINACION | F47: BALATAS TRASERAS | H47: AVEO|2018|GRIS|X59AWG | I47: REAL | J47: ASHC | L47: 410 | M47: 464 | P47: PENDIENTE YUL | Q47: BBVA EN 3 MESES | T47: -
A48: =WEEKNUM(C48) -> 37 | B48: 9 | C48: 45911 | D48: NAYE | F48: GALON DE ACEITE | H48: MARCH|2021|ROJO|NZU5163 | I48: REAL | J48: ASHC | L48: 555 | M48: 550 | P48: PENDIENTE YUL | Q48: BBVA
A49: =WEEKNUM(C49) -> 37 | B49: 9 | C49: 45911 | D49: NAYE | E49: AFINACION | F49: BUJIAS | H49: MARCH|2021|ROJO|NZU5163 | I49: REAL | J49: ASHC | L49: 200 | M49: 0 | P49: EN TALLER | Q49: -
A50: =WEEKNUM(C50) -> 37 | B50: 9 | C50: 45911 | D50: NAYE | F50: FILTRO DE AIRE | H50: MARCH|2021|ROJO|NZU5163 | I50: REAL | J50: ASHC | L50: 40 | M50: 77 | P50: PENDIENTE YUL | Q50: BBVA
A51: =WEEKNUM(C51) -> 37 | B51: 9 | C51: 45911 | D51: NAYE | F51: FILTRO DE ACEITE | H51: MARCH|2021|ROJO|NZU5163 | I51: REAL | J51: ASHC | L51: 35 | M51: 49 | P51: PENDIENTE YUL | Q51: BBVA
A52: =WEEKNUM(C52) -> 37 | B52: 9 | C52: 45911 | D52: NAYE | E52: AFINACION | F52: BALATAS DELANTERAS | H52: MARCH|2021|ROJO|NZU5163 | I52: REAL | J52: ASHC | L52: 480 | M52: 358 | P52: PENDIENTE YUL | Q52: BBVA
A53: =WEEKNUM(C53) -> 37 | B53: 9 | C53: 45911 | D53: NAYE | F53: GALON DE ACEITE | H53: AVEO|2020|AZUL|D28BET | I53: REAL | J53: ASHC | L53: 555 | M53: 550 | P53: PENDIENTE YUL | Q53: BBVA
A54: =WEEKNUM(C54) -> 37 | B54: 9 | C54: 45911 | D54: NAYE | E54: AFINACION | F54: BUJIAS | H54: AVEO|2020|AZUL|D28BET | I54: REAL | J54: ASHC | L54: 280 | M54: 328 | P54: PENDIENTE YUL | Q54: BBVA
A55: =WEEKNUM(C55) -> 37 | B55: 9 | C55: 45911 | D55: NAYE | F55: FILTRO DE AIRE | H55: AVEO|2020|AZUL|D28BET | I55: REAL | J55: ASHC | L55: 50 | M55: 0 | P55: EN TALLER | Q55: -
A56: =WEEKNUM(C56) -> 37 | B56: 9 | C56: 45911 | D56: NAYE | F56: FILTRO DE ACEITE | H56: AVEO|2020|AZUL|D28BET | I56: REAL | J56: ASHC | L56: 35 | M56: 124 | P56: PENDIENTE YUL | Q56: BBVA
A57: =WEEKNUM(C57) -> 37 | B57: 9 | C57: 45911 | D57: NAYE | E57: AFINACION | F57: BALATAS DELANTERAS | H57: AVEO|2020|AZUL|D28BET | I57: REAL | J57: ASHC | L57: 580 | M57: 397 | P57: PENDIENTE YUL | Q57: BBVA
A58: =WEEKNUM(C58) -> 37 | B58: 9 | C58: 45911 | D58: NAYE | F58: FACTURAS DE GASOLINA | H58: ADMINISTRATIVO | I58: REAL | J58: ASHC | L58: 1500 | M58: 1500 | P58: PENDIENTE YUL | Q58: BBVA
A59: =WEEKNUM(C59) -> 37 | B59: 9 | C59: 45912 | D59: NAYE | F59: ELECTRICO REVISION | H59: VENTO|2017|GRIS|MMA672C | I59: REAL | J59: ASHC | L59: 250 | M59: 250 | P59: 15,100 PPTO
A60: =WEEKNUM(C60) -> 37 | B60: 9 | C60: 45912 | D60: NAYE | F60: VERIFICACIÓN | H60: AVEO|2021|GRIS|MLC126A | I60: REAL | J60: ASHC | L60: 720 | M60: 1131 | P60: 15,100 PPTO
A61: =WEEKNUM(C61) -> 37 | B61: 9 | C61: 45913 | D61: NAYE | F61: ELECTRICO CARGA DE BATERIA | H61: VENTO|2017|GRIS|MMA672C | I61: REAL | J61: ASHC | L61: 100 | M61: 100 | P61: 15,100 PPTO
A62: =WEEKNUM(C62) -> 37 | B62: 9 | C62: 45913 | D62: NAYE | F62: ELECTRICO CARGA DE BATERIA | H62: VENTO|2017|GRIS|MMA672C | I62: REAL | J62: ASHC | L62: 100 | M62: 100 | P62: 15,100 PPTO
A63: =WEEKNUM(C63) -> 37 | B63: 9 | C63: 45913 | D63: NAYE | F63: ELECTRICO CARGA DE BATERIA | H63: TALLER | I63: REAL | J63: ASHC | L63: 100 | M63: 100 | P63: 15,100 PPTO
A64: =WEEKNUM(C64) -> 37 | B64: 9 | C64: 45913 | D64: NAYE | F64: ELECTRICO CARGA DE BATERIA | H64: TALLER | I64: REAL | J64: ASHC | L64: 100 | M64: 100 | P64: 15,100 PPTO
A65: =WEEKNUM(C65) -> 37 | B65: 9 | C65: 45913 | D65: NAYE | F65: FOCOS PARA DIRECCIONAL | H65: MARCH|2021|BLANCO|MGC417C | I65: REAL | J65: JGD | L65: 100 | M65: 60 | P65: 15,100 PPTO
A66: =WEEKNUM(C66) -> 38 | B66: 9 | C66: 45915 | D66: NAYE | F66: GASOLINA PARA MOTO VENTO OP. | H66: MOTO OPERATIVA | I66: REAL | J66: ASHC | M66: 50 | P66: 15,100 PPTO
A67: =WEEKNUM(C67) -> 38 | B67: 9 | C67: 45915 | D67: NAYE | F67: MANGUERA DE VACIO | H67: MARCH|2020|TURQ|NI5BKD | I67: REAL | J67: ASHC | M67: 45 | P67: 15,100 PPTO
A68: =WEEKNUM(C68) -> 38 | B68: 9 | C68: 45915 | D68: NAYE | F68: DOS TALACHAS | H68: VENTO|2019|BLANCO|LUE965C | I68: REAL | J68: JGD | M68: 100 | P68: 15,100 PPTO
A69: =WEEKNUM(C69) -> 38 | B69: 9 | C69: 45915 | D69: NAYE | F69: TALACHA | H69: MARCH|2020|TURQ|NI5BKD | I69: REAL | J69: ASHC | M69: 50 | P69: 15,100 PPTO
A70: =WEEKNUM(C70) -> 38 | B70: 9 | C70: 45917 | D70: NAYE | F70: VERIFICACIÓN | H70: AVEO|2020|AZUL|D28BET | I70: REAL | J70: ASHC | L70: 720 | M70: 740 | P70: 15,100 PPTO
A71: =WEEKNUM(C71) -> 38 | B71: 9 | C71: 45917 | D71: NAYE | F71: FOCOS AMBAR | H71: TALLER | I71: REAL | J71: ASHC | M71: 50 | P71: 15,100 PPTO
A72: =WEEKNUM(C72) -> 38 | B72: 9 | C72: 45918 | D72: NAYE | F72: FOCOS PARA DIRECCIONAL | H72: AVEO|2020|AZUL|D28BET | I72: REAL | J72: ASHC | M72: 40 | P72: 15,100 PPTO
A73: =WEEKNUM(C73) -> 38 | B73: 9 | C73: 45918 | D73: NAYE | F73: ALTERNADOR | H73: VENTO|2017|GRIS|MMA672C | I73: REAL | J73: ASHC | L73: 1800 | M73: 2082 | P73: 15,100 PPTO
A74: =WEEKNUM(C74) -> 38 | B74: 9 | C74: 45918 | D74: NAYE | F74: PROPINA DE REFACCIONARIA | H74: VENTO|2017|GRIS|MMA672C | I74: REAL | J74: ASHC | M74: 18 | P74: 15,100 PPTO
A75: =WEEKNUM(C75) -> 38 | B75: 9 | C75: 45918 | D75: NAYE | F75: PAGO DE FACTURAS | H75: ADMINISTRACIÓN | I75: REAL | J75: ASHC | M75: 1500 | P75: 15,100 PPTO
A76: =WEEKNUM(C76) -> 38 | B76: 9 | C76: 45919 | D76: NAYE | F76: PAGO DE POLICIA MUF | H76: OPERACIÓN | I76: REAL | J76: ASHC | M76: 200 | P76: 15,100 PPTO
A77: =WEEKNUM(C77) -> 38 | B77: 9 | C77: 45919 | D77: NAYE | F77: CAFÉ PARA OPERACIÓN | H77: OPERACIÓN | I77: REAL | J77: ASHC | M77: 50 | P77: 15,100 PPTO
A78: =WEEKNUM(C78) -> 38 | B78: 9 | C78: 45919 | D78: NAYE | F78: GALON DE ACEITE | H78: KIA RIO|2020|GRIS|NCK475B | I78: REAL | J78: ASHC | L78: 555 | M78: 550 | P78: 15,100 PPTO
A79: =WEEKNUM(C79) -> 38 | B79: 9 | C79: 45919 | D79: NAYE | E79: AFINACION | F79: BUJIAS | H79: KIA RIO|2020|GRIS|NCK475B | I79: REAL | J79: ASHC | L79: 280 | M79: 0 | P79: 15,100 PPTO | Q79: NO SE REQUERIAN
A80: =WEEKNUM(C80) -> 38 | B80: 9 | C80: 45919 | D80: NAYE | F80: FILTRO DE AIRE | H80: KIA RIO|2020|GRIS|NCK475B | I80: REAL | J80: ASHC | L80: 50 | M80: 50 | P80: 15,100 PPTO
A81: =WEEKNUM(C81) -> 38 | B81: 9 | C81: 45919 | D81: NAYE | F81: FILTRO DE ACEITE | H81: KIA RIO|2020|GRIS|NCK475B | I81: REAL | J81: ASHC | L81: 35 | M81: 50 | P81: 15,100 PPTO
A82: =WEEKNUM(C82) -> 38 | B82: 9 | C82: 45919 | D82: NAYE | F82: MASA DE BALERO | H82: AVEO|2018|ROJO|R51BKD | I82: REAL | J82: ASHC | M82: 183 | P82: 15,100 PPTO
A83: =WEEKNUM(C83) -> 38 | B83: 9 | C83: 45919 | D83: NAYE | F83: BALERO DOBLE IZQUIERDO | H83: AVEO|2018|ROJO|R51BKD | I83: REAL | J83: ASHC | M83: 365 | P83: 15,100 PPTO
A84: =WEEKNUM(C84) -> 38 | B84: 9 | C84: 45919 | D84: NAYE | F84: GASOLINA PARA MOTO VENTO OP. | H84: MOTO OPERATIVA | I84: REAL | J84: ASHC | M84: 200 | P84: 15,100 PPTO
A85: =WEEKNUM(C85) -> 38 | B85: 9 | C85: 45919 | D85: NAYE | F85: GASOLINA APOYO | H85: MARCH|2021|BLANCO|MGC417C | I85: REAL | J85: JGD | M85: 966 | P85: 15,100 PPTO
A86: =WEEKNUM(C86) -> 38 | B86: 9 | C86: 45920 | D86: NAYE | F86: PRENSA DE BALERO | H86: AVEO|2018|ROJO|R51BKD | I86: REAL | J86: ASHC | M86: 120 | P86: 15,100 PPTO
A87: =WEEKNUM(C87) -> 38 | B87: 9 | C87: 45920 | D87: NAYE | F87: VERIFICACIÓN | H87: VENTO|2017|GRIS|MMA672C | I87: REAL | J87: ASHC | L87: 740 | M87: 740 | P87: 15,100 PPTO
A88: =WEEKNUM(C88) -> 38 | B88: 9 | C88: 45920 | D88: NAYE | F88: GASOLINA | H88: AVEO|2021|GRIS|MLC126A | I88: REAL | J88: ASHC | M88: 250 | P88: 15,100 PPTO
A89: =WEEKNUM(C89) -> 38 | B89: 9 | C89: 45920 | D89: NAYE | F89: BRINCO POR NO ENCENDER | H89: VENTO|2017|GRIS|MMA672C | I89: REAL | J89: ASHC | M89: 50 | P89: 15,100 PPTO
A90: =WEEKNUM(C90) -> 38 | B90: 9 | C90: 45920 | D90: NAYE | F90: GASOLINA DE ASISTENCIA | H90: KIA|2020|AZUL|LUE960C | I90: REAL | J90: JGD | M90: 100 | P90: 15,100 PPTO
A91: =WEEKNUM(C91) -> 38 | B91: 9 | C91: 45920 | D91: NAYE | F91: GASOLINA PARA GPS | H91: VENTO|2019|BLANCO|MGC410C | I91: REAL | J91: JGD | M91: 200 | P91: 15,100 PPTO
A92: =WEEKNUM(C92) -> 39 | B92: 9 | C92: 45922 | D92: NAYE | F92: AUTOLAVADO | H92: KIA|2020|AZUL|LUE960C | I92: REAL | J92: JGD | M92: 120 | P92: 15,100 PPTO
A93: =WEEKNUM(C93) -> 39 | B93: 9 | C93: 45922 | D93: NAYE | F93: ELECTRICO | H93: VENTO|2017|GRIS|MMA672C | I93: REAL | J93: ASHC | M93: 500 | P93: 15,100 PPTO
A94: =WEEKNUM(C94) -> 39 | B94: 9 | C94: 45922 | D94: NAYE | F94: GASOLINA APOYO | H94: MARCH|2021|BLANCO|MGC417C | I94: REAL | J94: JGD | M94: 807 | P94: 15,100 PPTO
A95: =WEEKNUM(C95) -> 39 | B95: 9 | C95: 45922 | D95: NAYE | F95: GASOLINA APOYO | H95: MARCH|2021|BLANCO|MGC417C | I95: REAL | J95: JGD | M95: 200 | P95: 15,100 PPTO
A96: =WEEKNUM(C96) -> 39 | B96: 9 | C96: 45922 | D96: NAYE | F96: DEDUCIBLE DE PARABRISAS | H96: AVEO|2018|ROJO|R51BKD | I96: REAL | J96: ASHC | M96: 440 | P96: 15,100 PPTO
A97: =WEEKNUM(C97) -> 39 | B97: 9 | C97: 45923 | D97: NAYE | F97: VERIFICACIÓN | H97: KIA RIO|2021|ROJO|MFP751C | I97: REAL | J97: ASHC | L97: 720 | M97: 740 | P97: 15,100 PPTO
A98: =WEEKNUM(C98) -> 39 | B98: 9 | C98: 45923 | D98: NAYE | F98: REVISION DE BATERIA | H98: MARCH|2021|ROJO|NZU5163 | I98: REAL | J98: ASHC | M98: 30 | P98: 15,100 PPTO
A99: =WEEKNUM(C99) -> 39 | B99: 9 | C99: 45923 | D99: NAYE | F99: REPARACIÓN DE MARCHA | H99: MARCH|2020|TURQ|NI5BKD | I99: REAL | J99: ASHC | M99: 250 | P99: 15,100 PPTO
A100: =WEEKNUM(C100) -> 39 | B100: 9 | C100: 45923 | D100: NAYE | F100: ABRAZADERAS DE MANGERA ANTICONGELANTE | H100: VENTO|2019|BLANCO|LUE965C | I100: REAL | J100: JGD | M100: 40 | P100: 15,100 PPTO
A101: =WEEKNUM(C101) -> 39 | B101: 9 | C101: 45923 | D101: NAYE | F101: CARBONES PARA ALTERNADOR | H101: MARCH|2020|TURQ|NI5BKD | I101: REAL | J101: ASHC | M101: 20 | P101: 15,100 PPTO
A102: =WEEKNUM(C102) -> 39 | B102: 9 | C102: 45923 | D102: NAYE | F102: LLAVE DE CRUZ | H102: VENTO|2019|BLANCO|MGC410C | I102: REAL | J102: JGD | M102: 135 | P102: 3,914 JG
A103: =WEEKNUM(C103) -> 39 | B103: 9 | C103: 45923 | D103: NAYE | F103: RETROVISOR | H103: VENTO|2019|BLANCO|MGC410C | I103: REAL | J103: JGD | M103: 165 | P103: 3,914 JG
A104: =WEEKNUM(C104) -> 39 | B104: 9 | C104: 45923 | D104: NAYE | F104: GASOLINA | H104: VENTO|2019|BLANCO|MGC410C | I104: REAL | J104: JGD | M104: 150 | P104: 3,914 JG
A105: =WEEKNUM(C105) -> 39 | B105: 9 | C105: 45923 | D105: NAYE | F105: GASOLINA | H105: MARCH|2020|TURQ|NI5BKD | I105: REAL | J105: ASHC | M105: 300 | P105: 15,100 PPTO
A106: =WEEKNUM(C106) -> 39 | B106: 9 | C106: 45923 | D106: NAYE | F106: CAUTIN PARA BATERIAS | H106: TALLER | I106: REAL | J106: ASHC | M106: 200 | P106: 15,100 PPTO
A107: =WEEKNUM(C107) -> 39 | B107: 9 | C107: 45923 | D107: NAYE | F107: FILTRO DE AIRE | H107: MARCH|2020|TURQ|MAY737C | I107: REAL | J107: BYER | M107: 120 | P107: 15,100 PPTO
A108: =WEEKNUM(C108) -> 39 | B108: 9 | C108: 45924 | D108: NAYE | F108: CLOUCH COMPLETO | H108: VENTO|2018|AMARILLO|PED1652 | I108: REAL | J108: ASHC | M108: 3600 | P108: 2,000 FIANZA DE GONZALO EFECT + 1,600 CUENTA JUAN DIEGO EFECT
A109: =WEEKNUM(C109) -> 39 | B109: 9 | C109: 45924 | D109: NAYE | F109: HORQUILLA IZQUIERDA DELANTERA | H109: VENTO|2018|AMARILLO|PED1652 | I109: REAL | J109: ASHC | M109: 350 | P109: CUENTA JUAN DIEGO EFECT
... A139: =WEEKNUM(C139) -> 40 | B139: 10 | C139: 45932 | D139: NAYE | F139: FACTURAS ASHC-BYER | H139: ADMINISTRACIÓN | I139: REAL | J139: ASHC | M139: 1500 | P139: YUL BBVA
A140: 40 | B140: 10 | C140: 45933 | D140: NAYE | F140: CUERPO DE ACELERACIÓN | H140: VENTO|2019|BLANCO|MGC410C | I140: REAL | J140: JGD | L140: 2300 | M140: 1492 | P140: NOMINA JAIME
A141: 40 | B141: 10 | C141: 45933 | D141: NAYE | F141: PERMISO PARA MOTO VENTO | H141: OPERACIÓN | I141: REAL | J141: ASHC | L141: 150 | M141: 100 | P141: NOMINA JAIME
A142: 40 | B142: 10 | C142: 45933 | D142: NAYE | F142: PAGO DE DERECHOS TARJETA DE CIRCULACION | H142: VENTO|2020|GRIS|R66BER | I142: REAL | J142: ASHC | L142: 480 | M142: 417 | P142: NOMINA JAIME
A143: 40 | B143: 10 | C143: 45933 | D143: NAYE | F143: RECARGA OPERACIÓN | H143: OPERACIÓN | I143: REAL | J143: BYER | L143: 100 | M143: 100 | P143: 15,100 PPTO
A144: 40 | B144: 10 | C144: 45933 | D144: NAYE | F144: GASOLINA OPERACIÓN | H144: BEAT|2019|OCRE|MAY730C | I144: REAL | J144: BYER | M144: 200 | P144: NOMINA JAIME
A145: 40 | B145: 10 | C145: 45933 | D145: NAYE | F145: PLAZA VIAJE | H145: OPERACIÓN | I145: REAL | J145: BYER | M145: 30 | P145: NOMINA JAIME
A146: 40 | B146: 10 | C146: 45933 | D146: NAYE | F146: FILTRO DE ACEITE (2) | H146: JAC CAMIONETA | I146: REAL | J146: ASHC | M146: 720 | P146: PAGA YUL
A147: 40 | B147: 10 | C147: 45933 | D147: NAYE | F147: FILTO DE AIRE (2) | H147: JAC CAMIONETA | I147: REAL | J147: ASHC | M147: 1263 | P147: PAGA YUL
A148: 40 | B148: 10 | C148: 45933 | D148: NAYE | F148: FILTRO (2) | H148: JAC CAMIONETA | I148: REAL | J148: ASHC | M148: 2338 | P148: PAGA YUL
A149: 40 | B149: 10 | C149: 45933 | D149: NAYE | F149: ANTICIPO REFACCIONES | H149: JAC CAMIONETA | I149: REAL | J149: ASHC | M149: 3931 | P149: PAGA YUL
...

Sheet Gastos 2026
A1: SEM | B1: FECHA | C1: MES | D1: INVENTARIO | E1: CONCEPTO | F1: DETALLE | G1: CANTIDAD | H1: UNIDAD | I1: V UNIT | J1: SUBTOTAL | K1: IVA | L1: REAL | M1: PLAN | N1: CONDUCTOR | O1: LLAVE | P1: SOCIO | Q1: RESPONSABLE | R1: METODO DE PAGO | S1: COMERCIO | T1: MARCA | U1: COMENTARIOS | V1: ADICIONAL | W1: FOLIO FISCAL | X1: CÓDIGO TICKET
A2: =WEEKNUM(B2) -> 1 | B2: 46023 | C2: =TEXT(B2,"MMMM") -> enero | D2: NO | E2: GESTORIA | F2: GESTORIA ALTA PLACAS | G2: 1 | H2: SERVICIO | I2: 1200 | J2: 1200 | K2: 0 | L2: 1200 | M2: 0 | N2: N/A | O2: AVEOH|2026|GRIS|NEZ118C | P2: IVETT | Q2: YUL | R2: TRANSFERENCIA | S2: ANTONIO BEDOLLA | W2: N/A | AJ2: PIEZAS
A3: =WEEKNUM(B3) -> 1 | B3: 46023 | C3: =TEXT(B3,"MMMM") -> enero | D3: NO | E3: GESTORIA | F3: GESTORIA ALTA PLACAS | G3: 1 | H3: SERVICIO | I3: 1200 | J3: 1200 | K3: 0 | L3: 1200 | M3: 0 | N3: N/A | O3: AVEOH|2026|GRIS|NEZ115C | P3: IVETT | Q3: YUL | R3: TRANSFERENCIA | S3: ANTONIO BEDOLLA | W3: N/A | AJ3: JUEGO
A4: =WEEKNUM(B4) -> 1 | B4: 46023 | C4: =TEXT(B4,"MMMM") -> enero | D4: NO | E4: GESTORIA | F4: GESTORIA ALTA PLACAS | G4: 1 | H4: SERVICIO | I4: 1200 | J4: 1200 | K4: 0 | L4: 1200 | M4: 0 | N4: N/A | O4: AVEOH|2026|GRIS|NEZ110C | P4: IVETT | Q4: YUL | R4: TRANSFERENCIA | S4: ANTONIO BEDOLLA | W4: N/A | AJ4: LITROS
A5: =WEEKNUM(B5) -> 1 | B5: 46023 | C5: =TEXT(B5,"MMMM") -> enero | D5: NO | E5: GESTORIA | F5: GESTORIA ALTA PLACAS | G5: 1 | H5: SERVICIO | I5: 1200 | J5: 1200 | K5: 0 | L5: 1200 | M5: 0 | N5: N/A | O5: AVEOH|2026|GRIS|NEZ103C | P5: IVETT | Q5: YUL | R5: TRANSFERENCIA | S5: ANTONIO BEDOLLA | W5: N/A | AJ5: SERVICIO
A6: =WEEKNUM(B6) -> 1 | B6: 46023 | C6: =TEXT(B6,"MMMM") -> enero | D6: NO | E6: GESTORIA | F6: GESTORIA ALTA PLACAS | G6: 1 | H6: SERVICIO | I6: 1200 | J6: 1200 | K6: 0 | L6: 1200 | M6: 0 | N6: N/A | O6: AVEO|2022|AZUL|PCH9635 | P6: IVETT | Q6: YUL | R6: TRANSFERENCIA | S6: ANTONIO BEDOLLA | W6: N/A | AJ6: PAQUETE
A7: =WEEKNUM(B7) -> 1 | B7: 46024 | C7: =TEXT(B7,"MMMM") -> enero | D7: NO | E7: GPS | F7: CHIPS GPS | G7: 1 | H7: PIEZAS | I7: 1850 | J7: =+G7*I7 -> 1850 | K7: 0 | L7: =+J7 -> 1850 | M7: 0 | N7: N/A | O7: AVEOH|2026|BLANCO|NJJ925C | P7: ASHC | Q7: SANTIAGO | R7: TRANSFERENCIA | S7: JUAN LOZADA | T7: - | U7: TRANSFIERE ASHC | V7: NO SE ME ENTREGO GASTO
A8: =WEEKNUM(B8) -> 1 | B8: 46024 | C8: =TEXT(B8,"MMMM") -> enero | D8: NO | E8: GPS | F8: CHIPS GPS | G8: 1 | H8: PIEZAS | I8: 1850 | J8: =+G8*I8 -> 1850 | K8: 0 | L8: =+J8 -> 1850 | M8: 0 | N8: N/A | O8: AVEOH|2026|BLANCO|NJG485C | P8: ASHC | Q8: SANTIAGO | R8: TRANSFERENCIA | S8: JUAN LOZADA | T8: - | U8: TRANSFIERE ASHC | V8: NO SE ME ENTREGO GASTO
A9: =WEEKNUM(B9) -> 1 | B9: 46024 | C9: =TEXT(B9,"MMMM") -> enero | D9: NO | E9: GPS | F9: CHIPS GPS | G9: 1 | H9: PIEZAS | I9: 1850 | J9: =+G9*I9 -> 1850 | K9: 0 | L9: =+J9 -> 1850 | M9: 0 | N9: N/A | O9: AVEOH|2026|BLANCO|NJG467C | P9: ASHC | Q9: SANTIAGO | R9: TRANSFERENCIA | S9: JUAN LOZADA | T9: - | U9: TRANSFIERE ASHC | V9: NO SE ME ENTREGO GASTO
A10: =WEEKNUM(B10) -> 1 | B10: 46024 | C10: =TEXT(B10,"MMMM") -> enero | D10: NO | E10: GPS | F10: CHIPS GPS | G10: 1 | H10: PIEZAS | I10: 1850 | J10: =+G10*I10 -> 1850 | K10: 0 | L10: =+J10 -> 1850 | M10: 0 | N10: N/A | O10: AVEOH|2026|BLANCO|NJG464C | P10: ASHC | Q10: SANTIAGO | R10: TRANSFERENCIA | S10: JUAN LOZADA | T10: - | U10: TRANSFIERE ASHC | V10: NO SE ME ENTREGO GASTO
A11: =WEEKNUM(B11) -> 1 | B11: 46024 | C11: =TEXT(B11,"MMMM") -> enero | D11: NO | E11: GPS | F11: CHIPS GPS | G11: 1 | H11: PIEZAS | I11: 1850 | J11: =+G11*I11 -> 1850 | K11: 0 | L11: =+J11 -> 1850 | M11: 0 | N11: N/A | O11: AVEOH|2026|BLANCO|NJG451C | P11: ASHC | Q11: SANTIAGO | R11: TRANSFERENCIA | S11: JUAN LOZADA | T11: - | U11: TRANSFIERE ASHC | V11: NO SE ME ENTREGO GASTO
A12: =WEEKNUM(B12) -> 1 | B12: 46024 | C12: =TEXT(B12,"MMMM") -> enero | D12: NO | E12: GPS | F12: CHIPS GPS | G12: 1 | H12: PIEZAS | I12: 1850 | J12: =+G12*I12 -> 1850 | K12: 0 | L12: =+J12 -> 1850 | M12: 0 | N12: N/A | O12: AVEOH|2026|BLANCO|NJG470C | P12: ASHC | Q12: SANTIAGO | R12: TRANSFERENCIA | S12: JUAN LOZADA | T12: - | U12: TRANSFIERE ASHC | V12: NO SE ME ENTREGO GASTO
A13: =WEEKNUM(B13) -> 1 | B13: 46024 | C13: =TEXT(B13,"MMMM") -> enero | D13: NO | E13: GPS | F13: CHIPS GPS | G13: 1 | H13: PIEZAS | I13: 1850 | J13: =+G13*I13 -> 1850 | K13: 0 | L13: =+J13 -> 1850 | M13: 0 | N13: N/A | O13: AVEOH|2026|GRIS|NEZ118C | P13: IVETT | Q13: SANTIAGO | R13: TRANSFERENCIA | S13: JUAN LOZADA | T13: - | U13: TRANSFIERE ASHC | V13: NO SE ME ENTREGO GASTO
A14: =WEEKNUM(B14) -> 1 | B14: 46024 | C14: =TEXT(B14,"MMMM") -> enero | D14: NO | E14: GPS | F14: CHIPS GPS | G14: 1 | H14: PIEZAS | I14: 1850 | J14: =+G14*I14 -> 1850 | K14: 0 | L14: =+J14 -> 1850 | M14: 0 | N14: N/A | O14: AVEOH|2026|GRIS|NEZ115C | P14: IVETT | Q14: SANTIAGO | R14: TRANSFERENCIA | S14: JUAN LOZADA | T14: - | U14: TRANSFIERE ASHC | V14: NO SE ME ENTREGO GASTO
A15: =WEEKNUM(B15) -> 1 | B15: 46024 | C15: =TEXT(B15,"MMMM") -> enero | D15: NO | E15: GPS | F15: CHIPS GPS | G15: 1 | H15: PIEZAS | I15: 1850 | J15: =+G15*I15 -> 1850 | K15: 0 | L15: =+J15 -> 1850 | M15: 0 | N15: N/A | O15: AVEOH|2026|GRIS|NEZ110C | P15: IVETT | Q15: SANTIAGO | R15: TRANSFERENCIA | S15: JUAN LOZADA | T15: - | U15: TRANSFIERE ASHC | V15: NO SE ME ENTREGO GASTO
A16: =WEEKNUM(B16) -> 1 | B16: 46024 | C16: =TEXT(B16,"MMMM") -> enero | D16: NO | E16: GPS | F16: CHIPS GPS | G16: 1 | H16: PIEZAS | I16: 1850 | J16: =+G16*I16 -> 1850 | K16: 0 | L16: =+J16 -> 1850 | M16: 0 | N16: N/A | O16: AVEOH|2026|GRIS|NEZ103C | P16: IVETT | Q16: SANTIAGO | R16: TRANSFERENCIA | S16: JUAN LOZADA | T16: - | U16: TRANSFIERE ASHC | V16: NO SE ME ENTREGO GASTO
A17: =WEEKNUM(B17) -> 1 | B17: 46024 | C17: =TEXT(B17,"MMMM") -> enero | D17: NO | E17: TRASLADO | F17: GASOLINA | G17: 1 | H17: SERVICIO | I17: 250 | J17: 215.51724 | K17: 34.482759 | L17: 250 | M17: 0 | N17: S/C | O17: AVEOH|2026|ROJO|NEZ101C | P17: ASHC | Q17: ISMAEL | R17: TC PLATA ASHC | S17: PEMEX | T17: - | U17: - | V17: NO SE ME ENTREGO GASTO
A18: =WEEKNUM(B18) -> 1 | B18: 46024 | C18: =TEXT(B18,"MMMM") -> enero | D18: NO | E18: TRASLADO | F18: GASOLINA | G18: 1 | H18: SERVICIO | I18: 250 | J18: 215.51724 | K18: 34.482759 | L18: 250 | M18: 0 | N18: S/C | O18: AVEOH|2026|ROJO|NEZ108C | P18: ASHC | Q18: ISMAEL | R18: TC DIDI ASHC | S18: PEMEX | T18: - | U18: - | V18: NO SE ME ENTREGO GASTO
A19: =WEEKNUM(B19) -> 1 | B19: 46024 | C19: =TEXT(B19,"MMMM") -> enero | D19: NO | E19: DERECHOS | F19: VERIFICACIÓN | G19: 1 | H19: SERVICIO | I19: 1154 | J19: 994.82759 | K19: 159.17241 | L19: 1154 | M19: 0 | N19: S/C | O19: AVEOH|2026|ROJO|NEZ101C | P19: ASHC | Q19: ALEJANDRA | R19: TC PLATA ASHC | S19: GOBIERNO EDOMEX | T19: - | U19: - | V19: NO SE ME ENTREGO GASTO
A20: =WEEKNUM(B20) -> 1 | B20: 46024 | C20: =TEXT(B20,"MMMM") -> enero | D20: NO | E20: DERECHOS | F20: VERIFICACIÓN | G20: 1 | H20: SERVICIO | I20: 1154 | J20: 994.82759 | K20: 159.17241 | L20: 1154 | M20: 0 | N20: S/C | O20: AVEOH|2026|ROJO|NEZ108C | P20: ASHC | Q20: ALEJANDRA | R20: TC DIDI ASHC | S20: GOBIERNO EDOMEX | T20: - | U20: - | V20: NO SE ME ENTREGO GASTO
A21: =WEEKNUM(B21) -> 1 | B21: 46025 | C21: =TEXT(B21,"MMMM") -> enero | D21: NO | E21: MTTO | F21: AMORTIGUADOR DELANTERO DERECHO | G21: 1 | H21: PIEZAS | I21: 853.96 | J21: 853.96 | K21: 0 | L21: 853.96 | M21: 0 | N21: JESUS AURELIO NUNGARAY CASTILLO | O21: MARCH|2021|ROJO|NZU5163 | P21: ASHC | Q21: ISMAEL | R21: TC PLATA ASHC | S21: REFACCIONES VERTIZ | T21: VAZLO | U21: - | V21: NO SE ME ENTREGO GASTO
A22: =WEEKNUM(B22) -> 1 | B22: 46025 | C22: =TEXT(B22,"MMMM") -> enero | D22: NO | E22: MTTO | F22: HUESO | G22: 1 | H22: PIEZAS | I22: 437.72 | J22: 437.72 | K22: 0 | L22: 437.72 | M22: 0 | N22: S/C | O22: VERSA|2022|GRIS|NES596C | P22: ASHC | Q22: ISMAEL | R22: TC PLATA ASHC | S22: REFACCIONES VERTIZ | T22: EAGLEBHP | U22: - | V22: NO SE ME ENTREGO GASTO
A23: =WEEKNUM(B23) -> 1 | B23: 46025 | C23: =TEXT(B23,"MMMM") -> enero | D23: NO | E23: MTTO | F23: DEPOSITO DE ANTICONGELANTE | G23: 1 | H23: PIEZAS | I23: 550 | J23: 550 | K23: 0 | L23: 550 | M23: 0 | N23: ALEJANDRO PAZ CAMACHO | O23: MARCH|2020|TURQ|N15BKD | P23: ASHC | Q23: ISMAEL | R23: TC PLATA ASHC | S23: AUTOPARTES LOCAR | T23: ORIGINAL | U23: SE FACTURA A NOMBRE DE YULIANA | V23: NO SE ME ENTREGO GASTO
A24: =WEEKNUM(B24) -> 1 | B24: 46025 | C24: =TEXT(B24,"MMMM") -> enero | D24: NO | E24: MTTO | F24: MARCHA | G24: 1 | H24: PIEZAS | I24: 2100 | J24: 2100 | K24: 0 | L24: 2100 | M24: 0 | N24: EDUARDO LICONA GODINEZ | O24: KIA RIO|2020|ROJO|MFP751C | P24: ASHC | Q24: ISMAEL | R24: EFECTIVO | S24: AUTOPARTES ELECTRICAS ROMERO | T24: VALUE | U24: PEND A SR ISMAEL | V24: NO SE ME ENTREGO GASTO
A25: =WEEKNUM(B25) -> 1 | B25: 46025 | C25: =TEXT(B25,"MMMM") -> enero | D25: NO | E25: MTTO | F25: MANO DE OBRA MARCHA | G25: 1 | H25: SERVICIO | I25: 250 | J25: 250 | K25: 0 | L25: 250 | M25: 0 | N25: EDUARDO LICONA GODINEZ | O25: KIA RIO|2020|ROJO|MFP751C | P25: ASHC | Q25: ISMAEL | R25: EFECTIVO | S25: - | T25: - | U25: PEND A SR ISMAEL | V25: NO SE ME ENTREGO GASTO
A26: =WEEKNUM(B26) -> 1 | B26: 46025 | C26: =TEXT(B26,"MMMM") -> enero | D26: NO | E26: MTTO | F26: FOCOS PELLIZCO (4) | G26: 4 | H26: PIEZAS | I26: 7.5 | J26: 30 | K26: 0 | L26: 30 | M26: 0 | N26: N/A | O26: TALLER | P26: ASHC | Q26: ISMAEL | R26: EFECTIVO | S26: - | T26: - | U26: PEND A SR ISMAEL | V26: NO SE ME ENTREGO GASTO
A27: =WEEKNUM(B27) -> 1 | B27: 46025 | C27: =TEXT(B27,"MMMM") -> enero | D27: NO | E27: TRASLADO | F27: TAXI | G27: 1 | H27: PAQUETE | I27: 100 | J27: 100 | K27: 0 | L27: 100 | M27: 0 | N27: N/A | O27: OPERACIÓN | P27: ASHC | R27: EFECTIVO | S27: CDMX | T27: CALLE | U27: PEND A SR ISMAEL | V27: NO EMITE FACTURA/NO SE ME ENTREGO GASTO | W27: N/A
A28: =WEEKNUM(B28) -> 1 | B28: 46025 | C28: =TEXT(B28,"MMMM") -> enero | D28: NO | E28: GASOLINA | F28: FACTURAS | G28: 1 | H28: PAQUETE | I28: 1500 | J28: 1500 | K28: 0 | L28: 1500 | M28: 0 | N28: N/A | O28: ADMINISTRACIÓN | P28: ASHC | Q28: YUL | R28: TRANSFERENCIA | S28: ENRIQUE | T28: N/A | U28: $3400 DE CUENTA YOSHUA ASHC | W28: N/A
A29: =WEEKNUM(B29) -> 2 | B29: 46027 | C29: =TEXT(B29,"MMMM") -> enero | D29: NO | E29: MTTO | F29: SOPORTE FRONTAL DERECHO | G29: 1 | H29: PIEZAS | I29: 764.6488 | J29: 764.6488 | K29: 0 | L29: 764.6488 | M29: 0 | N29: KEVIN ALEXIS MERLOS CORTES | O29: VENTO|2020|GRIS|R66BER | P29: ASHC | Q29: ISMAEL | R29: TC DIDI ASHC | S29: REFACCIONES VERTIZ | T29: VAZLO | U29: DIDI ASHC | V29: NO SE ME ENTREGO GASTO
A30: =WEEKNUM(B30) -> 2 | B30: 46027 | C30: =TEXT(B30,"MMMM") -> enero | D30: NO | E30: MTTO | F30: SOPORTE TRASERO DERECHO | G30: 1 | H30: PIEZAS | I30: 508.5092 | J30: 508.5092 | K30: 0 | L30: 508.5092 | M30: 0 | N30: KEVIN ALEXIS MERLOS CORTES | O30: VENTO|2020|GRIS|R66BER | P30: ASHC | Q30: ISMAEL | R30: TC DIDI ASHC | S30: REFACCIONES VERTIZ | T30: EAGLEVZK | U30: DIDI ASHC | V30: NO SE ME ENTREGO GASTO
A31: =WEEKNUM(B31) -> 2 | B31: 46027 | C31: =TEXT(B31,"MMMM") -> enero | D31: NO | E31: MTTO | F31: HORQUILLA INFERIOR DERECHA | G31: 1 | H31: PIEZAS | I31: 537.5208 | J31: 537.5208 | K31: 0 | L31: 537.5208 | M31: 0 | N31: KEVIN ALEXIS MERLOS CORTES | O31: VENTO|2020|GRIS|R66BER | P31: ASHC | Q31: ISMAEL | R31: TC DIDI ASHC | S31: REFACCIONES VERTIZ | T31: GENERICO | U31: DIDI ASHC | V31: NO SE ME ENTREGO GASTO
A32: =WEEKNUM(B32) -> 2 | B32: 46027 | C32: =TEXT(B32,"MMMM") -> enero | D32: NO | E32: MTTO | F32: HORQUILLA INFERIOR IZQUIERDA | G32: 1 | H32: PIEZAS | I32: 537.5208 | J32: 537.5208 | K32: 0 | L32: 537.5208 | M32: 0 | N32: KEVIN ALEXIS MERLOS CORTES | O32: VENTO|2020|GRIS|R66BER | P32: ASHC | Q32: ISMAEL | R32: TC DIDI ASHC | S32: REFACCIONES VERTIZ | T32: GENERICO | U32: DIDI ASHC | V32: NO SE ME ENTREGO GASTO
A33: =WEEKNUM(B33) -> 2 | B33: 46027 | C33: =TEXT(B33,"MMMM") -> enero | D33: NO | E33: MTTO | F33: BOBINAS (2) | G33: 2 | H33: PIEZAS | I33: 484.915 | J33: 969.83 | K33: 0 | L33: 969.8296 | M33: 0 | N33: S/C | O33: VENTO|2020|GRIS|NES586C | P33: ASHC | Q33: ISMAEL | R33: TC DIDI ASHC | S33: REFACCIONES VERTIZ | T33: NGK | U33: DIDI ASHC | V33: NO SE ME ENTREGO GASTO
A34: =WEEKNUM(B34) -> 2 | B34: 46027 | C34: =TEXT(B34,"MMMM") -> enero | D34: NO | E34: MTTO | F34: ELECTRICO | G34: 1 | H34: PIEZAS | I34: 500 | J34: 500 | K34: 0 | L34: 500 | M34: 0 | N34: OSCAR IVAN MIÑON RAMIREZ | O34: MARCH|2020|TURQ|N15BKD | P34: ASHC | Q34: ISMAEL | R34: EFECTIVO | S34: FRANCISCO JAVIER ELECTRICO | T34: - | U34: $3400 DE CUENTA YOSHUA ASHC | V34: NO SE ME ENTREGO GASTO
A35: =WEEKNUM(B35) -> 2 | B35: 46027 | C35: =TEXT(B35,"MMMM") -> enero | D35: NO | E35: MTTO | F35: ALINEACION | G35: 1 | H35: SERVICIO | I35: 380 | J35: 380 | K35: 0 | L35: 380 | M35: 0 | N35: JESUS AURELIO NUNGARAY CASTILLO | O35: MARCH|2021|ROJO|NZU5163 | P35: ASHC | Q35: ISMAEL | R35: EFECTIVO | S35: LLANTERA TREJO | T35: - | U35: $3400 DE CUENTA YOSHUA ASHC | V35: NO SE ME ENTREGO GASTO
A36: =WEEKNUM(B36) -> 2 | B36: 46027 | C36: =TEXT(B36,"MMMM") -> enero | D36: NO | E36: MTTO | F36: BALANCEO (2) | G36: 2 | H36: PIEZAS | I36: 0 | J36: 0 | K36: 0 | L36: 0 | M36: 0 | N36: JESUS AURELIO NUNGARAY CASTILLO | O36: MARCH|2021|ROJO|NZU5163 | P36: ASHC | Q36: ISMAEL | R36: EFECTIVO | S36: LLANTERA TREJO | T36: - | U36: $3400 DE CUENTA YOSHUA ASHC | V36: NO SE ME ENTREGO GASTO/RESTAN $1020 EN EFEC
A37: =WEEKNUM(B37) -> 2 | B37: 46027 | C37: =TEXT(B37,"MMMM") -> enero | D37: NO | E37: TRASLADO | F37: GASOLINA | G37: 1 | H37: SERVICIO | I37: 100 | J37: 100 | K37: 0 | L37: 100 | M37: 0 | N37: JOSE AGUILAR SOTO | O37: AVEO|2020|AZUL|D28BET | P37: ASHC | Q37: ISMAEL | R37: TC PLATA ASHC | S37: SHELL SERVICE | T37: - | U37: PLATA ASHC | V37: NO SE ME ENTREGO GASTO
A38: =WEEKNUM(B38) -> 2 | B38: 46028 | C38: =TEXT(B38,"MMMM") -> enero | D38: NO | E38: MTTO | F38: TALACHA | G38: 1 | H38: SERVICIO | I38: 0 | J38: 0 | K38: 0 | L38: 0 | M38: 0 | N38: KEVIN ALEXIS MERLOS CORTES | O38: VENTO|2020|GRIS|R66BER | P38: ASHC | Q38: ISMAEL | U38: $3400 DE CUENTA YOSHUA ASHC | V38: NO SE ME ENTREGO GASTO
A39: =WEEKNUM(B39) -> 2 | B39: 46028 | C39: =TEXT(B39,"MMMM") -> enero | D39: NO | E39: MTTO | F39: TALACHA | G39: 1 | H39: SERVICIO | I39: 0 | J39: 0 | K39: 0 | L39: 0 | M39: 0 | O39: OPERACIÓN | P39: ASHC | Q39: ISMAEL | U39: $3400 DE CUENTA YOSHUA ASHC | V39: NO SE ME ENTREGO GASTO
A40: =WEEKNUM(B40) -> 2 | B40: 46028 | C40: =TEXT(B40,"MMMM") -> enero | D40: NO | E40: MTTO | F40: TALACHA | G40: 1 | H40: SERVICIO | I40: 0 | J40: 0 | K40: 0 | L40: 0 | M40: 0 | O40: OPERACIÓN | P40: ASHC | Q40: ISMAEL | U40: $3400 DE CUENTA YOSHUA ASHC | V40: NO SE ME ENTREGO GASTO
A41: =WEEKNUM(B41) -> 2 | B41: 46028 | C41: =TEXT(B41,"MMMM") -> enero | D41: NO | E41: DERECHOS | F41: VERIFICACIÓN | G41: 1 | H41: PIEZAS | I41: 0 | J41: 0 | K41: 0 | L41: 0 | M41: 0 | N41: RICARDO HERNANDEZ ARIAS | O41: VERSA|2022|GRIS|NES596C | P41: ASHC | Q41: ALEJANDRA | U41: $3400 DE CUENTA YOSHUA ASHC | V41: NO SE ME ENTREGO GASTO/SE VERIFICAN Y PAGA BRINCO | W41: PREGUNTAR A EMMANUEL
A42: =WEEKNUM(B42) -> 2 | B42: 46028 | C42: =TEXT(B42,"MMMM") -> enero | D42: NO | E42: DESPENSA AZCONA | F42: LECHES | G42: 1 | H42: PIEZAS | I42: 228 | J42: 228 | K42: 0 | L42: 228 | M42: 0 | N42: N/A | O42: ADMINISTRACIÓN | P42: ASHC | Q42: SANTIAGO | R42: TC PLATA ASHC | S42: OXXO | T42: N/A | U42: LECHES PARA ROSCA DE REYES | V42: NO SE ME ENTREGO GASTO
A43: =WEEKNUM(B43) -> 2 | B43: 46028 | C43: =TEXT(B43,"MMMM") -> enero | D43: NO | E43: TRASLADO | F43: GASOLINA | G43: 1 | H43: SERVICIO | I43: 250 | J43: 250 | K43: 0 | L43: 250 | M43: 0 | O43: OPERACIÓN | P43: ASHC | Q43: ISMAEL | R43: TC DIDI ASHC | S43: PEMEX | T43: - | U43: SE FACTURA A NOMBRE DE YULIANA | V43: NO SE ME ENTREGO GASTO/FALTA VERIFICAR VEHÍCULO
A44: =WEEKNUM(B44) -> 2 | B44: 46028 | C44: =TEXT(B44,"MMMM") -> enero | D44: NO | E44: GPS | F44: LINEA DE VOLTAJE - RADIO | G44: 1 | H44: PIEZAS | I44: 200 | J44: 200 | K44: 0 | L44: 200 | M44: 0 | N44: JESUS AURELIO NUNGARAY CASTILLO | O44: MARCH|2021|ROJO|NZU5163 | P44: ASHC | Q44: ISMAEL | S44: JUAN LOZADA | U44: SE COBRA A CONDUCTOR | V44: NO SE ME ENTREGO GASTO
A45: =WEEKNUM(B45) -> 2 | B45: 46028 | C45: =TEXT(B45,"MMMM") -> enero | D45: NO | E45: MTTO | F45: HORQUILLA INFERIOR IZQUIERDA | G45: 1 | H45: PIEZAS | I45: 360.45 | J45: 360.45 | K45: 0 | L45: 360.45 | M45: 0 | N45: FIDEL ALEJANDRO SANCHEZ VERGARA | O45: VERSA|2023|PLATA|NCT814A | P45: ASHC | Q45: ISMAEL | R45: TC DIDI ASHC | S45: REFACCIONES VERTIZ | T45: GENERICO | V45: NO SE ME ENTREGO GASTO
A46: =WEEKNUM(B46) -> 2 | B46: 46028 | C46: =TEXT(B46,"MMMM") -> enero | D46: NO | E46: MTTO | F46: SOPORTE DE MOTOR TRASERO | G46: 1 | H46: PIEZAS | I46: 507.76 | J46: 507.76 | K46: 0 | L46: 507.76 | M46: 0 | N46: FIDEL ALEJANDRO SANCHEZ VERGARA | O46: VERSA|2023|PLATA|NCT814A | P46: ASHC | Q46: ISMAEL | R46: TC DIDI ASHC | S46: REFACCIONES VERTIZ | T46: EAGLEBHP | V46: NO SE ME ENTREGO GASTO
A47: =WEEKNUM(B47) -> 2 | B47: 46028 | C47: =TEXT(B47,"MMMM") -> enero | D47: NO | E47: DERECHOS | F47: VERIFICACIÓN | G47: 1 | H47: PIEZAS | I47: 588 | J47: 588 | K47: 0 | L47: 588 | M47: 0 | N47: RICARDO HERNANDEZ ARIAS | O47: VERSA|2022|GRIS|NES596C | P47: ASHC | Q47: ALEJANDRA | R47: TC DIDI ASHC | S47: GOBIERNO EDOMEX | T47: - | V47: NO SE ME ENTREGO GASTO
A48: =WEEKNUM(B48) -> 2 | B48: 46028 | C48: =TEXT(B48,"MMMM") -> enero | D48: NO | E48: PENDIENTE | F48: PENDIENTE | G48: 1 | H48: SERVICIO | I48: 150 | J48: 150 | K48: 0 | L48: 150 | M48: 0 | O48: OPERACIÓN | P48: ASHC | R48: TC DIDI ASHC | U48: PENDIENTE REVISIÓN | V48: NO SE ME ENTREGO GASTO
A49: =WEEKNUM(B49) -> 2 | B49: 46028 | C49: =TEXT(B49,"MMMM") -> enero | D49: NO | E49: PENDIENTE | F49: FOCOS LED | G49: 1 | H49: PIEZAS | I49: 285 | J49: 285 | K49: 0 | L49: 285 | M49: 0 | O49: OPERACIÓN | P49: DISP | Q49: ISMAEL | R49: TC PARA REEMB | U49: PENDIENTE REVISIÓN | V49: NO SE ME ENTREGO GASTO
A50: =WEEKNUM(B50) -> 2 | B50: 46029 | C50: =TEXT(B50,"MMMM") -> enero | D50: NO | E50: MTTO | F50: TESTIGOS | G50: 1 | H50: PAQUETE | I50: 680 | J50: 680 | K50: 108.8 | L50: 788.8 | M50: 0 | N50: FRANCISCO GOMEZ URQUIZA SILVA | O50: VERSA|2023|PLATA|NCT814A | P50: ASHC | Q50: ISMAEL | R50: TRANSFERENCIA | S50: AUTOMOTRIZ GARROM | T50: N/A | U50: VERIFICAR TRANSFERENCIA | X50: M1/1
A51: =WEEKNUM(B51) -> 2 | B51: 46029 | C51: =TEXT(B51,"MMMM") -> enero | D51: NO | E51: MTTO | F51: ACEITE/FILTROS | G51: 1 | H51: SERVICIO | I51: 1168.53 | J51: 1168.53 | K51: 0 | L51: 1168.53 | M51: 0 | O51: OPERACIÓN | P51: ASHC | Q51: ISMAEL | R51: TC DIDI ASHC | S51: REFACCIONES VERTIZ | U51: PENDIENTE REVISIÓN | V51: NO SE ME ENTREGO GASTO
A52: =WEEKNUM(B52) -> 2 | B52: 46029 | C52: =TEXT(B52,"MMMM") -> enero | D52: NO | E52: MTTO | F52: BUJIAS/ACEITE/FILTROS | G52: 1 | H52: PIEZAS | I52: 1206.37 | J52: 1206.37 | K52: 0 | L52: 1206.37 | M52: 0 | O52: OPERACIÓN | P52: ASHC | Q52: ISMAEL | R52: TC PLATA ASHC | S52: REFACCIONES VERTIZ | U52: PENDIENTE REVISIÓN | V52: NO SE ME ENTREGO GASTO
A53: =WEEKNUM(B53) -> 2 | B53: 46029 | C53: =TEXT(B53,"MMMM") -> enero | D53: NO | E53: MTTO | F53: TERMINALES VENTO | G53: 1 | H53: PIEZAS | I53: 223.28 | J53: 223.28 | K53: 0 | L53: 223.28 | M53: 0 | O53: OPERACIÓN | P53: DISP | Q53: ISMAEL | S53: REFACCIONES VERTIZ | U53: PENDIENTE REVISIÓN | V53: NO SE ME ENTREGO GASTO
A54: =WEEKNUM(B54) -> 2 | B54: 46029 | C54: =TEXT(B54,"MMMM") -> enero | D54: NO | E54: MTTO | F54: AMORTIGUADORES | G54: 1 | H54: PIEZAS | I54: 3973.24 | J54: 3973.24 | K54: 0 | L54: 3973.24 | M54: 0 | O54: OPERACIÓN | P54: DISP | Q54: ISMAEL | S54: DAR PORTALES | U54: PENDIENTE REVISIÓN | V54: NO SE ME ENTREGO GASTO
A55: =WEEKNUM(B55) -> 2 | B55: 46029 | C55: =TEXT(B55,"MMMM") -> enero | D55: NO | E55: MTTO | F55: BIRLOS | G55: 1 | H55: PIEZAS | I55: 105 | J55: 105 | K55: 0 | L55: 105 | M55: 0 | O55: OPERACIÓN | P55: DISP | Q55: ISMAEL | S55: CORMERCIALIZADORA DE TORNILLOS Y BIRLOS | U55: PENDIENTE REVISIÓN | V55: NO SE ME ENTREGO GASTO
A56: =WEEKNUM(B56) -> 2 | B56: 46030 | C56: =TEXT(B56,"MMMM") -> enero | D56: NO | E56: TRASLADO | F56: GASOLINA | G56: 1 | H56: SERVICIO | I56: 250 | J56: 250 | K56: 0 | L56: 250 | M56: 0 | N56: S/C | O56: AVEOH|2026|GRIS|NEZ118C | P56: IVETT | Q56: ISMAEL | R56: TC DIDI ASHC | S56: PEMEX | T56: - | V56: NO SE ME ENTREGO GASTO
A57: =WEEKNUM(B57) -> 2 | B57: 46030 | C57: =TEXT(B57,"MMMM") -> enero | D57: NO | E57: TRASLADO | F57: GASOLINA | G57: 1 | H57: SERVICIO | I57: 844.47 | J57: 844.47 | K57: 0 | L57: 844.47 | M57: 0 | N57: JORGE IVAN PALOMINO PEREZ FIGUEROA | O57: AVEOH|2026|GRIS|NEZ115C | P57: IVETT | Q57: ISMAEL | R57: TC DIDI ASHC | S57: PEMEX | T57: - | V57: NO SE ME ENTREGO GASTO
A58: =WEEKNUM(B58) -> 2 | B58: 46030 | C58: =TEXT(B58,"MMMM") -> enero | D58: NO | E58: DESPENSA AZCONA | F58: POLLOS | G58: 1 | H58: SERVICIO | I58: 502 | J58: 502 | K58: 0 | L58: 502 | M58: 0 | N58: N/A | O58: ADMINISTRACIÓN | P58: ASHC | Q58: SANTIAGO | R58: TC DIDI ASHC | S58: SANTO GALLO | T58: - | V58: NO SE ME ENTREGO GASTO
A59: =WEEKNUM(B59) -> 2 | B59: 46030 | C59: =TEXT(B59,"MMMM") -> enero | D59: NO | E59: DESPENSA AZCONA | F59: PAN | G59: 1 | H59: SERVICIO | I59: 45 | J59: 45 | K59: 0 | L59: 45 | M59: 0 | N59: N/A | O59: ADMINISTRACIÓN | P59: ASHC | Q59: SANTIAGO | R59: TC DIDI ASHC | S59: LA ESPERANZA | T59: - | V59: NO SE ME ENTREGO GASTO
A60: =WEEKNUM(B60) -> 2 | B60: 46030 | C60: =TEXT(B60,"MMMM") -> enero | D60: NO | E60: MTTO | F60: AMORTIGUADORES | G60: 1 | H60: PIEZAS | I60: 2715.44 | J60: 2715.44 | K60: 0 | L60: 2715.44 | M60: 0 | O60: OPERACIÓN | P60: DISP | Q60: ISMAEL | S60: DAR PORTALES | U60: PENDIENTE REVISIÓN | V60: NO SE ME ENTREGO GASTO
A61: =WEEKNUM(B61) -> 2 | B61: 46030 | C61: =TEXT(B61,"MMMM") -> enero | D61: NO | E61: MTTO | F61: ALINEACION | G61: 1 | H61: SERVICIO | I61: 400 | J61: 400 | K61: 0 | L61: 400 | M61: 0 | O61: OPERACIÓN | P61: DISP | Q61: ISMAEL | S61: LLANTERA TREJO | U61: PENDIENTE REVISIÓN | V61: NO SE ME ENTREGO GASTO
A62: =WEEKNUM(B62) -> 2 | B62: 46030 | C62: =TEXT(B62,"MMMM") -> enero | D62: NO | E62: MTTO | F62: HORQUILLA INFERIOR | G62: 1 | H62: PIEZAS | I62: 848.94 | J62: 848.94 | K62: 0 | L62: 848.94 | M62: 0 | N62: N/A | O62: OPERACIÓN | P62: ASHC | Q62: PENDIENTE | R62: TC PARA REEMB | S62: SUSPENSIONES Y DIRECCION | T62: N/A | U62: NO SE FACTURA, FUERA DE TIEMPO | W62: N/A | X62: M1/2
A63: =WEEKNUM(B63) -> 2 | B63: 46030 | C63: =TEXT(B63,"MMMM") -> enero | D63: NO | E63: MTTO | F63: HORQUILLA INFERIOR (L) | G63: 1 | H63: PIEZAS | I63: 826.27 | J63: 826.27 | K63: 0 | L63: 826.27 | M63: 0 | N63: N/A | O63: OPERACIÓN | P63: ASHC | Q63: PENDIENTE | R63: TC PARA REEMB | S63: SUSPENSIONES Y DIRECCION | T63: N/A | U63: NO SE FACTURA, FUERA DE TIEMPO | V63: TOTAL TICKET $1,675.21 | W63: N/A | X63: M1/2
A64: =WEEKNUM(B64) -> 2 | B64: 46030 | C64: =TEXT(B64,"MMMM") -> enero | D64: NO | E64: MTTO | F64: CAMBIO LLANTA | G64: 4 | H64: PIEZAS | I64: 117.5 | J64: 470 | K64: 0 | L64: 470 | M64: 0 | N64: KEVIN ALEXIS MERLOS CORTES | O64: VENTO|2020|GRIS|R66BER | P64: ASHC | Q64: ISMAEL | R64: TC PLATA ASHC | S64: VULCANIZADORA LOS PITS | T64: N/A | W64: N/A | X64: M1/3
A65: =WEEKNUM(B65) -> 2 | B65: 46031 | C65: =TEXT(B65,"MMMM") -> enero | D65: NO | E65: MTTO | F65: BALATAS DELANTERAS | G65: 1 | H65: JUEGO | I65: 466.72 | J65: 466.72 | K65: 74.6752 | L65: 541.3952 | M65: 0 | N65: N/A | O65: MARCH|2020|GRIS|NEJ984C | P65: BYER | Q65: ISMAEL | R65: TC PLATA ASHC | S65: REFACCIONES VERTIZ | T65: RAYBESTAS | U65: - | X65: M1/4
A66: =WEEKNUM(B66) -> 2 | B66: 46031 | C66: =TEXT(B66,"MMMM") -> enero | D66: NO | E66: MTTO | F66: BALATAS TRASERAS | G66: 1 | H66: JUEGO | I66: 236.18 | J66: 236.18 | K66: 37.7888 | L66: 273.9688 | M66: 0 | N66: N/A | O66: MARCH|2020|GRIS|NEJ984C | P66: BYER | Q66: ISMAEL | R66: TC PLATA ASHC | S66: REFACCIONES VERTIZ | T66: FARET | U66: - | V66: TOTAL TICKET $815.36 | X66: M1/4
A67: =WEEKNUM(B67) -> 2 | B67: 46031 | C67: =TEXT(B67,"MMMM") -> enero | D67: NO | E67: MTTO | F67: BUJIA | G67: 4 | H67: PIEZAS | I67: 108.38 | J67: 433.52 | K67: 69.3632 | L67: 502.8832 | M67: 0 | N67: N/A | O67: MARCH|2020|GRIS|NEJ984C | P67: BYER | Q67: ISMAEL | R67: TC PLATA ASHC | S67: REFACCIONES VERTIZ | T67: NGK | X67: M1/5
A68: =WEEKNUM(B68) -> 2 | B68: 46031 | C68: =TEXT(B68,"MMMM") -> enero | D68: NO | E68: MTTO | F68: BALATAS | G68: 2 | H68: JUEGO | I68: 181.8 | J68: 363.6 | K68: 58.176 | L68: 421.776 | M68: 0 | N68: N/A | O68: MARCH|2020|GRIS|NEJ984C | P68: BYER | Q68: ISMAEL | R68: TC PLATA ASHC | S68: REFACCIONES VERTIZ | T68: TKM | X68: M1/5
A69: =WEEKNUM(B69) -> 2 | B69: 46031 | C69: =TEXT(B69,"MMMM") -> enero | D69: NO | E69: MTTO | F69: FILTROS AIRE | G69: 1 | H69: PIEZAS | I69: 35.7 | J69: 35.7 | K69: 5.712 | L69: 41.412 | M69: 0 | N69: N/A | O69: MARCH|2020|GRIS|NEJ984C | P69: BYER | Q69: ISMAEL | R69: TC PLATA ASHC | S69: REFACCIONES VERTIZ | T69: N/A | X69: M1/5
A70: =WEEKNUM(B70) -> 2 | B70: 46031 | C70: =TEXT(B70,"MMMM") -> enero | D70: NO | E70: MTTO | F70: FILTRO ACEITE | G70: 1 | H70: PIEZAS | I70: 48.09 | J70: 48.09 | K70: 7.6944 | L70: 55.7844 | M70: 0 | N70: S/C | O70: MARCH|2020|GRIS|NEJ984C | P70: BYER | Q70: ISMAEL | R70: TC PLATA ASHC | S70: REFACCIONES VERTIZ | T70: WIX | X70: M1/5
A71: =WEEKNUM(B71) -> 2 | B71: 46031 | C71: =TEXT(B71,"MMMM") -> enero | D71: NO | E71: MTTO | F71: ACEITE 5W30 | G71: 1 | H71: PIEZAS | I71: 900.25 | J71: 900.25 | K71: 144.04 | L71: 1044.29 | M71: 0 | N71: S/C | O71: MARCH|2020|GRIS|NEJ984C | P71: BYER | Q71: ISMAEL | R71: TC PLATA ASHC | S71: REFACCIONES VERTIZ | T71: MOBIL | V71: TOTAL TICKET $2,066.15 | X71: M1/5
A72: =WEEKNUM(B72) -> 2 | B72: 46031 | C72: =TEXT(B72,"MMMM") -> enero | D72: NO | E72: MTTO | F72: METRO MANGUERA | G72: 1 | H72: PIEZAS | I72: 100 | J72: 100 | K72: 0 | L72: 100 | M72: 0 | N72: N/A | O72: MARCH|2020|GRIS|NEJ984C | P72: BYER | Q72: ISMAEL | R72: TC DIDI ASHC | S72: AUTOP MANG Y CONEXIONE | T72: N/A | X72: M1/6
A73: =WEEKNUM(B73) -> 2 | B73: 46031 | C73: =TEXT(B73,"MMMM") -> enero | D73: NO | E73: MTTO | F73: BALATAS | G73: 1 | H73: JUEGO | I73: 474.1379 | J73: 474.1379 | K73: 75.862064 | L73: 549.99996 | M73: 0 | N73: VICTOR HUGO RUIZ CASTILLO | O73: VERSA|2021|BLANCO|MEE228C | P73: ASHC | Q73: ISMAEL | R73: TC PARA REEMB | S73: UNIVBRAKES | T73: WAGNER | U73: REEMBOLSO ISMAEL/pagado 31-01-26 | X73: M1/7
A74: =WEEKNUM(B74) -> 2 | B74: 46031 | C74: =TEXT(B74,"MMMM") -> enero | D74: NO | E74: MTTO | F74: HORQUILLAS INFERIOR (L) | G74: 1 | H74: PIEZAS | I74: 689.35 | J74: 689.35 | K74: 110.296 | L74: 799.646 | M74: 0 | N74: S/C | O74: MARCH|2020|GRIS|NEJ984C | P74: BYER | Q74: ISMAEL | R74: TC DIDI ASHC | S74: REFACCIONARIA DAR | T74: N/A | X74: M1/8
A75: =WEEKNUM(B75) -> 2 | B75: 46031 | C75: =TEXT(B75,"MMMM") -> enero | D75: NO | E75: MTTO | F75: HORQUILLAS INFERIOR (R) | G75: 1 | H75: PIEZAS | I75: 689.35 | J75: 689.35 | K75: 110.296 | L75: 799.646 | M75: 0 | N75: S/C | O75: MARCH|2020|GRIS|NEJ984C | P75: BYER | Q75: ISMAEL | R75: TC DIDI ASHC | S75: REFACCIONARIA DAR | T75: N/A | V75: TOTAL TICKET $1,599.29 | X75: M1/8
A76: =WEEKNUM(B76) -> 2 | B76: 46031 | C76: =TEXT(B76,"MMMM") -> enero | D76: NO | E76: MTTO | F76: SILICON NEGRO | G76: 1 | H76: PIEZAS | I76: 100 | J76: 100 | K76: 0 | L76: 100 | M76: 0 | N76: N/A | O76: MARCH|2020|GRIS|NEJ984C | P76: BYER | Q76: ISMAEL | R76: EFECTIVO | S76: REFACCIONARIA MOBU | T76: HELLA | U76: REEMBOLSO ISMAEL/pagado 31-01-26 | X76: M1/9
A77: =WEEKNUM(B77) -> 2 | B77: 46031 | C77: =TEXT(B77,"MMMM") -> enero | D77: NO | E77: MTTO | F77: CUERPO DE ACELERACION | G77: 1 | H77: PIEZAS | I77: 1400 | J77: 1400 | K77: 224 | L77: 1624 | M77: 0 | N77: S/C | O77: MARCH|2020|GRIS|NEJ984C | P77: BYER | Q77: ISMAEL | R77: TRANSFERENCIA | S77: AUTO PARTES PEUGEOT | T77: N/A | U77: TRANSFIERE BYER | X77: M1/10
A78: =WEEKNUM(B78) -> 2 | B78: 46031 | C78: =TEXT(B78,"MMMM") -> enero | D78: NO | E78: MTTO | F78: CAMBIO BALEROS TRASEROS | G78: 2 | H78: PIEZAS | I78: 150 | J78: 300 | K78: 0 | L78: 300 | M78: 0 | N78: S/C | O78: MARCH|2020|GRIS|NEJ984C | P78: BYER | Q78: ISMAEL | R78: TRANSFERENCIA | S78: MANTENIMIENTO INDUSTRIAL | T78: N/A | U78: TRANSFIERE BYER | X78: M1/11
A79: =WEEKNUM(B79) -> 2 | B79: 46031 | C79: =TEXT(B79,"MMMM") -> enero | D79: NO | E79: MTTO | F79: REPARACION TAPA CARTER | G79: 1 | H79: PIEZAS | I79: 150 | J79: 150 | K79: 0 | L79: 150 | M79: 0 | N79: S/C | O79: MARCH|2020|GRIS|NEJ984C | P79: BYER | Q79: ISMAEL | R79: TRANSFERENCIA | S79: MANTENIMIENTO INDUSTRIAL | T79: N/A | U79: TRANSFIERE BYER | V79: TOTAL $450 | X79: M1/11
A80: =WEEKNUM(B80) -> 2 | B80: 46031 | C80: =TEXT(B80,"MMMM") -> enero | D80: NO | E80: MTTO | F80: BATERIA | G80: 1 | H80: PIEZAS | I80: 2248.27 | J80: 2248.27 | K80: 359.7232 | L80: 2607.9932 | M80: 0 | N80: KEVIN ALEXIS MERLOS CORTES | O80: VENTO|2020|GRIS|R66BER | P80: ASHC | Q80: ISMAEL | R80: TC DIDI ASHC | S80: RADIADORES UNIDOS (RUNSA) | T80: AMERICA | X80: M1/12
A81: =WEEKNUM(B81) -> 2 | B81: 46031 | C81: =TEXT(B81,"MMMM") -> enero | D81: NO | E81: MTTO | F81: ANTISULFANTE | G81: 1 | H81: PIEZAS | I81: 3.3 | J81: 3.3 | K81: 0.528 | L81: 3.828 | M81: 0 | N81: KEVIN ALEXIS MERLOS CORTES | O81: VENTO|2020|GRIS|R66BER | P81: ASHC | Q81: ISMAEL | R81: TC DIDI ASHC | S81: RADIADORES UNIDOS (RUNSA) | T81: AMERICA | V81: TOTAL TICKET $2,611.82 | X81: M1/12
A82: =WEEKNUM(B82) -> 2 | B82: 46031 | C82: =TEXT(B82,"MMMM") -> enero | D82: NO | E82: MTTO | F82: PENDIENTE | G82: 1 | H82: SERVICIO | I82: 3875 | J82: 3875 | K82: 0 | L82: 3875 | M82: 0 | N82: N/A | O82: OPERACIÓN | P82: ASHC | Q82: PENDIENTE | R82: TC DIDI ASHC | S82: REFACCIONARIA PUEBLA | U82: SOLO SE ENTREGO EL TICKET DE PAGO | V82: NO SE ME ENTREGO GASTO | W82: N/A
A83: =WEEKNUM(B83) -> 2 | B83: 46032 | C83: =TEXT(B83,"MMMM") -> enero | D83: NO | E83: TRASLADO | F83: SANTIAGO PIDIO UBER PARA ROSA DE GPS A LA OFICINA | G83: 1 | H83: PAQUETE | I83: 182.08 | J83: 182.08 | K83: 0 | L83: 182.08 | M83: 0 | N83: N/A | O83: OPERACIÓN | P83: DISP | Q83: SANTIAGO | R83: TC PARA REEMB | S83: UBER | T83: UBER X | U83: PENDIENTE REEMBOLSO NAYE | W83: N/A
A84: =WEEKNUM(B84) -> 2 | B84: 46032 | C84: =TEXT(B84,"MMMM") -> enero | D84: NO | E84: TRASLADO | F84: GASOLINA | G84: 9.982 | H84: LITROS | I84: 20.5948 | J84: 205.57729 | K84: 32.892367 | L84: 238.46966 | M84: 0 | N84: N/A | O84: MARCH|2020|GRIS|NEJ984C | P84: BYER | Q84: ISMAEL | R84: TC PLATA ASHC | S84: SHELL SERVICE | T84: SHELL SUP | X84: M1/13
A85: =WEEKNUM(B85) -> 2 | B85: 46032 | C85: =TEXT(B85,"MMMM") -> enero | D85: NO | E85: TRASLADO | F85: GASOLINA | G85: 10.42 | H85: LITROS | I85: 20.683 | J85: 215.51686 | K85: 34.482698 | L85: 249.99956 | M85: 0 | N85: JUAN PABLO COLIN HERMENEGILDO | O85: AVEOH|2026|GRIS|NEZ110C | P85: IVETT | Q85: ISMAEL | R85: TC DIDI ASHC | S85: GOGAS | T85: MAGNA | X85: M1/14
A86: =WEEKNUM(B86) -> 2 | B86: 46032 | C86: =TEXT(B86,"MMMM") -> enero | D86: NO | E86: TRASLADO | F86: GASOLINA PARA EMERGENCIA | G86: 12.04 | H86: LITROS | I86: 20.5948 | J86: 247.96139 | K86: 39.673823 | L86: 287.63521 | M86: 0 | N86: N/A | O86: OPERACIÓN | P86: ASHC | Q86: ISMAEL | R86: TC PLATA ASHC | S86: G500 | T86: G SUPER | X86: M1/15
A87: =WEEKNUM(B87) -> 2 | B87: 46032 | C87: =TEXT(B87,"MMMM") -> enero | D87: NO | E87: MTTO | F87: AMORTIGUADOR COFRE | G87: 2 | H87: PIEZAS | I87: 258.6206 | J87: 517.2412 | K87: 82.758592 | L87: 599.99979 | M87: 0 | N87: S/C | O87: MARCH|2020|GRIS|NEJ984C | P87: BYER | Q87: ISMAEL | R87: TC PLATA ASHC | S87: SUSPENSIONES PORTALES | T87: SAFETY | X87: M1/16
A88: =WEEKNUM(B88) -> 2 | B88: 46032 | C88: =TEXT(B88,"MMMM") -> enero | D88: NO | E88: MTTO | F88: MOTOR CON VARILLAJE | G88: 1 | H88: PIEZAS | I88: 1680 | J88: 1680 | K88: 0 | L88: 1680 | M88: 0 | N88: N/A | O88: VENTO|2020|GRIS|NES586C | P88: ASHC | Q88: ISMAEL | R88: EFECTIVO | S88: KSA VEGA | U88: REEMBOLSO ISMAEL/pagado 31-01-26 | X88: M1/17
A89: =WEEKNUM(B89) -> 2 | B89: 46032 | C89: =TEXT(B89,"MMMM") -> enero | D89: NO | E89: MTTO | F89: SUSPERIA 175/65 R14 | G89: 4 | H89: PIEZAS | I89: 839.13 | J89: 3356.52 | K89: 537.0432 | L89: 3893.5632 | M89: 0 | N89: N/A | O89: MARCH|2020|GRIS|NEJ984C | P89: BYER | Q89: ISMAEL | R89: TC DIDI ASHC | S89: METZ | T89: N/A | U89: Garantia 9 meses | W89: FACTURADO | X89: M1/18
A90: =WEEKNUM(B90) -> 2 | B90: 46032 | C90: =TEXT(B90,"MMMM") -> enero | D90: NO | E90: DERECHOS | F90: VERIFICACIÓN | G90: 1 | H90: SERVICIO | I90: 1154 | J90: 1154 | K90: 0 | L90: 1154 | M90: 0 | N90: JORGE IVAN PALOMINO PEREZ FIGUEROA | O90: AVEOH|2026|GRIS|NEZ115C | P90: IVETT | Q90: ALEJANDRA | R90: TC DIDI ASHC | S90: GOBIERNO EDOMEX | U90: PENDIENTE FACTURACION
A91: =WEEKNUM(B91) -> 2 | B91: 46032 | C91: =TEXT(B91,"MMMM") -> enero | D91: NO | E91: DERECHOS | F91: VERIFICACIÓN | G91: 1 | H91: PIEZAS | I91: 1154 | J91: 1154 | K91: 0 | L91: 1154 | M91: 0 | N91: JOEL RAUL PEREA PEÑA | O91: AVEO|2019|BLANCO|NBS225A | P91: ASHC | Q91: ALEJANDRA | R91: TC DIDI ASHC | S91: GOBIERNO EDOMEX | U91: PENDIENTE FACTURACION
A92: =WEEKNUM(B92) -> 3 | B92: 46034 | C92: =TEXT(B92,"MMMM") -> enero | D92: NO | E92: TRASLADO | F92: UBER PARA GABO ENTREGO CARRO A PICACHU TRASLADO A OFICINA | G92: 1 | H92: PAQUETE | I92: 189.93 | J92: 189.93 | K92: 0 | L92: 189.93 | M92: 0 | N92: N/A | O92: OPERACIÓN | P92: DISP | Q92: GABO | R92: TC PARA REEMB | S92: UBER | T92: UBER X | U92: PENDIENTE REEMBOLSO NAYE | W92: N/A
A93: =WEEKNUM(B93) -> 3 | B93: 46034 | C93: =TEXT(B93,"MMMM") -> enero | D93: NO | E93: TRASLADO | F93: UBER PARA EMMANUEL Y ROSA FUERON A DEJAR CARROS AL AEROPUETO CON LORENZO HOJALATERO | G93: 1 | H93: PAQUETE | I93: 157.45 | J93: 157.45 | K93: 0 | L93: 157.45 | M93: 0 | N93: N/A | O93: OPERACIÓN | P93: DISP | Q93: GABO | R93: TC PARA REEMB | S93: UBER | T93: UBER X | U93: PENDIENTE REEMBOLSO NAYE | W93: N/A
A94: 3 | B94: 46034 | C94: =TEXT(B94,"MMMM") -> enero | D94: NO | E94: DERECHOS | F94: VERIFICACIÓN | G94: 1 | H94: SERVICIO | I94: 740 | J94: 740 | K94: 0 | L94: 740 | M94: 0 | N94: DIEGO DIAZ BARRIGA GARCIA | O94: VENTO|2020|GRIS|R66BER | P94: ASHC | Q94: ALEJANDRA | R94: TC PARA REEMB | S94: ARTE AUTOMOTRIZ | T94: N/A | U94: SE REGISTRA TICKET/SE PREGUNTARÁ A ROSA COMO SE GESTIONE LA VERIFICACIÓN | X94: M1/19
A95: =WEEKNUM(B95) -> 3 | B95: 46034 | C95: =TEXT(B95,"MMMM") -> enero | D95: NO | E95: MTTO | F95: FOCO H4 55W/60W | G95: 1 | H95: PIEZAS | I95: 54 | J95: 54 | K95: 0 | L95: 54 | M95: 0 | N95: TOMAS ARIAS ESPINOSA | O95: AVEO|2019|BLANCO|NBS225A | P95: ASHC | Q95: FERNANDO | R95: TC DIDI ASHC | S95: AUTOPARTES FUJIYAMA | T95: HELLA | X95: M1/20
A96: =WEEKNUM(B96) -> 3 | B96: 46034 | C96: =TEXT(B96,"MMMM") -> enero | D96: NO | E96: MTTO | F96: MONTAJE LLANTA | G96: 1 | H96: PIEZAS | I96: 75 | J96: 75 | K96: 0 | L96: 75 | M96: 0 | N96: DAVID ROMERO JAIME | O96: BEAT|2020|GRIS|NFN014B | P96: BYER | Q96: NICO | R96: EFECTIVO | S96: N/A | T96: N/A | U96: CAJA CHICA | V96: CONFIRMAR COMERCIO | X96: M1/21
A97: =WEEKNUM(B97) -> 3 | B97: 46034 | C97: =TEXT(B97,"MMMM") -> enero | D97: NO | E97: MTTO | F97: BIRLO 14X50 | G97: 2 | H97: PIEZAS | I97: 40 | J97: 80 | K97: 0 | L97: 80 | M97: 0 | N97: DIEGO DIAZ BARRIGA GARCIA | O97: VENTO|2020|GRIS|R66BER | P97: ASHC | Q97: FERNANDO | R97: EFECTIVO | S97: CORMERCIALIZADORA DE TORNILLOS Y BIRLOS | T97: N/A | U97: CAJA CHICA | X97: M1/22
A98: =WEEKNUM(B98) -> 3 | B98: 46034 | C98: =TEXT(B98,"MMMM") -> enero | D98: NO | E98: DERECHOS | F98: VERIFICACIÓN | G98: 1 | H98: SERVICIO | I98: 588 | J98: 588 | K98: 0 | L98: 588 | M98: 0 | N98: TOMAS ARIAS ESPINOSA | O98: AVEO|2019|BLANCO|NBS225A | P98: ASHC | Q98: ALEJANDRA | R98: TC DIDI ASHC | S98: GOBIERNO EDOMEX | T98: N/A
A99: =WEEKNUM(B99) -> 3 | B99: 46034 | C99: =TEXT(B99,"MMMM") -> enero | D99: NO | E99: DERECHOS | F99: VERIFICACIÓN | G99: 1 | H99: SERVICIO | I99: 610 | J99: 610 | K99: 0 | L99: 610 | M99: 0 | N99: N/A | O99: AVEOH|2026|GRIS|NEZ103C | P99: IVETT | Q99: ALEJANDRA | R99: EFECTIVO | S99: OPERADORA VIVA | T99: N/A | V99: NO ENTREGARON TICKET DE PAGO TERMINAL
A100: =WEEKNUM(B100) -> 3 | B100: 46035 | C100: =TEXT(B100,"MMMM") -> enero | D100: NO | E100: MTTO | F100: REVISION VELOCIMETRO | G100: 1 | H100: PIEZAS | I100: 350 | J100: 350 | K100: 0 | L100: 350 | M100: 0 | N100: DAVID ROMERO JAIME | O100: BEAT|2020|GRIS|NFN014B | P100: BYER | Q100: NICO | R100: EFECTIVO | S100: VELOCIMETROS DIGITALES | T100: N/A | U100: PAGO ASHC | X100: M1/23
...
